Workbook

Sheet Instructions
A1: SupplierPulse - Supplier Performance & Procurement Analytics
A2: Procurement analysis workbook - author: Harjot Sandhu
A4: What this workbook does
A5: Evaluates supplier reliability, purchasing spend and procurement risk, and turns them into a prioritised action list.
A6: Two data sources - never mixed
A7: OBSERVED: City of Austin purchase-order lines, FY2022-FY2026 (1 Oct 2021 - 30 Sep 2026), from data.austintexas.gov. Supports spend, concentration, agreement coverage and like-for-like price analysis. It has no delivery dates.
A8: SYNTHETIC: a deterministic demonstration dataset of 14 anonymous suppliers (SUP-01 ... SUP-14), purchase orders and goods receipts. Used only to demonstrate delivery, quality, scorecard and scenario methods. Not real suppliers or real performance.
A9: Header colours
A10: Navy header = data loaded from the Python pipeline (values). Teal header = live Excel formula.
A11: Sheets
A12: Assumptions | B12: Inputs and thresholds used by every formula (yellow cells).
A13: Syn_Lines | B13: Synthetic PO lines (Excel table tblLines): loaded line facts + formula columns for due, on-time, in-full, OTIF, days late, lead time.
A14: Syn_Suppliers | B14: Synthetic supplier master and the designed behaviour of each supplier.
A15: Supplier_Summary | B15: Per-supplier delivery, quality, spend and PPV metrics (COUNTIFS / SUMIFS / AVERAGEIFS).
A16: Dependency | B16: Supplier spend share by category, main category and dependency tier.
A17: Scorecard | B17: Weighted 0-100 performance score, evidence status, competition rank, tier and action quadrant (XLOOKUP for names).
A18: Delivery_Trend | B18: Monthly OTIF by promised month.
A19: Exceptions | B19: Live supplier exception flags S1-S8 and the overdue-line list.
A20: Scenario | B20: A: volume reallocation model with inputs and sensitivity; B: OTIF-target scenario; C: observed price harmonisation.
A21: Austin_Vendors | B21: Observed vendor spend, share, cumulative share, rank and Pareto class (top 150 + aggregate).
A22: Austin_Categories | B22: Observed category spend, top-vendor share, HHI and dependency flags.
A23: Austin_Families | B23: Observed spend by family and fiscal year.
... A27: Validation | B27: Excel formulas reconciled against the Python pipeline.
A29: Testing note
A30: Formulas calculate when the file is opened (full recalculation on load). This workbook was generated with openpyxl and verified by recalculating it with the Python 'formulas' engine and comparing results with pandas and SQL; it has not been manually opened in Microsoft Excel by the author's build process.
A32: Modelled values (scenarios, price opportunity) are estimates under stated assumptions, not realised savings.

Sheet Assumptions
A1: Assumptions and thresholds
A2: Yellow cells are inputs. Every formula in the workbook reads its thresholds from this sheet.
B4: Assumption | C4: Value | D4: Used by / note
B5: Reporting (synthetic delivery data)
B6: As-of (reporting) date | C6: 46295 | D6: Lines promised after this date are not yet due
B7: On-time grace days | C7: 0 | D7: Days after promised date still counted on time
B8: In-full tolerance | C8: 0 | D8: 0% = full ordered quantity required
B9: Scorecard weights (must total 100%)
B10: Weight: OTIF | C10: 0.4
B11: Weight: quality (reject rate) | C11: 0.25
B12: Weight: lead-time consistency | C12: 0.2
B13: Weight: lateness (avg days late) | C13: 0.15
B14: Scorecard scaling (target = 100 points, poor = 0 points)
B15: OTIF target | C15: 0.95
B16: OTIF poor | C16: 0.7
B17: Reject rate target | C17: 0.005
B18: Reject rate poor | C18: 0.05
B19: Lead-time SD target (days) | C19: 2
B20: Lead-time SD poor (days) | C20: 7
B21: Avg days late target | C21: 0
B22: Avg days late poor | C22: 5
B23: Evidence and tiers
B24: Due lines needed to rank | C24: 30
B25: Due lines needed for a provisional score | C25: 10
B26: Completed lines needed for lead-time variability | C26: 20
B27: Tier: Preferred at or above | C27: 85
B28: Tier: Acceptable at or above | C28: 70
B29: Tier: Improvement needed at or above | C29: 55
B30: Exception thresholds
B31: Chronic late: OTIF below | C31: 0.8 | D31: S1
B32: Minimum due lines for rate-based flags | C32: 30 | D32: S1, S2, S4, S5
B33: Unstable lead time: SD at or above (days) | C33: 5 | D33: S3
B34: Incomplete deliveries: in-full below | C34: 0.9 | D34: S4
B35: Quality: reject rate at or above | C35: 0.02 | D35: S5
B36: Deterioration: OTIF drop of at least | C36: 0.1 | D36: S2
B37: PPV: paid above contract by at least | C37: 0.1 | D37: S6
B38: High dependency: category share at or above | C38: 0.6 | D38: S8
B39: High dependency: share of total at or above | C39: 0.15 | D39: S8
B40: Medium dependency: category share at or above | C40: 0.35
B41: Medium dependency: share of total at or above | C41: 0.08
B42: Scenario assumptions (modelled, not realised)
B43: Cost of handling one late PO line (USD) | C43: 150 | D43: Expediting and disruption; an assumption
B45: Weights total (check) | C45: =Assumptions!$C$10+Assumptions!$C$11+Assumptions!$C$12+Assumptions!$C$13

Sheet Syn_Lines
A1: po_line_id | B1: po_id | C1: supplier_id | D1: category_id | E1: item_id | F1: order_date | G1: promised_date | H1: ordered_qty | I1: unit_price | J1: standard_price | K1: cancelled | L1: short_closed | M1: received_qty | N1: qty_by_promise | O1: rejected_qty | P1: first_receipt_date | Q1: completion_date | R1: last_receipt_or_close_date | S1: line_value | T1: standard_value | U1: due | V1: on_time | W1: in_full | X1: otif | Y1: complete | Z1: open | AA1: overdue | AB1: days_late | AC1: lead_time_days | AD1: lead_time_sq | AE1: open_value | AF1: due_period | AG1: due_month
A2: SPO-00001-1 | B2: SPO-00001 | C2: SUP-14 | D2: FLEET | E2: FLEET-05 | F2: 45566 | G2: 45580 | H2: 8 | I2: 161.89 | J2: 168 | K2: 0 | L2: 0 | M2: 8 | N2: 8 | O2: 0 | P2: 45578 | Q2: 45578 | R2: 45578 | S2: =H2*I2 | T2: =H2*J2 | U2: =IF(AND(K2=0,G2<=Assumptions!$C$6),1,0) | V2: =IF(U2=1,IF(M2>0,IF(P2<=G2+Assumptions!$C$7,1,0),0),0) | W2: =IF(AND(U2=1,M2>=H2*(1-Assumptions!$C$8)),1,0) | X2: =IF(AND(U2=1,N2>=H2*(1-Assumptions!$C$8)),1,0) | Y2: =IF(ISNUMBER(Q2),1,0) | Z2: =IF(AND(K2=0,L2=0,Y2=0),1,0) | AA2: =IF(AND(Z2=1,G2<Assumptions!$C$6),1,0) | AB2: =IF(U2=0,"",IF(Y2=1,MAX(0,Q2-G2),IF(L2=1,MAX(0,R2-G2),MAX(0,Assumptions!$C$6-G2)))) | AC2: =IF(Y2=1,Q2-F2,"") | AD2: =IF(Y2=1,AC2^2,"") | AE2: =IF(Z2=1,(H2-M2)*I2,0) | AF2: =IF(G2<EDATE(Assumptions!$C$6,-12)+1,"prior_12m","last_12m") | AG2: =DATE(YEAR(G2),MONTH(G2),1)
A3: SPO-00001-2 | B3: SPO-00001 | C3: SUP-14 | D3: FLEET | E3: FLEET-08 | F3: 45566 | G3: 45580 | H3: 267 | I3: 5.81 | J3: 6.4 | K3: 0 | L3: 0 | M3: 267 | N3: 267 | O3: 0 | P3: 45575 | Q3: 45575 | R3: 45575 | S3: =H3*I3 | T3: =H3*J3 | U3: =IF(AND(K3=0,G3<=Assumptions!$C$6),1,0) | V3: =IF(U3=1,IF(M3>0,IF(P3<=G3+Assumptions!$C$7,1,0),0),0) | W3: =IF(AND(U3=1,M3>=H3*(1-Assumptions!$C$8)),1,0) | X3: =IF(AND(U3=1,N3>=H3*(1-Assumptions!$C$8)),1,0) | Y3: =IF(ISNUMBER(Q3),1,0) | Z3: =IF(AND(K3=0,L3=0,Y3=0),1,0) | AA3: =IF(AND(Z3=1,G3<Assumptions!$C$6),1,0) | AB3: =IF(U3=0,"",IF(Y3=1,MAX(0,Q3-G3),IF(L3=1,MAX(0,R3-G3),MAX(0,Assumptions!$C$6-G3)))) | AC3: =IF(Y3=1,Q3-F3,"") | AD3: =IF(Y3=1,AC3^2,"") | AE3: =IF(Z3=1,(H3-M3)*I3,0) | AF3: =IF(G3<EDATE(Assumptions!$C$6,-12)+1,"prior_12m","last_12m") | AG3: =DATE(YEAR(G3),MONTH(G3),1)
A4: SPO-00002-1 | B4: SPO-00002 | C4: SUP-01 | D4: ELEC | E4: ELEC-02 | F4: 45566 | G4: 45584 | H4: 675 | I4: 4.25 | J4: 4.2 | K4: 0 | L4: 0 | M4: 675 | N4: 0 | O4: 0 | P4: 45586 | Q4: 45586 | R4: 45586 | S4: =H4*I4 | T4: =H4*J4 | U4: =IF(AND(K4=0,G4<=Assumptions!$C$6),1,0) | V4: =IF(U4=1,IF(M4>0,IF(P4<=G4+Assumptions!$C$7,1,0),0),0) | W4: =IF(AND(U4=1,M4>=H4*(1-Assumptions!$C$8)),1,0) | X4: =IF(AND(U4=1,N4>=H4*(1-Assumptions!$C$8)),1,0) | Y4: =IF(ISNUMBER(Q4),1,0) | Z4: =IF(AND(K4=0,L4=0,Y4=0),1,0) | AA4: =IF(AND(Z4=1,G4<Assumptions!$C$6),1,0) | AB4: =IF(U4=0,"",IF(Y4=1,MAX(0,Q4-G4),IF(L4=1,MAX(0,R4-G4),MAX(0,Assumptions!$C$6-G4)))) | AC4: =IF(Y4=1,Q4-F4,"") | AD4: =IF(Y4=1,AC4^2,"") | AE4: =IF(Z4=1,(H4-M4)*I4,0) | AF4: =IF(G4<EDATE(Assumptions!$C$6,-12)+1,"prior_12m","last_12m") | AG4: =DATE(YEAR(G4),MONTH(G4),1)
A5: SPO-00002-2 | B5: SPO-00002 | C5: SUP-01 | D5: ELEC | E5: ELEC-08 | F5: 45566 | G5: 45584 | H5: 121 | I5: 18.87 | J5: 18 | K5: 0 | L5: 0 | M5: 121 | N5: 121 | O5: 0 | P5: 45578 | Q5: 45578 | R5: 45578 | S5: =H5*I5 | T5: =H5*J5 | U5: =IF(AND(K5=0,G5<=Assumptions!$C$6),1,0) | V5: =IF(U5=1,IF(M5>0,IF(P5<=G5+Assumptions!$C$7,1,0),0),0) | W5: =IF(AND(U5=1,M5>=H5*(1-Assumptions!$C$8)),1,0) | X5: =IF(AND(U5=1,N5>=H5*(1-Assumptions!$C$8)),1,0) | Y5: =IF(ISNUMBER(Q5),1,0) | Z5: =IF(AND(K5=0,L5=0,Y5=0),1,0) | AA5: =IF(AND(Z5=1,G5<Assumptions!$C$6),1,0) | AB5: =IF(U5=0,"",IF(Y5=1,MAX(0,Q5-G5),IF(L5=1,MAX(0,R5-G5),MAX(0,Assumptions!$C$6-G5)))) | AC5: =IF(Y5=1,Q5-F5,"") | AD5: =IF(Y5=1,AC5^2,"") | AE5: =IF(Z5=1,(H5-M5)*I5,0) | AF5: =IF(G5<EDATE(Assumptions!$C$6,-12)+1,"prior_12m","last_12m") | AG5: =DATE(YEAR(G5),MONTH(G5),1)
A6: SPO-00002-3 | B6: SPO-00002 | C6: SUP-01 | D6: ELEC | E6: ELEC-07 | F6: 45566 | G6: 45584 | H6: 416 | I6: 10.12 | J6: 9.8 | K6: 0 | L6: 0 | M6: 416 | N6: 416 | O6: 0 | P6: 45584 | Q6: 45584 | R6: 45584 | S6: =H6*I6 | T6: =H6*J6 | U6: =IF(AND(K6=0,G6<=Assumptions!$C$6),1,0) | V6: =IF(U6=1,IF(M6>0,IF(P6<=G6+Assumptions!$C$7,1,0),0),0) | W6: =IF(AND(U6=1,M6>=H6*(1-Assumptions!$C$8)),1,0) | X6: =IF(AND(U6=1,N6>=H6*(1-Assumptions!$C$8)),1,0) | Y6: =IF(ISNUMBER(Q6),1,0) | Z6: =IF(AND(K6=0,L6=0,Y6=0),1,0) | AA6: =IF(AND(Z6=1,G6<Assumptions!$C$6),1,0) | AB6: =IF(U6=0,"",IF(Y6=1,MAX(0,Q6-G6),IF(L6=1,MAX(0,R6-G6),MAX(0,Assumptions!$C$6-G6)))) | AC6: =IF(Y6=1,Q6-F6,"") | AD6: =IF(Y6=1,AC6^2,"") | AE6: =IF(Z6=1,(H6-M6)*I6,0) | AF6: =IF(G6<EDATE(Assumptions!$C$6,-12)+1,"prior_12m","last_12m") | AG6: =DATE(YEAR(G6),MONTH(G6),1)
A7: SPO-00003-1 | B7: SPO-00003 | C7: SUP-09 | D7: CHEM | E7: CHEM-04 | F7: 45567 | G7: 45581 | H7: 4 | I7: 815.23 | J7: 820 | K7: 0 | L7: 0 | M7: 4 | N7: 4 | O7: 0 | P7: 45578 | Q7: 45578 | R7: 45578 | S7: =H7*I7 | T7: =H7*J7 | U7: =IF(AND(K7=0,G7<=Assumptions!$C$6),1,0) | V7: =IF(U7=1,IF(M7>0,IF(P7<=G7+Assumptions!$C$7,1,0),0),0) | W7: =IF(AND(U7=1,M7>=H7*(1-Assumptions!$C$8)),1,0) | X7: =IF(AND(U7=1,N7>=H7*(1-Assumptions!$C$8)),1,0) | Y7: =IF(ISNUMBER(Q7),1,0) | Z7: =IF(AND(K7=0,L7=0,Y7=0),1,0) | AA7: =IF(AND(Z7=1,G7<Assumptions!$C$6),1,0) | AB7: =IF(U7=0,"",IF(Y7=1,MAX(0,Q7-G7),IF(L7=1,MAX(0,R7-G7),MAX(0,Assumptions!$C$6-G7)))) | AC7: =IF(Y7=1,Q7-F7,"") | AD7: =IF(Y7=1,AC7^2,"") | AE7: =IF(Z7=1,(H7-M7)*I7,0) | AF7: =IF(G7<EDATE(Assumptions!$C$6,-12)+1,"prior_12m","last_12m") | AG7: =DATE(YEAR(G7),MONTH(G7),1)
A8: SPO-00003-2 | B8: SPO-00003 | C8: SUP-09 | D8: CHEM | E8: CHEM-05 | F8: 45567 | G8: 45581 | H8: 2 | I8: 967.79 | J8: 930 | K8: 0 | L8: 0 | M8: 2 | N8: 2 | O8: 0 | P8: 45580 | Q8: 45580 | R8: 45580 | S8: =H8*I8 | T8: =H8*J8 | U8: =IF(AND(K8=0,G8<=Assumptions!$C$6),1,0) | V8: =IF(U8=1,IF(M8>0,IF(P8<=G8+Assumptions!$C$7,1,0),0),0) | W8: =IF(AND(U8=1,M8>=H8*(1-Assumptions!$C$8)),1,0) | X8: =IF(AND(U8=1,N8>=H8*(1-Assumptions!$C$8)),1,0) | Y8: =IF(ISNUMBER(Q8),1,0) | Z8: =IF(AND(K8=0,L8=0,Y8=0),1,0) | AA8: =IF(AND(Z8=1,G8<Assumptions!$C$6),1,0) | AB8: =IF(U8=0,"",IF(Y8=1,MAX(0,Q8-G8),IF(L8=1,MAX(0,R8-G8),MAX(0,Assumptions!$C$6-G8)))) | AC8: =IF(Y8=1,Q8-F8,"") | AD8: =IF(Y8=1,AC8^2,"") | AE8: =IF(Z8=1,(H8-M8)*I8,0) | AF8: =IF(G8<EDATE(Assumptions!$C$6,-12)+1,"prior_12m","last_12m") | AG8: =DATE(YEAR(G8),MONTH(G8),1)
A9: SPO-00003-3 | B9: SPO-00003 | C9: SUP-09 | D9: CHEM | E9: CHEM-03 | F9: 45567 | G9: 45581 | H9: 4 | I9: 274.27 | J9: 265 | K9: 0 | L9: 0 | M9: 4 | N9: 4 | O9: 0 | P9: 45578 | Q9: 45578 | R9: 45578 | S9: =H9*I9 | T9: =H9*J9 | U9: =IF(AND(K9=0,G9<=Assumptions!$C$6),1,0) | V9: =IF(U9=1,IF(M9>0,IF(P9<=G9+Assumptions!$C$7,1,0),0),0) | W9: =IF(AND(U9=1,M9>=H9*(1-Assumptions!$C$8)),1,0) | X9: =IF(AND(U9=1,N9>=H9*(1-Assumptions!$C$8)),1,0) | Y9: =IF(ISNUMBER(Q9),1,0) | Z9: =IF(AND(K9=0,L9=0,Y9=0),1,0) | AA9: =IF(AND(Z9=1,G9<Assumptions!$C$6),1,0) | AB9: =IF(U9=0,"",IF(Y9=1,MAX(0,Q9-G9),IF(L9=1,MAX(0,R9-G9),MAX(0,Assumptions!$C$6-G9)))) | AC9: =IF(Y9=1,Q9-F9,"") | AD9: =IF(Y9=1,AC9^2,"") | AE9: =IF(Z9=1,(H9-M9)*I9,0) | AF9: =IF(G9<EDATE(Assumptions!$C$6,-12)+1,"prior_12m","last_12m") | AG9: =DATE(YEAR(G9),MONTH(G9),1)
A10: SPO-00004-1 | B10: SPO-00004 | C10: SUP-07 | D10: MRO | E10: MRO-02 | F10: 45567 | G10: 45577 | H10: 32 | I10: 39.84 | J10: 41 | K10: 0 | L10: 0 | M10: 32 | N10: 32 | O10: 0 | P10: 45576 | Q10: 45576 | R10: 45576 | S10: =H10*I10 | T10: =H10*J10 | U10: =IF(AND(K10=0,G10<=Assumptions!$C$6),1,0) | V10: =IF(U10=1,IF(M10>0,IF(P10<=G10+Assumptions!$C$7,1,0),0),0) | W10: =IF(AND(U10=1,M10>=H10*(1-Assumptions!$C$8)),1,0) | X10: =IF(AND(U10=1,N10>=H10*(1-Assumptions!$C$8)),1,0) | Y10: =IF(ISNUMBER(Q10),1,0) | Z10: =IF(AND(K10=0,L10=0,Y10=0),1,0) | AA10: =IF(AND(Z10=1,G10<Assumptions!$C$6),1,0) | AB10: =IF(U10=0,"",IF(Y10=1,MAX(0,Q10-G10),IF(L10=1,MAX(0,R10-G10),MAX(0,Assumptions!$C$6-G10)))) | AC10: =IF(Y10=1,Q10-F10,"") | AD10: =IF(Y10=1,AC10^2,"") | AE10: =IF(Z10=1,(H10-M10)*I10,0) | AF10: =IF(G10<EDATE(Assumptions!$C$6,-12)+1,"prior_12m","last_12m") | AG10: =DATE(YEAR(G10),MONTH(G10),1)
A11: SPO-00004-2 | B11: SPO-00004 | C11: SUP-07 | D11: MRO | E11: MRO-01 | F11: 45567 | G11: 45577 | H11: 26 | I11: 53.75 | J11: 52 | K11: 0 | L11: 0 | M11: 26 | N11: 26 | O11: 0 | P11: 45576 | Q11: 45576 | R11: 45576 | S11: =H11*I11 | T11: =H11*J11 | U11: =IF(AND(K11=0,G11<=Assumptions!$C$6),1,0) | V11: =IF(U11=1,IF(M11>0,IF(P11<=G11+Assumptions!$C$7,1,0),0),0) | W11: =IF(AND(U11=1,M11>=H11*(1-Assumptions!$C$8)),1,0) | X11: =IF(AND(U11=1,N11>=H11*(1-Assumptions!$C$8)),1,0) | Y11: =IF(ISNUMBER(Q11),1,0) | Z11: =IF(AND(K11=0,L11=0,Y11=0),1,0) | AA11: =IF(AND(Z11=1,G11<Assumptions!$C$6),1,0) | AB11: =IF(U11=0,"",IF(Y11=1,MAX(0,Q11-G11),IF(L11=1,MAX(0,R11-G11),MAX(0,Assumptions!$C$6-G11)))) | AC11: =IF(Y11=1,Q11-F11,"") | AD11: =IF(Y11=1,AC11^2,"") | AE11: =IF(Z11=1,(H11-M11)*I11,0) | AF11: =IF(G11<EDATE(Assumptions!$C$6,-12)+1,"prior_12m","last_12m") | AG11: =DATE(YEAR(G11),MONTH(G11),1)
A12: SPO-00004-3 | B12: SPO-00004 | C12: SUP-07 | D12: MRO | E12: MRO-06 | F12: 45567 | G12: 45577 | H12: 510 | I12: 6.09 | J12: 6.1 | K12: 0 | L12: 0 | M12: 510 | N12: 510 | O12: 0 | P12: 45572 | Q12: 45572 | R12: 45572 | S12: =H12*I12 | T12: =H12*J12 | U12: =IF(AND(K12=0,G12<=Assumptions!$C$6),1,0) | V12: =IF(U12=1,IF(M12>0,IF(P12<=G12+Assumptions!$C$7,1,0),0),0) | W12: =IF(AND(U12=1,M12>=H12*(1-Assumptions!$C$8)),1,0) | X12: =IF(AND(U12=1,N12>=H12*(1-Assumptions!$C$8)),1,0) | Y12: =IF(ISNUMBER(Q12),1,0) | Z12: =IF(AND(K12=0,L12=0,Y12=0),1,0) | AA12: =IF(AND(Z12=1,G12<Assumptions!$C$6),1,0) | AB12: =IF(U12=0,"",IF(Y12=1,MAX(0,Q12-G12),IF(L12=1,MAX(0,R12-G12),MAX(0,Assumptions!$C$6-G12)))) | AC12: =IF(Y12=1,Q12-F12,"") | AD12: =IF(Y12=1,AC12^2,"") | AE12: =IF(Z12=1,(H12-M12)*I12,0) | AF12: =IF(G12<EDATE(Assumptions!$C$6,-12)+1,"prior_12m","last_12m") | AG12: =DATE(YEAR(G12),MONTH(G12),1)
A13: SPO-00004-4 | B13: SPO-00004 | C13: SUP-07 | D13: MRO | E13: MRO-07 | F13: 45567 | G13: 45577 | H13: 157 | I13: 14.19 | J13: 14 | K13: 0 | L13: 1 | M13: 115 | N13: 115 | O13: 0 | P13: 45570 | R13: 45570 | S13: =H13*I13 | T13: =H13*J13 | U13: =IF(AND(K13=0,G13<=Assumptions!$C$6),1,0) | V13: =IF(U13=1,IF(M13>0,IF(P13<=G13+Assumptions!$C$7,1,0),0),0) | W13: =IF(AND(U13=1,M13>=H13*(1-Assumptions!$C$8)),1,0) | X13: =IF(AND(U13=1,N13>=H13*(1-Assumptions!$C$8)),1,0) | Y13: =IF(ISNUMBER(Q13),1,0) | Z13: =IF(AND(K13=0,L13=0,Y13=0),1,0) | AA13: =IF(AND(Z13=1,G13<Assumptions!$C$6),1,0) | AB13: =IF(U13=0,"",IF(Y13=1,MAX(0,Q13-G13),IF(L13=1,MAX(0,R13-G13),MAX(0,Assumptions!$C$6-G13)))) | AC13: =IF(Y13=1,Q13-F13,"") | AD13: =IF(Y13=1,AC13^2,"") | AE13: =IF(Z13=1,(H13-M13)*I13,0) | AF13: =IF(G13<EDATE(Assumptions!$C$6,-12)+1,"prior_12m","last_12m") | AG13: =DATE(YEAR(G13),MONTH(G13),1)
A14: SPO-00005-1 | B14: SPO-00005 | C14: SUP-09 | D14: CHEM | E14: CHEM-03 | F14: 45568 | G14: 45582 | H14: 6 | I14: 276.03 | J14: 265 | K14: 0 | L14: 0 | M14: 6 | N14: 6 | O14: 0 | P14: 45582 | Q14: 45582 | R14: 45582 | S14: =H14*I14 | T14: =H14*J14 | U14: =IF(AND(K14=0,G14<=Assumptions!$C$6),1,0) | V14: =IF(U14=1,IF(M14>0,IF(P14<=G14+Assumptions!$C$7,1,0),0),0) | W14: =IF(AND(U14=1,M14>=H14*(1-Assumptions!$C$8)),1,0) | X14: =IF(AND(U14=1,N14>=H14*(1-Assumptions!$C$8)),1,0) | Y14: =IF(ISNUMBER(Q14),1,0) | Z14: =IF(AND(K14=0,L14=0,Y14=0),1,0) | AA14: =IF(AND(Z14=1,G14<Assumptions!$C$6),1,0) | AB14: =IF(U14=0,"",IF(Y14=1,MAX(0,Q14-G14),IF(L14=1,MAX(0,R14-G14),MAX(0,Assumptions!$C$6-G14)))) | AC14: =IF(Y14=1,Q14-F14,"") | AD14: =IF(Y14=1,AC14^2,"") | AE14: =IF(Z14=1,(H14-M14)*I14,0) | AF14: =IF(G14<EDATE(Assumptions!$C$6,-12)+1,"prior_12m","last_12m") | AG14: =DATE(YEAR(G14),MONTH(G14),1)
A15: SPO-00005-2 | B15: SPO-00005 | C15: SUP-09 | D15: CHEM | E15: CHEM-01 | F15: 45568 | G15: 45582 | H15: 2 | I15: 680.98 | J15: 640 | K15: 0 | L15: 0 | M15: 2 | N15: 2 | O15: 0 | P15: 45580 | Q15: 45580 | R15: 45580 | S15: =H15*I15 | T15: =H15*J15 | U15: =IF(AND(K15=0,G15<=Assumptions!$C$6),1,0) | V15: =IF(U15=1,IF(M15>0,IF(P15<=G15+Assumptions!$C$7,1,0),0),0) | W15: =IF(AND(U15=1,M15>=H15*(1-Assumptions!$C$8)),1,0) | X15: =IF(AND(U15=1,N15>=H15*(1-Assumptions!$C$8)),1,0) | Y15: =IF(ISNUMBER(Q15),1,0) | Z15: =IF(AND(K15=0,L15=0,Y15=0),1,0) | AA15: =IF(AND(Z15=1,G15<Assumptions!$C$6),1,0) | AB15: =IF(U15=0,"",IF(Y15=1,MAX(0,Q15-G15),IF(L15=1,MAX(0,R15-G15),MAX(0,Assumptions!$C$6-G15)))) | AC15: =IF(Y15=1,Q15-F15,"") | AD15: =IF(Y15=1,AC15^2,"") | AE15: =IF(Z15=1,(H15-M15)*I15,0) | AF15: =IF(G15<EDATE(Assumptions!$C$6,-12)+1,"prior_12m","last_12m") | AG15: =DATE(YEAR(G15),MONTH(G15),1)
A16: SPO-00005-3 | B16: SPO-00005 | C16: SUP-09 | D16: CHEM | E16: CHEM-05 | F16: 45568 | G16: 45582 | H16: 2 | I16: 962.73 | J16: 930 | K16: 0 | L16: 0 | M16: 2 | N16: 2 | O16: 0 | P16: 45582 | Q16: 45582 | R16: 45582 | S16: =H16*I16 | T16: =H16*J16 | U16: =IF(AND(K16=0,G16<=Assumptions!$C$6),1,0) | V16: =IF(U16=1,IF(M16>0,IF(P16<=G16+Assumptions!$C$7,1,0),0),0) | W16: =IF(AND(U16=1,M16>=H16*(1-Assumptions!$C$8)),1,0) | X16: =IF(AND(U16=1,N16>=H16*(1-Assumptions!$C$8)),1,0) | Y16: =IF(ISNUMBER(Q16),1,0) | Z16: =IF(AND(K16=0,L16=0,Y16=0),1,0) | AA16: =IF(AND(Z16=1,G16<Assumptions!$C$6),1,0) | AB16: =IF(U16=0,"",IF(Y16=1,MAX(0,Q16-G16),IF(L16=1,MAX(0,R16-G16),MAX(0,Assumptions!$C$6-G16)))) | AC16: =IF(Y16=1,Q16-F16,"") | AD16: =IF(Y16=1,AC16^2,"") | AE16: =IF(Z16=1,(H16-M16)*I16,0) | AF16: =IF(G16<EDATE(Assumptions!$C$6,-12)+1,"prior_12m","last_12m") | AG16: =DATE(YEAR(G16),MONTH(G16),1)
A17: SPO-00006-1 | B17: SPO-00006 | C17: SUP-14 | D17: FLEET | E17: FLEET-08 | F17: 45569 | G17: 45583 | H17: 398 | I17: 6.45 | J17: 6.4 | K17: 0 | L17: 0 | M17: 398 | N17: 0 | O17: 0 | P17: 45584 | Q17: 45584 | R17: 45584 | S17: =H17*I17 | T17: =H17*J17 | U17: =IF(AND(K17=0,G17<=Assumptions!$C$6),1,0) | V17: =IF(U17=1,IF(M17>0,IF(P17<=G17+Assumptions!$C$7,1,0),0),0) | W17: =IF(AND(U17=1,M17>=H17*(1-Assumptions!$C$8)),1,0) | X17: =IF(AND(U17=1,N17>=H17*(1-Assumptions!$C$8)),1,0) | Y17: =IF(ISNUMBER(Q17),1,0) | Z17: =IF(AND(K17=0,L17=0,Y17=0),1,0) | AA17: =IF(AND(Z17=1,G17<Assumptions!$C$6),1,0) | AB17: =IF(U17=0,"",IF(Y17=1,MAX(0,Q17-G17),IF(L17=1,MAX(0,R17-G17),MAX(0,Assumptions!$C$6-G17)))) | AC17: =IF(Y17=1,Q17-F17,"") | AD17: =IF(Y17=1,AC17^2,"") | AE17: =IF(Z17=1,(H17-M17)*I17,0) | AF17: =IF(G17<EDATE(Assumptions!$C$6,-12)+1,"prior_12m","last_12m") | AG17: =DATE(YEAR(G17),MONTH(G17),1)
A18: SPO-00007-1 | B18: SPO-00007 | C18: SUP-08 | D18: MRO | E18: MRO-06 | F18: 45569 | G18: 45580 | H18: 486 | I18: 5.89 | J18: 6.1 | K18: 0 | L18: 0 | M18: 486 | N18: 486 | O18: 0 | P18: 45577 | Q18: 45577 | R18: 45577 | S18: =H18*I18 | T18: =H18*J18 | U18: =IF(AND(K18=0,G18<=Assumptions!$C$6),1,0) | V18: =IF(U18=1,IF(M18>0,IF(P18<=G18+Assumptions!$C$7,1,0),0),0) | W18: =IF(AND(U18=1,M18>=H18*(1-Assumptions!$C$8)),1,0) | X18: =IF(AND(U18=1,N18>=H18*(1-Assumptions!$C$8)),1,0) | Y18: =IF(ISNUMBER(Q18),1,0) | Z18: =IF(AND(K18=0,L18=0,Y18=0),1,0) | AA18: =IF(AND(Z18=1,G18<Assumptions!$C$6),1,0) | AB18: =IF(U18=0,"",IF(Y18=1,MAX(0,Q18-G18),IF(L18=1,MAX(0,R18-G18),MAX(0,Assumptions!$C$6-G18)))) | AC18: =IF(Y18=1,Q18-F18,"") | AD18: =IF(Y18=1,AC18^2,"") | AE18: =IF(Z18=1,(H18-M18)*I18,0) | AF18: =IF(G18<EDATE(Assumptions!$C$6,-12)+1,"prior_12m","last_12m") | AG18: =DATE(YEAR(G18),MONTH(G18),1)
A19: SPO-00008-1 | B19: SPO-00008 | C19: SUP-06 | D19: MRO | E19: MRO-03 | F19: 45569 | G19: 45577 | H19: 415 | I19: 8.59 | J19: 8.9 | K19: 0 | L19: 0 | M19: 415 | N19: 415 | O19: 0 | P19: 45576 | Q19: 45576 | R19: 45576 | S19: =H19*I19 | T19: =H19*J19 | U19: =IF(AND(K19=0,G19<=Assumptions!$C$6),1,0) | V19: =IF(U19=1,IF(M19>0,IF(P19<=G19+Assumptions!$C$7,1,0),0),0) | W19: =IF(AND(U19=1,M19>=H19*(1-Assumptions!$C$8)),1,0) | X19: =IF(AND(U19=1,N19>=H19*(1-Assumptions!$C$8)),1,0) | Y19: =IF(ISNUMBER(Q19),1,0) | Z19: =IF(AND(K19=0,L19=0,Y19=0),1,0) | AA19: =IF(AND(Z19=1,G19<Assumptions!$C$6),1,0) | AB19: =IF(U19=0,"",IF(Y19=1,MAX(0,Q19-G19),IF(L19=1,MAX(0,R19-G19),MAX(0,Assumptions!$C$6-G19)))) | AC19: =IF(Y19=1,Q19-F19,"") | AD19: =IF(Y19=1,AC19^2,"") | AE19: =IF(Z19=1,(H19-M19)*I19,0) | AF19: =IF(G19<EDATE(Assumptions!$C$6,-12)+1,"prior_12m","last_12m") | AG19: =DATE(YEAR(G19),MONTH(G19),1)
A20: SPO-00008-2 | B20: SPO-00008 | C20: SUP-06 | D20: MRO | E20: MRO-08 | F20: 45569 | G20: 45577 | H20: 344 | I20: 7.3 | J20: 7.2 | K20: 0 | L20: 0 | M20: 344 | N20: 344 | O20: 0 | P20: 45575 | Q20: 45575 | R20: 45575 | S20: =H20*I20 | T20: =H20*J20 | U20: =IF(AND(K20=0,G20<=Assumptions!$C$6),1,0) | V20: =IF(U20=1,IF(M20>0,IF(P20<=G20+Assumptions!$C$7,1,0),0),0) | W20: =IF(AND(U20=1,M20>=H20*(1-Assumptions!$C$8)),1,0) | X20: =IF(AND(U20=1,N20>=H20*(1-Assumptions!$C$8)),1,0) | Y20: =IF(ISNUMBER(Q20),1,0) | Z20: =IF(AND(K20=0,L20=0,Y20=0),1,0) | AA20: =IF(AND(Z20=1,G20<Assumptions!$C$6),1,0) | AB20: =IF(U20=0,"",IF(Y20=1,MAX(0,Q20-G20),IF(L20=1,MAX(0,R20-G20),MAX(0,Assumptions!$C$6-G20)))) | AC20: =IF(Y20=1,Q20-F20,"") | AD20: =IF(Y20=1,AC20^2,"") | AE20: =IF(Z20=1,(H20-M20)*I20,0) | AF20: =IF(G20<EDATE(Assumptions!$C$6,-12)+1,"prior_12m","last_12m") | AG20: =DATE(YEAR(G20),MONTH(G20),1)
A21: SPO-00009-1 | B21: SPO-00009 | C21: SUP-01 | D21: ELEC | E21: ELEC-03 | F21: 45569 | G21: 45587 | H21: 24 | I21: 100.42 | J21: 96 | K21: 0 | L21: 0 | M21: 24 | N21: 24 | O21: 0 | P21: 45586 | Q21: 45586 | R21: 45586 | S21: =H21*I21 | T21: =H21*J21 | U21: =IF(AND(K21=0,G21<=Assumptions!$C$6),1,0) | V21: =IF(U21=1,IF(M21>0,IF(P21<=G21+Assumptions!$C$7,1,0),0),0) | W21: =IF(AND(U21=1,M21>=H21*(1-Assumptions!$C$8)),1,0) | X21: =IF(AND(U21=1,N21>=H21*(1-Assumptions!$C$8)),1,0) | Y21: =IF(ISNUMBER(Q21),1,0) | Z21: =IF(AND(K21=0,L21=0,Y21=0),1,0) | AA21: =IF(AND(Z21=1,G21<Assumptions!$C$6),1,0) | AB21: =IF(U21=0,"",IF(Y21=1,MAX(0,Q21-G21),IF(L21=1,MAX(0,R21-G21),MAX(0,Assumptions!$C$6-G21)))) | AC21: =IF(Y21=1,Q21-F21,"") | AD21: =IF(Y21=1,AC21^2,"") | AE21: =IF(Z21=1,(H21-M21)*I21,0) | AF21: =IF(G21<EDATE(Assumptions!$C$6,-12)+1,"prior_12m","last_12m") | AG21: =DATE(YEAR(G21),MONTH(G21),1)
A22: SPO-00009-2 | B22: SPO-00009 | C22: SUP-01 | D22: ELEC | E22: ELEC-01 | F22: 45569 | G22: 45587 | H22: 56 | I22: 38.16 | J22: 38 | K22: 0 | L22: 0 | M22: 56 | N22: 56 | O22: 0 | P22: 45586 | Q22: 45586 | R22: 45586 | S22: =H22*I22 | T22: =H22*J22 | U22: =IF(AND(K22=0,G22<=Assumptions!$C$6),1,0) | V22: =IF(U22=1,IF(M22>0,IF(P22<=G22+Assumptions!$C$7,1,0),0),0) | W22: =IF(AND(U22=1,M22>=H22*(1-Assumptions!$C$8)),1,0) | X22: =IF(AND(U22=1,N22>=H22*(1-Assumptions!$C$8)),1,0) | Y22: =IF(ISNUMBER(Q22),1,0) | Z22: =IF(AND(K22=0,L22=0,Y22=0),1,0) | AA22: =IF(AND(Z22=1,G22<Assumptions!$C$6),1,0) | AB22: =IF(U22=0,"",IF(Y22=1,MAX(0,Q22-G22),IF(L22=1,MAX(0,R22-G22),MAX(0,Assumptions!$C$6-G22)))) | AC22: =IF(Y22=1,Q22-F22,"") | AD22: =IF(Y22=1,AC22^2,"") | AE22: =IF(Z22=1,(H22-M22)*I22,0) | AF22: =IF(G22<EDATE(Assumptions!$C$6,-12)+1,"prior_12m","last_12m") | AG22: =DATE(YEAR(G22),MONTH(G22),1)
A23: SPO-00009-3 | B23: SPO-00009 | C23: SUP-01 | D23: ELEC | E23: ELEC-06 | F23: 45569 | G23: 45587 | H23: 48 | I23: 153.53 | J23: 145 | K23: 0 | L23: 0 | M23: 48 | N23: 48 | O23: 0 | P23: 45583 | Q23: 45583 | R23: 45583 | S23: =H23*I23 | T23: =H23*J23 | U23: =IF(AND(K23=0,G23<=Assumptions!$C$6),1,0) | V23: =IF(U23=1,IF(M23>0,IF(P23<=G23+Assumptions!$C$7,1,0),0),0) | W23: =IF(AND(U23=1,M23>=H23*(1-Assumptions!$C$8)),1,0) | X23: =IF(AND(U23=1,N23>=H23*(1-Assumptions!$C$8)),1,0) | Y23: =IF(ISNUMBER(Q23),1,0) | Z23: =IF(AND(K23=0,L23=0,Y23=0),1,0) | AA23: =IF(AND(Z23=1,G23<Assumptions!$C$6),1,0) | AB23: =IF(U23=0,"",IF(Y23=1,MAX(0,Q23-G23),IF(L23=1,MAX(0,R23-G23),MAX(0,Assumptions!$C$6-G23)))) | AC23: =IF(Y23=1,Q23-F23,"") | AD23: =IF(Y23=1,AC23^2,"") | AE23: =IF(Z23=1,(H23-M23)*I23,0) | AF23: =IF(G23<EDATE(Assumptions!$C$6,-12)+1,"prior_12m","last_12m") | AG23: =DATE(YEAR(G23),MONTH(G23),1)
A24: SPO-00009-4 | B24: SPO-00009 | C24: SUP-01 | D24: ELEC | E24: ELEC-05 | F24: 45569 | G24: 45587 | H24: 234 | I24: 11.59 | J24: 11.5 | K24: 0 | L24: 0 | M24: 234 | N24: 234 | O24: 0 | P24: 45583 | Q24: 45583 | R24: 45583 | S24: =H24*I24 | T24: =H24*J24 | U24: =IF(AND(K24=0,G24<=Assumptions!$C$6),1,0) | V24: =IF(U24=1,IF(M24>0,IF(P24<=G24+Assumptions!$C$7,1,0),0),0) | W24: =IF(AND(U24=1,M24>=H24*(1-Assumptions!$C$8)),1,0) | X24: =IF(AND(U24=1,N24>=H24*(1-Assumptions!$C$8)),1,0) | Y24: =IF(ISNUMBER(Q24),1,0) | Z24: =IF(AND(K24=0,L24=0,Y24=0),1,0) | AA24: =IF(AND(Z24=1,G24<Assumptions!$C$6),1,0) | AB24: =IF(U24=0,"",IF(Y24=1,MAX(0,Q24-G24),IF(L24=1,MAX(0,R24-G24),MAX(0,Assumptions!$C$6-G24)))) | AC24: =IF(Y24=1,Q24-F24,"") | AD24: =IF(Y24=1,AC24^2,"") | AE24: =IF(Z24=1,(H24-M24)*I24,0) | AF24: =IF(G24<EDATE(Assumptions!$C$6,-12)+1,"prior_12m","last_12m") | AG24: =DATE(YEAR(G24),MONTH(G24),1)
A25: SPO-00010-1 | B25: SPO-00010 | C25: SUP-06 | D25: MRO | E25: MRO-03 | F25: 45569 | G25: 45577 | H25: 131 | I25: 8.72 | J25: 8.9 | K25: 0 | L25: 0 | M25: 131 | N25: 131 | O25: 0 | P25: 45574 | Q25: 45574 | R25: 45574 | S25: =H25*I25 | T25: =H25*J25 | U25: =IF(AND(K25=0,G25<=Assumptions!$C$6),1,0) | V25: =IF(U25=1,IF(M25>0,IF(P25<=G25+Assumptions!$C$7,1,0),0),0) | W25: =IF(AND(U25=1,M25>=H25*(1-Assumptions!$C$8)),1,0) | X25: =IF(AND(U25=1,N25>=H25*(1-Assumptions!$C$8)),1,0) | Y25: =IF(ISNUMBER(Q25),1,0) | Z25: =IF(AND(K25=0,L25=0,Y25=0),1,0) | AA25: =IF(AND(Z25=1,G25<Assumptions!$C$6),1,0) | AB25: =IF(U25=0,"",IF(Y25=1,MAX(0,Q25-G25),IF(L25=1,MAX(0,R25-G25),MAX(0,Assumptions!$C$6-G25)))) | AC25: =IF(Y25=1,Q25-F25,"") | AD25: =IF(Y25=1,AC25^2,"") | AE25: =IF(Z25=1,(H25-M25)*I25,0) | AF25: =IF(G25<EDATE(Assumptions!$C$6,-12)+1,"prior_12m","last_12m") | AG25: =DATE(YEAR(G25),MONTH(G25),1)
... A48: SPO-00022-3 | B48: SPO-00022 | C48: SUP-09 | D48: CHEM | E48: CHEM-05 | F48: 45571 | G48: 45585 | H48: 2 | I48: 984.25 | J48: 930 | K48: 0 | L48: 0 | M48: 2 | N48: 2 | O48: 0 | P48: 45583 | Q48: 45583 | R48: 45583 | S48: =H48*I48 | T48: =H48*J48 | U48: =IF(AND(K48=0,G48<=Assumptions!$C$6),1,0) | V48: =IF(U48=1,IF(M48>0,IF(P48<=G48+Assumptions!$C$7,1,0),0),0) | W48: =IF(AND(U48=1,M48>=H48*(1-Assumptions!$C$8)),1,0) | X48: =IF(AND(U48=1,N48>=H48*(1-Assumptions!$C$8)),1,0) | Y48: =IF(ISNUMBER(Q48),1,0) | Z48: =IF(AND(K48=0,L48=0,Y48=0),1,0) | AA48: =IF(AND(Z48=1,G48<Assumptions!$C$6),1,0) | AB48: =IF(U48=0,"",IF(Y48=1,MAX(0,Q48-G48),IF(L48=1,MAX(0,R48-G48),MAX(0,Assumptions!$C$6-G48)))) | AC48: =IF(Y48=1,Q48-F48,"") | AD48: =IF(Y48=1,AC48^2,"") | AE48: =IF(Z48=1,(H48-M48)*I48,0) | AF48: =IF(G48<EDATE(Assumptions!$C$6,-12)+1,"prior_12m","last_12m") | AG48: =DATE(YEAR(G48),MONTH(G48),1)
A49: SPO-00023-1 | B49: SPO-00023 | C49: SUP-05 | D49: FLEET | E49: FLEET-01 | F49: 45571 | G49: 45585 | H49: 44 | I49: 67.73 | J49: 64 | K49: 1 | L49: 0 | M49: 0 | N49: 0 | O49: 0 | S49: =H49*I49 | T49: =H49*J49 | U49: =IF(AND(K49=0,G49<=Assumptions!$C$6),1,0) | V49: =IF(U49=1,IF(M49>0,IF(P49<=G49+Assumptions!$C$7,1,0),0),0) | W49: =IF(AND(U49=1,M49>=H49*(1-Assumptions!$C$8)),1,0) | X49: =IF(AND(U49=1,N49>=H49*(1-Assumptions!$C$8)),1,0) | Y49: =IF(ISNUMBER(Q49),1,0) | Z49: =IF(AND(K49=0,L49=0,Y49=0),1,0) | AA49: =IF(AND(Z49=1,G49<Assumptions!$C$6),1,0) | AB49: =IF(U49=0,"",IF(Y49=1,MAX(0,Q49-G49),IF(L49=1,MAX(0,R49-G49),MAX(0,Assumptions!$C$6-G49)))) | AC49: =IF(Y49=1,Q49-F49,"") | AD49: =IF(Y49=1,AC49^2,"") | AE49: =IF(Z49=1,(H49-M49)*I49,0) | AF49: =IF(G49<EDATE(Assumptions!$C$6,-12)+1,"prior_12m","last_12m") | AG49: =DATE(YEAR(G49),MONTH(G49),1)
A50: SPO-00023-2 | B50: SPO-00023 | C50: SUP-05 | D50: FLEET | E50: FLEET-03 | F50: 45571 | G50: 45585 | H50: 35 | I50: 21.3 | J50: 21 | K50: 0 | L50: 0 | M50: 35 | N50: 35 | O50: 0 | P50: 45581 | Q50: 45581 | R50: 45581 | S50: =H50*I50 | T50: =H50*J50 | U50: =IF(AND(K50=0,G50<=Assumptions!$C$6),1,0) | V50: =IF(U50=1,IF(M50>0,IF(P50<=G50+Assumptions!$C$7,1,0),0),0) | W50: =IF(AND(U50=1,M50>=H50*(1-Assumptions!$C$8)),1,0) | X50: =IF(AND(U50=1,N50>=H50*(1-Assumptions!$C$8)),1,0) | Y50: =IF(ISNUMBER(Q50),1,0) | Z50: =IF(AND(K50=0,L50=0,Y50=0),1,0) | AA50: =IF(AND(Z50=1,G50<Assumptions!$C$6),1,0) | AB50: =IF(U50=0,"",IF(Y50=1,MAX(0,Q50-G50),IF(L50=1,MAX(0,R50-G50),MAX(0,Assumptions!$C$6-G50)))) | AC50: =IF(Y50=1,Q50-F50,"") | AD50: =IF(Y50=1,AC50^2,"") | AE50: =IF(Z50=1,(H50-M50)*I50,0) | AF50: =IF(G50<EDATE(Assumptions!$C$6,-12)+1,"prior_12m","last_12m") | AG50: =DATE(YEAR(G50),MONTH(G50),1)
A51: SPO-00023-3 | B51: SPO-00023 | C51: SUP-05 | D51: FLEET | E51: FLEET-06 | F51: 45571 | G51: 45585 | H51: 36 | I51: 31.73 | J51: 33 | K51: 0 | L51: 0 | M51: 36 | N51: 36 | O51: 0 | P51: 45583 | Q51: 45583 | R51: 45583 | S51: =H51*I51 | T51: =H51*J51 | U51: =IF(AND(K51=0,G51<=Assumptions!$C$6),1,0) | V51: =IF(U51=1,IF(M51>0,IF(P51<=G51+Assumptions!$C$7,1,0),0),0) | W51: =IF(AND(U51=1,M51>=H51*(1-Assumptions!$C$8)),1,0) | X51: =IF(AND(U51=1,N51>=H51*(1-Assumptions!$C$8)),1,0) | Y51: =IF(ISNUMBER(Q51),1,0) | Z51: =IF(AND(K51=0,L51=0,Y51=0),1,0) | AA51: =IF(AND(Z51=1,G51<Assumptions!$C$6),1,0) | AB51: =IF(U51=0,"",IF(Y51=1,MAX(0,Q51-G51),IF(L51=1,MAX(0,R51-G51),MAX(0,Assumptions!$C$6-G51)))) | AC51: =IF(Y51=1,Q51-F51,"") | AD51: =IF(Y51=1,AC51^2,"") | AE51: =IF(Z51=1,(H51-M51)*I51,0) | AF51: =IF(G51<EDATE(Assumptions!$C$6,-12)+1,"prior_12m","last_12m") | AG51: =DATE(YEAR(G51),MONTH(G51),1)
A52: SPO-00023-4 | B52: SPO-00023 | C52: SUP-05 | D52: FLEET | E52: FLEET-08 | F52: 45571 | G52: 45585 | H52: 175 | I52: 6.58 | J52: 6.4 | K52: 0 | L52: 0 | M52: 175 | N52: 175 | O52: 0 | P52: 45583 | Q52: 45583 | R52: 45583 | S52: =H52*I52 | T52: =H52*J52 | U52: =IF(AND(K52=0,G52<=Assumptions!$C$6),1,0) | V52: =IF(U52=1,IF(M52>0,IF(P52<=G52+Assumptions!$C$7,1,0),0),0) | W52: =IF(AND(U52=1,M52>=H52*(1-Assumptions!$C$8)),1,0) | X52: =IF(AND(U52=1,N52>=H52*(1-Assumptions!$C$8)),1,0) | Y52: =IF(ISNUMBER(Q52),1,0) | Z52: =IF(AND(K52=0,L52=0,Y52=0),1,0) | AA52: =IF(AND(Z52=1,G52<Assumptions!$C$6),1,0) | AB52: =IF(U52=0,"",IF(Y52=1,MAX(0,Q52-G52),IF(L52=1,MAX(0,R52-G52),MAX(0,Assumptions!$C$6-G52)))) | AC52: =IF(Y52=1,Q52-F52,"") | AD52: =IF(Y52=1,AC52^2,"") | AE52: =IF(Z52=1,(H52-M52)*I52,0) | AF52: =IF(G52<EDATE(Assumptions!$C$6,-12)+1,"prior_12m","last_12m") | AG52: =DATE(YEAR(G52),MONTH(G52),1)
A53: SPO-00024-1 | B53: SPO-00024 | C53: SUP-04 | D53: FLEET | E53: FLEET-06 | F53: 45571 | G53: 45584 | H53: 38 | I53: 31.84 | J53: 33 | K53: 0 | L53: 0 | M53: 38 | N53: 0 | O53: 0 | P53: 45728 | Q53: 45728 | R53: 45728 | S53: =H53*I53 | T53: =H53*J53 | U53: =IF(AND(K53=0,G53<=Assumptions!$C$6),1,0) | V53: =IF(U53=1,IF(M53>0,IF(P53<=G53+Assumptions!$C$7,1,0),0),0) | W53: =IF(AND(U53=1,M53>=H53*(1-Assumptions!$C$8)),1,0) | X53: =IF(AND(U53=1,N53>=H53*(1-Assumptions!$C$8)),1,0) | Y53: =IF(ISNUMBER(Q53),1,0) | Z53: =IF(AND(K53=0,L53=0,Y53=0),1,0) | AA53: =IF(AND(Z53=1,G53<Assumptions!$C$6),1,0) | AB53: =IF(U53=0,"",IF(Y53=1,MAX(0,Q53-G53),IF(L53=1,MAX(0,R53-G53),MAX(0,Assumptions!$C$6-G53)))) | AC53: =IF(Y53=1,Q53-F53,"") | AD53: =IF(Y53=1,AC53^2,"") | AE53: =IF(Z53=1,(H53-M53)*I53,0) | AF53: =IF(G53<EDATE(Assumptions!$C$6,-12)+1,"prior_12m","last_12m") | AG53: =DATE(YEAR(G53),MONTH(G53),1)
A54: SPO-00024-2 | B54: SPO-00024 | C54: SUP-04 | D54: FLEET | E54: FLEET-05 | F54: 45571 | G54: 45584 | H54: 4 | I54: 161.58 | J54: 168 | K54: 0 | L54: 0 | M54: 4 | N54: 4 | O54: 0 | P54: 45577 | Q54: 45582 | R54: 45582 | S54: =H54*I54 | T54: =H54*J54 | U54: =IF(AND(K54=0,G54<=Assumptions!$C$6),1,0) | V54: =IF(U54=1,IF(M54>0,IF(P54<=G54+Assumptions!$C$7,1,0),0),0) | W54: =IF(AND(U54=1,M54>=H54*(1-Assumptions!$C$8)),1,0) | X54: =IF(AND(U54=1,N54>=H54*(1-Assumptions!$C$8)),1,0) | Y54: =IF(ISNUMBER(Q54),1,0) | Z54: =IF(AND(K54=0,L54=0,Y54=0),1,0) | AA54: =IF(AND(Z54=1,G54<Assumptions!$C$6),1,0) | AB54: =IF(U54=0,"",IF(Y54=1,MAX(0,Q54-G54),IF(L54=1,MAX(0,R54-G54),MAX(0,Assumptions!$C$6-G54)))) | AC54: =IF(Y54=1,Q54-F54,"") | AD54: =IF(Y54=1,AC54^2,"") | AE54: =IF(Z54=1,(H54-M54)*I54,0) | AF54: =IF(G54<EDATE(Assumptions!$C$6,-12)+1,"prior_12m","last_12m") | AG54: =DATE(YEAR(G54),MONTH(G54),1)
A55: SPO-00025-1 | B55: SPO-00025 | C55: SUP-01 | D55: ELEC | E55: ELEC-06 | F55: 45571 | G55: 45589 | H55: 19 | I55: 147 | J55: 145 | K55: 0 | L55: 0 | M55: 19 | N55: 19 | O55: 0 | P55: 45588 | Q55: 45588 | R55: 45588 | S55: =H55*I55 | T55: =H55*J55 | U55: =IF(AND(K55=0,G55<=Assumptions!$C$6),1,0) | V55: =IF(U55=1,IF(M55>0,IF(P55<=G55+Assumptions!$C$7,1,0),0),0) | W55: =IF(AND(U55=1,M55>=H55*(1-Assumptions!$C$8)),1,0) | X55: =IF(AND(U55=1,N55>=H55*(1-Assumptions!$C$8)),1,0) | Y55: =IF(ISNUMBER(Q55),1,0) | Z55: =IF(AND(K55=0,L55=0,Y55=0),1,0) | AA55: =IF(AND(Z55=1,G55<Assumptions!$C$6),1,0) | AB55: =IF(U55=0,"",IF(Y55=1,MAX(0,Q55-G55),IF(L55=1,MAX(0,R55-G55),MAX(0,Assumptions!$C$6-G55)))) | AC55: =IF(Y55=1,Q55-F55,"") | AD55: =IF(Y55=1,AC55^2,"") | AE55: =IF(Z55=1,(H55-M55)*I55,0) | AF55: =IF(G55<EDATE(Assumptions!$C$6,-12)+1,"prior_12m","last_12m") | AG55: =DATE(YEAR(G55),MONTH(G55),1)
A56: SPO-00026-1 | B56: SPO-00026 | C56: SUP-06 | D56: MRO | E56: MRO-06 | F56: 45571 | G56: 45579 | H56: 183 | I56: 5.83 | J56: 6.1 | K56: 0 | L56: 0 | M56: 183 | N56: 183 | O56: 0 | P56: 45576 | Q56: 45576 | R56: 45576 | S56: =H56*I56 | T56: =H56*J56 | U56: =IF(AND(K56=0,G56<=Assumptions!$C$6),1,0) | V56: =IF(U56=1,IF(M56>0,IF(P56<=G56+Assumptions!$C$7,1,0),0),0) | W56: =IF(AND(U56=1,M56>=H56*(1-Assumptions!$C$8)),1,0) | X56: =IF(AND(U56=1,N56>=H56*(1-Assumptions!$C$8)),1,0) | Y56: =IF(ISNUMBER(Q56),1,0) | Z56: =IF(AND(K56=0,L56=0,Y56=0),1,0) | AA56: =IF(AND(Z56=1,G56<Assumptions!$C$6),1,0) | AB56: =IF(U56=0,"",IF(Y56=1,MAX(0,Q56-G56),IF(L56=1,MAX(0,R56-G56),MAX(0,Assumptions!$C$6-G56)))) | AC56: =IF(Y56=1,Q56-F56,"") | AD56: =IF(Y56=1,AC56^2,"") | AE56: =IF(Z56=1,(H56-M56)*I56,0) | AF56: =IF(G56<EDATE(Assumptions!$C$6,-12)+1,"prior_12m","last_12m") | AG56: =DATE(YEAR(G56),MONTH(G56),1)
A57: SPO-00026-2 | B57: SPO-00026 | C57: SUP-06 | D57: MRO | E57: MRO-03 | F57: 45571 | G57: 45579 | H57: 153 | I57: 8.81 | J57: 8.9 | K57: 0 | L57: 0 | M57: 153 | N57: 153 | O57: 0 | P57: 45575 | Q57: 45575 | R57: 45575 | S57: =H57*I57 | T57: =H57*J57 | U57: =IF(AND(K57=0,G57<=Assumptions!$C$6),1,0) | V57: =IF(U57=1,IF(M57>0,IF(P57<=G57+Assumptions!$C$7,1,0),0),0) | W57: =IF(AND(U57=1,M57>=H57*(1-Assumptions!$C$8)),1,0) | X57: =IF(AND(U57=1,N57>=H57*(1-Assumptions!$C$8)),1,0) | Y57: =IF(ISNUMBER(Q57),1,0) | Z57: =IF(AND(K57=0,L57=0,Y57=0),1,0) | AA57: =IF(AND(Z57=1,G57<Assumptions!$C$6),1,0) | AB57: =IF(U57=0,"",IF(Y57=1,MAX(0,Q57-G57),IF(L57=1,MAX(0,R57-G57),MAX(0,Assumptions!$C$6-G57)))) | AC57: =IF(Y57=1,Q57-F57,"") | AD57: =IF(Y57=1,AC57^2,"") | AE57: =IF(Z57=1,(H57-M57)*I57,0) | AF57: =IF(G57<EDATE(Assumptions!$C$6,-12)+1,"prior_12m","last_12m") | AG57: =DATE(YEAR(G57),MONTH(G57),1)
A58: SPO-00026-3 | B58: SPO-00026 | C58: SUP-06 | D58: MRO | E58: MRO-01 | F58: 45571 | G58: 45579 | H58: 53 | I58: 51.36 | J58: 52 | K58: 0 | L58: 0 | M58: 53 | N58: 53 | O58: 0 | P58: 45577 | Q58: 45577 | R58: 45577 | S58: =H58*I58 | T58: =H58*J58 | U58: =IF(AND(K58=0,G58<=Assumptions!$C$6),1,0) | V58: =IF(U58=1,IF(M58>0,IF(P58<=G58+Assumptions!$C$7,1,0),0),0) | W58: =IF(AND(U58=1,M58>=H58*(1-Assumptions!$C$8)),1,0) | X58: =IF(AND(U58=1,N58>=H58*(1-Assumptions!$C$8)),1,0) | Y58: =IF(ISNUMBER(Q58),1,0) | Z58: =IF(AND(K58=0,L58=0,Y58=0),1,0) | AA58: =IF(AND(Z58=1,G58<Assumptions!$C$6),1,0) | AB58: =IF(U58=0,"",IF(Y58=1,MAX(0,Q58-G58),IF(L58=1,MAX(0,R58-G58),MAX(0,Assumptions!$C$6-G58)))) | AC58: =IF(Y58=1,Q58-F58,"") | AD58: =IF(Y58=1,AC58^2,"") | AE58: =IF(Z58=1,(H58-M58)*I58,0) | AF58: =IF(G58<EDATE(Assumptions!$C$6,-12)+1,"prior_12m","last_12m") | AG58: =DATE(YEAR(G58),MONTH(G58),1)
A59: SPO-00027-1 | B59: SPO-00027 | C59: SUP-01 | D59: ELEC | E59: ELEC-04 | F59: 45572 | G59: 45590 | H59: 40 | I59: 72.7 | J59: 72 | K59: 0 | L59: 0 | M59: 40 | N59: 40 | O59: 0 | P59: 45585 | Q59: 45585 | R59: 45585 | S59: =H59*I59 | T59: =H59*J59 | U59: =IF(AND(K59=0,G59<=Assumptions!$C$6),1,0) | V59: =IF(U59=1,IF(M59>0,IF(P59<=G59+Assumptions!$C$7,1,0),0),0) | W59: =IF(AND(U59=1,M59>=H59*(1-Assumptions!$C$8)),1,0) | X59: =IF(AND(U59=1,N59>=H59*(1-Assumptions!$C$8)),1,0) | Y59: =IF(ISNUMBER(Q59),1,0) | Z59: =IF(AND(K59=0,L59=0,Y59=0),1,0) | AA59: =IF(AND(Z59=1,G59<Assumptions!$C$6),1,0) | AB59: =IF(U59=0,"",IF(Y59=1,MAX(0,Q59-G59),IF(L59=1,MAX(0,R59-G59),MAX(0,Assumptions!$C$6-G59)))) | AC59: =IF(Y59=1,Q59-F59,"") | AD59: =IF(Y59=1,AC59^2,"") | AE59: =IF(Z59=1,(H59-M59)*I59,0) | AF59: =IF(G59<EDATE(Assumptions!$C$6,-12)+1,"prior_12m","last_12m") | AG59: =DATE(YEAR(G59),MONTH(G59),1)
A60: SPO-00028-1 | B60: SPO-00028 | C60: SUP-10 | D60: PPE | E60: PPE-05 | F60: 45572 | G60: 45585 | H60: 189 | I60: 10.92 | J60: 11 | K60: 0 | L60: 0 | M60: 189 | N60: 89 | O60: 0 | P60: 45582 | Q60: 45590 | R60: 45590 | S60: =H60*I60 | T60: =H60*J60 | U60: =IF(AND(K60=0,G60<=Assumptions!$C$6),1,0) | V60: =IF(U60=1,IF(M60>0,IF(P60<=G60+Assumptions!$C$7,1,0),0),0) | W60: =IF(AND(U60=1,M60>=H60*(1-Assumptions!$C$8)),1,0) | X60: =IF(AND(U60=1,N60>=H60*(1-Assumptions!$C$8)),1,0) | Y60: =IF(ISNUMBER(Q60),1,0) | Z60: =IF(AND(K60=0,L60=0,Y60=0),1,0) | AA60: =IF(AND(Z60=1,G60<Assumptions!$C$6),1,0) | AB60: =IF(U60=0,"",IF(Y60=1,MAX(0,Q60-G60),IF(L60=1,MAX(0,R60-G60),MAX(0,Assumptions!$C$6-G60)))) | AC60: =IF(Y60=1,Q60-F60,"") | AD60: =IF(Y60=1,AC60^2,"") | AE60: =IF(Z60=1,(H60-M60)*I60,0) | AF60: =IF(G60<EDATE(Assumptions!$C$6,-12)+1,"prior_12m","last_12m") | AG60: =DATE(YEAR(G60),MONTH(G60),1)
A61: SPO-00029-1 | B61: SPO-00029 | C61: SUP-01 | D61: ELEC | E61: ELEC-04 | F61: 45573 | G61: 45591 | H61: 73 | I61: 69.24 | J61: 72 | K61: 0 | L61: 0 | M61: 73 | N61: 73 | O61: 0 | P61: 45585 | Q61: 45585 | R61: 45585 | S61: =H61*I61 | T61: =H61*J61 | U61: =IF(AND(K61=0,G61<=Assumptions!$C$6),1,0) | V61: =IF(U61=1,IF(M61>0,IF(P61<=G61+Assumptions!$C$7,1,0),0),0) | W61: =IF(AND(U61=1,M61>=H61*(1-Assumptions!$C$8)),1,0) | X61: =IF(AND(U61=1,N61>=H61*(1-Assumptions!$C$8)),1,0) | Y61: =IF(ISNUMBER(Q61),1,0) | Z61: =IF(AND(K61=0,L61=0,Y61=0),1,0) | AA61: =IF(AND(Z61=1,G61<Assumptions!$C$6),1,0) | AB61: =IF(U61=0,"",IF(Y61=1,MAX(0,Q61-G61),IF(L61=1,MAX(0,R61-G61),MAX(0,Assumptions!$C$6-G61)))) | AC61: =IF(Y61=1,Q61-F61,"") | AD61: =IF(Y61=1,AC61^2,"") | AE61: =IF(Z61=1,(H61-M61)*I61,0) | AF61: =IF(G61<EDATE(Assumptions!$C$6,-12)+1,"prior_12m","last_12m") | AG61: =DATE(YEAR(G61),MONTH(G61),1)
A62: SPO-00029-2 | B62: SPO-00029 | C62: SUP-01 | D62: ELEC | E62: ELEC-05 | F62: 45573 | G62: 45591 | H62: 402 | I62: 11.87 | J62: 11.5 | K62: 1 | L62: 0 | M62: 0 | N62: 0 | O62: 0 | S62: =H62*I62 | T62: =H62*J62 | U62: =IF(AND(K62=0,G62<=Assumptions!$C$6),1,0) | V62: =IF(U62=1,IF(M62>0,IF(P62<=G62+Assumptions!$C$7,1,0),0),0) | W62: =IF(AND(U62=1,M62>=H62*(1-Assumptions!$C$8)),1,0) | X62: =IF(AND(U62=1,N62>=H62*(1-Assumptions!$C$8)),1,0) | Y62: =IF(ISNUMBER(Q62),1,0) | Z62: =IF(AND(K62=0,L62=0,Y62=0),1,0) | AA62: =IF(AND(Z62=1,G62<Assumptions!$C$6),1,0) | AB62: =IF(U62=0,"",IF(Y62=1,MAX(0,Q62-G62),IF(L62=1,MAX(0,R62-G62),MAX(0,Assumptions!$C$6-G62)))) | AC62: =IF(Y62=1,Q62-F62,"") | AD62: =IF(Y62=1,AC62^2,"") | AE62: =IF(Z62=1,(H62-M62)*I62,0) | AF62: =IF(G62<EDATE(Assumptions!$C$6,-12)+1,"prior_12m","last_12m") | AG62: =DATE(YEAR(G62),MONTH(G62),1)
A63: SPO-00029-3 | B63: SPO-00029 | C63: SUP-01 | D63: ELEC | E63: ELEC-08 | F63: 45573 | G63: 45591 | H63: 288 | I63: 18.32 | J63: 18 | K63: 0 | L63: 0 | M63: 288 | N63: 288 | O63: 0 | P63: 45585 | Q63: 45585 | R63: 45585 | S63: =H63*I63 | T63: =H63*J63 | U63: =IF(AND(K63=0,G63<=Assumptions!$C$6),1,0) | V63: =IF(U63=1,IF(M63>0,IF(P63<=G63+Assumptions!$C$7,1,0),0),0) | W63: =IF(AND(U63=1,M63>=H63*(1-Assumptions!$C$8)),1,0) | X63: =IF(AND(U63=1,N63>=H63*(1-Assumptions!$C$8)),1,0) | Y63: =IF(ISNUMBER(Q63),1,0) | Z63: =IF(AND(K63=0,L63=0,Y63=0),1,0) | AA63: =IF(AND(Z63=1,G63<Assumptions!$C$6),1,0) | AB63: =IF(U63=0,"",IF(Y63=1,MAX(0,Q63-G63),IF(L63=1,MAX(0,R63-G63),MAX(0,Assumptions!$C$6-G63)))) | AC63: =IF(Y63=1,Q63-F63,"") | AD63: =IF(Y63=1,AC63^2,"") | AE63: =IF(Z63=1,(H63-M63)*I63,0) | AF63: =IF(G63<EDATE(Assumptions!$C$6,-12)+1,"prior_12m","last_12m") | AG63: =DATE(YEAR(G63),MONTH(G63),1)
A64: SPO-00030-1 | B64: SPO-00030 | C64: SUP-01 | D64: ELEC | E64: ELEC-07 | F64: 45573 | G64: 45591 | H64: 218 | I64: 10 | J64: 9.8 | K64: 0 | L64: 0 | M64: 218 | N64: 218 | O64: 0 | P64: 45590 | Q64: 45590 | R64: 45590 | S64: =H64*I64 | T64: =H64*J64 | U64: =IF(AND(K64=0,G64<=Assumptions!$C$6),1,0) | V64: =IF(U64=1,IF(M64>0,IF(P64<=G64+Assumptions!$C$7,1,0),0),0) | W64: =IF(AND(U64=1,M64>=H64*(1-Assumptions!$C$8)),1,0) | X64: =IF(AND(U64=1,N64>=H64*(1-Assumptions!$C$8)),1,0) | Y64: =IF(ISNUMBER(Q64),1,0) | Z64: =IF(AND(K64=0,L64=0,Y64=0),1,0) | AA64: =IF(AND(Z64=1,G64<Assumptions!$C$6),1,0) | AB64: =IF(U64=0,"",IF(Y64=1,MAX(0,Q64-G64),IF(L64=1,MAX(0,R64-G64),MAX(0,Assumptions!$C$6-G64)))) | AC64: =IF(Y64=1,Q64-F64,"") | AD64: =IF(Y64=1,AC64^2,"") | AE64: =IF(Z64=1,(H64-M64)*I64,0) | AF64: =IF(G64<EDATE(Assumptions!$C$6,-12)+1,"prior_12m","last_12m") | AG64: =DATE(YEAR(G64),MONTH(G64),1)
A65: SPO-00030-2 | B65: SPO-00030 | C65: SUP-01 | D65: ELEC | E65: ELEC-08 | F65: 45573 | G65: 45591 | H65: 79 | I65: 17.6 | J65: 18 | K65: 0 | L65: 0 | M65: 79 | N65: 79 | O65: 0 | P65: 45591 | Q65: 45591 | R65: 45591 | S65: =H65*I65 | T65: =H65*J65 | U65: =IF(AND(K65=0,G65<=Assumptions!$C$6),1,0) | V65: =IF(U65=1,IF(M65>0,IF(P65<=G65+Assumptions!$C$7,1,0),0),0) | W65: =IF(AND(U65=1,M65>=H65*(1-Assumptions!$C$8)),1,0) | X65: =IF(AND(U65=1,N65>=H65*(1-Assumptions!$C$8)),1,0) | Y65: =IF(ISNUMBER(Q65),1,0) | Z65: =IF(AND(K65=0,L65=0,Y65=0),1,0) | AA65: =IF(AND(Z65=1,G65<Assumptions!$C$6),1,0) | AB65: =IF(U65=0,"",IF(Y65=1,MAX(0,Q65-G65),IF(L65=1,MAX(0,R65-G65),MAX(0,Assumptions!$C$6-G65)))) | AC65: =IF(Y65=1,Q65-F65,"") | AD65: =IF(Y65=1,AC65^2,"") | AE65: =IF(Z65=1,(H65-M65)*I65,0) | AF65: =IF(G65<EDATE(Assumptions!$C$6,-12)+1,"prior_12m","last_12m") | AG65: =DATE(YEAR(G65),MONTH(G65),1)
A66: SPO-00031-1 | B66: SPO-00031 | C66: SUP-12 | D66: IT | E66: IT-08 | F66: 45574 | G66: 45584 | H66: 3 | I66: 274.38 | J66: 245 | K66: 0 | L66: 0 | M66: 3 | N66: 3 | O66: 0 | P66: 45579 | Q66: 45579 | R66: 45579 | S66: =H66*I66 | T66: =H66*J66 | U66: =IF(AND(K66=0,G66<=Assumptions!$C$6),1,0) | V66: =IF(U66=1,IF(M66>0,IF(P66<=G66+Assumptions!$C$7,1,0),0),0) | W66: =IF(AND(U66=1,M66>=H66*(1-Assumptions!$C$8)),1,0) | X66: =IF(AND(U66=1,N66>=H66*(1-Assumptions!$C$8)),1,0) | Y66: =IF(ISNUMBER(Q66),1,0) | Z66: =IF(AND(K66=0,L66=0,Y66=0),1,0) | AA66: =IF(AND(Z66=1,G66<Assumptions!$C$6),1,0) | AB66: =IF(U66=0,"",IF(Y66=1,MAX(0,Q66-G66),IF(L66=1,MAX(0,R66-G66),MAX(0,Assumptions!$C$6-G66)))) | AC66: =IF(Y66=1,Q66-F66,"") | AD66: =IF(Y66=1,AC66^2,"") | AE66: =IF(Z66=1,(H66-M66)*I66,0) | AF66: =IF(G66<EDATE(Assumptions!$C$6,-12)+1,"prior_12m","last_12m") | AG66: =DATE(YEAR(G66),MONTH(G66),1)
A67: SPO-00031-2 | B67: SPO-00031 | C67: SUP-12 | D67: IT | E67: IT-03 | F67: 45574 | G67: 45584 | H67: 81 | I67: 43.78 | J67: 38 | K67: 0 | L67: 0 | M67: 81 | N67: 81 | O67: 0 | P67: 45584 | Q67: 45584 | R67: 45584 | S67: =H67*I67 | T67: =H67*J67 | U67: =IF(AND(K67=0,G67<=Assumptions!$C$6),1,0) | V67: =IF(U67=1,IF(M67>0,IF(P67<=G67+Assumptions!$C$7,1,0),0),0) | W67: =IF(AND(U67=1,M67>=H67*(1-Assumptions!$C$8)),1,0) | X67: =IF(AND(U67=1,N67>=H67*(1-Assumptions!$C$8)),1,0) | Y67: =IF(ISNUMBER(Q67),1,0) | Z67: =IF(AND(K67=0,L67=0,Y67=0),1,0) | AA67: =IF(AND(Z67=1,G67<Assumptions!$C$6),1,0) | AB67: =IF(U67=0,"",IF(Y67=1,MAX(0,Q67-G67),IF(L67=1,MAX(0,R67-G67),MAX(0,Assumptions!$C$6-G67)))) | AC67: =IF(Y67=1,Q67-F67,"") | AD67: =IF(Y67=1,AC67^2,"") | AE67: =IF(Z67=1,(H67-M67)*I67,0) | AF67: =IF(G67<EDATE(Assumptions!$C$6,-12)+1,"prior_12m","last_12m") | AG67: =DATE(YEAR(G67),MONTH(G67),1)
A68: SPO-00032-1 | B68: SPO-00032 | C68: SUP-01 | D68: ELEC | E68: ELEC-08 | F68: 45575 | G68: 45593 | H68: 191 | I68: 18.07 | J68: 18 | K68: 0 | L68: 0 | M68: 191 | N68: 191 | O68: 0 | P68: 45590 | Q68: 45590 | R68: 45590 | S68: =H68*I68 | T68: =H68*J68 | U68: =IF(AND(K68=0,G68<=Assumptions!$C$6),1,0) | V68: =IF(U68=1,IF(M68>0,IF(P68<=G68+Assumptions!$C$7,1,0),0),0) | W68: =IF(AND(U68=1,M68>=H68*(1-Assumptions!$C$8)),1,0) | X68: =IF(AND(U68=1,N68>=H68*(1-Assumptions!$C$8)),1,0) | Y68: =IF(ISNUMBER(Q68),1,0) | Z68: =IF(AND(K68=0,L68=0,Y68=0),1,0) | AA68: =IF(AND(Z68=1,G68<Assumptions!$C$6),1,0) | AB68: =IF(U68=0,"",IF(Y68=1,MAX(0,Q68-G68),IF(L68=1,MAX(0,R68-G68),MAX(0,Assumptions!$C$6-G68)))) | AC68: =IF(Y68=1,Q68-F68,"") | AD68: =IF(Y68=1,AC68^2,"") | AE68: =IF(Z68=1,(H68-M68)*I68,0) | AF68: =IF(G68<EDATE(Assumptions!$C$6,-12)+1,"prior_12m","last_12m") | AG68: =DATE(YEAR(G68),MONTH(G68),1)
A69: SPO-00033-1 | B69: SPO-00033 | C69: SUP-06 | D69: MRO | E69: MRO-04 | F69: 45575 | G69: 45583 | H69: 55 | I69: 56.95 | J69: 58 | K69: 0 | L69: 0 | M69: 55 | N69: 55 | O69: 0 | P69: 45580 | Q69: 45580 | R69: 45580 | S69: =H69*I69 | T69: =H69*J69 | U69: =IF(AND(K69=0,G69<=Assumptions!$C$6),1,0) | V69: =IF(U69=1,IF(M69>0,IF(P69<=G69+Assumptions!$C$7,1,0),0),0) | W69: =IF(AND(U69=1,M69>=H69*(1-Assumptions!$C$8)),1,0) | X69: =IF(AND(U69=1,N69>=H69*(1-Assumptions!$C$8)),1,0) | Y69: =IF(ISNUMBER(Q69),1,0) | Z69: =IF(AND(K69=0,L69=0,Y69=0),1,0) | AA69: =IF(AND(Z69=1,G69<Assumptions!$C$6),1,0) | AB69: =IF(U69=0,"",IF(Y69=1,MAX(0,Q69-G69),IF(L69=1,MAX(0,R69-G69),MAX(0,Assumptions!$C$6-G69)))) | AC69: =IF(Y69=1,Q69-F69,"") | AD69: =IF(Y69=1,AC69^2,"") | AE69: =IF(Z69=1,(H69-M69)*I69,0) | AF69: =IF(G69<EDATE(Assumptions!$C$6,-12)+1,"prior_12m","last_12m") | AG69: =DATE(YEAR(G69),MONTH(G69),1)
A70: SPO-00033-2 | B70: SPO-00033 | C70: SUP-06 | D70: MRO | E70: MRO-01 | F70: 45575 | G70: 45583 | H70: 37 | I70: 52.47 | J70: 52 | K70: 0 | L70: 0 | M70: 37 | N70: 37 | O70: 0 | P70: 45582 | Q70: 45582 | R70: 45582 | S70: =H70*I70 | T70: =H70*J70 | U70: =IF(AND(K70=0,G70<=Assumptions!$C$6),1,0) | V70: =IF(U70=1,IF(M70>0,IF(P70<=G70+Assumptions!$C$7,1,0),0),0) | W70: =IF(AND(U70=1,M70>=H70*(1-Assumptions!$C$8)),1,0) | X70: =IF(AND(U70=1,N70>=H70*(1-Assumptions!$C$8)),1,0) | Y70: =IF(ISNUMBER(Q70),1,0) | Z70: =IF(AND(K70=0,L70=0,Y70=0),1,0) | AA70: =IF(AND(Z70=1,G70<Assumptions!$C$6),1,0) | AB70: =IF(U70=0,"",IF(Y70=1,MAX(0,Q70-G70),IF(L70=1,MAX(0,R70-G70),MAX(0,Assumptions!$C$6-G70)))) | AC70: =IF(Y70=1,Q70-F70,"") | AD70: =IF(Y70=1,AC70^2,"") | AE70: =IF(Z70=1,(H70-M70)*I70,0) | AF70: =IF(G70<EDATE(Assumptions!$C$6,-12)+1,"prior_12m","last_12m") | AG70: =DATE(YEAR(G70),MONTH(G70),1)
A71: SPO-00033-3 | B71: SPO-00033 | C71: SUP-06 | D71: MRO | E71: MRO-03 | F71: 45575 | G71: 45583 | H71: 168 | I71: 8.66 | J71: 8.9 | K71: 0 | L71: 0 | M71: 168 | N71: 168 | O71: 0 | P71: 45581 | Q71: 45581 | R71: 45581 | S71: =H71*I71 | T71: =H71*J71 | U71: =IF(AND(K71=0,G71<=Assumptions!$C$6),1,0) | V71: =IF(U71=1,IF(M71>0,IF(P71<=G71+Assumptions!$C$7,1,0),0),0) | W71: =IF(AND(U71=1,M71>=H71*(1-Assumptions!$C$8)),1,0) | X71: =IF(AND(U71=1,N71>=H71*(1-Assumptions!$C$8)),1,0) | Y71: =IF(ISNUMBER(Q71),1,0) | Z71: =IF(AND(K71=0,L71=0,Y71=0),1,0) | AA71: =IF(AND(Z71=1,G71<Assumptions!$C$6),1,0) | AB71: =IF(U71=0,"",IF(Y71=1,MAX(0,Q71-G71),IF(L71=1,MAX(0,R71-G71),MAX(0,Assumptions!$C$6-G71)))) | AC71: =IF(Y71=1,Q71-F71,"") | AD71: =IF(Y71=1,AC71^2,"") | AE71: =IF(Z71=1,(H71-M71)*I71,0) | AF71: =IF(G71<EDATE(Assumptions!$C$6,-12)+1,"prior_12m","last_12m") | AG71: =DATE(YEAR(G71),MONTH(G71),1)
A72: SPO-00034-1 | B72: SPO-00034 | C72: SUP-02 | D72: ELEC | E72: ELEC-05 | F72: 45575 | G72: 45591 | H72: 81 | I72: 11.4 | J72: 11.5 | K72: 0 | L72: 0 | M72: 81 | N72: 81 | O72: 0 | P72: 45590 | Q72: 45590 | R72: 45590 | S72: =H72*I72 | T72: =H72*J72 | U72: =IF(AND(K72=0,G72<=Assumptions!$C$6),1,0) | V72: =IF(U72=1,IF(M72>0,IF(P72<=G72+Assumptions!$C$7,1,0),0),0) | W72: =IF(AND(U72=1,M72>=H72*(1-Assumptions!$C$8)),1,0) | X72: =IF(AND(U72=1,N72>=H72*(1-Assumptions!$C$8)),1,0) | Y72: =IF(ISNUMBER(Q72),1,0) | Z72: =IF(AND(K72=0,L72=0,Y72=0),1,0) | AA72: =IF(AND(Z72=1,G72<Assumptions!$C$6),1,0) | AB72: =IF(U72=0,"",IF(Y72=1,MAX(0,Q72-G72),IF(L72=1,MAX(0,R72-G72),MAX(0,Assumptions!$C$6-G72)))) | AC72: =IF(Y72=1,Q72-F72,"") | AD72: =IF(Y72=1,AC72^2,"") | AE72: =IF(Z72=1,(H72-M72)*I72,0) | AF72: =IF(G72<EDATE(Assumptions!$C$6,-12)+1,"prior_12m","last_12m") | AG72: =DATE(YEAR(G72),MONTH(G72),1)
A73: SPO-00034-2 | B73: SPO-00034 | C73: SUP-02 | D73: ELEC | E73: ELEC-04 | F73: 45575 | G73: 45591 | H73: 23 | I73: 67.78 | J73: 72 | K73: 0 | L73: 0 | M73: 23 | N73: 23 | O73: 0 | P73: 45587 | Q73: 45587 | R73: 45587 | S73: =H73*I73 | T73: =H73*J73 | U73: =IF(AND(K73=0,G73<=Assumptions!$C$6),1,0) | V73: =IF(U73=1,IF(M73>0,IF(P73<=G73+Assumptions!$C$7,1,0),0),0) | W73: =IF(AND(U73=1,M73>=H73*(1-Assumptions!$C$8)),1,0) | X73: =IF(AND(U73=1,N73>=H73*(1-Assumptions!$C$8)),1,0) | Y73: =IF(ISNUMBER(Q73),1,0) | Z73: =IF(AND(K73=0,L73=0,Y73=0),1,0) | AA73: =IF(AND(Z73=1,G73<Assumptions!$C$6),1,0) | AB73: =IF(U73=0,"",IF(Y73=1,MAX(0,Q73-G73),IF(L73=1,MAX(0,R73-G73),MAX(0,Assumptions!$C$6-G73)))) | AC73: =IF(Y73=1,Q73-F73,"") | AD73: =IF(Y73=1,AC73^2,"") | AE73: =IF(Z73=1,(H73-M73)*I73,0) | AF73: =IF(G73<EDATE(Assumptions!$C$6,-12)+1,"prior_12m","last_12m") | AG73: =DATE(YEAR(G73),MONTH(G73),1)
A74: SPO-00035-1 | B74: SPO-00035 | C74: SUP-14 | D74: FLEET | E74: FLEET-07 | F74: 45575 | G74: 45589 | H74: 7 | I74: 115.4 | J74: 118 | K74: 0 | L74: 0 | M74: 7 | N74: 7 | O74: 2 | P74: 45583 | Q74: 45583 | R74: 45583 | S74: =H74*I74 | T74: =H74*J74 | U74: =IF(AND(K74=0,G74<=Assumptions!$C$6),1,0) | V74: =IF(U74=1,IF(M74>0,IF(P74<=G74+Assumptions!$C$7,1,0),0),0) | W74: =IF(AND(U74=1,M74>=H74*(1-Assumptions!$C$8)),1,0) | X74: =IF(AND(U74=1,N74>=H74*(1-Assumptions!$C$8)),1,0) | Y74: =IF(ISNUMBER(Q74),1,0) | Z74: =IF(AND(K74=0,L74=0,Y74=0),1,0) | AA74: =IF(AND(Z74=1,G74<Assumptions!$C$6),1,0) | AB74: =IF(U74=0,"",IF(Y74=1,MAX(0,Q74-G74),IF(L74=1,MAX(0,R74-G74),MAX(0,Assumptions!$C$6-G74)))) | AC74: =IF(Y74=1,Q74-F74,"") | AD74: =IF(Y74=1,AC74^2,"") | AE74: =IF(Z74=1,(H74-M74)*I74,0) | AF74: =IF(G74<EDATE(Assumptions!$C$6,-12)+1,"prior_12m","last_12m") | AG74: =DATE(YEAR(G74),MONTH(G74),1)
... A102: SPO-00050-1 | B102: SPO-00050 | C102: SUP-08 | D102: PPE | E102: PPE-03 | F102: 45577 | G102: 45588 | H102: 109 | I102: 20.44 | J102: 21 | K102: 0 | L102: 0 | M102: 109 | N102: 109 | O102: 0 | P102: 45582 | Q102: 45582 | R102: 45582 | S102: =H102*I102 | T102: =H102*J102 | U102: =IF(AND(K102=0,G102<=Assumptions!$C$6),1,0) | V102: =IF(U102=1,IF(M102>0,IF(P102<=G102+Assumptions!$C$7,1,0),0),0) | W102: =IF(AND(U102=1,M102>=H102*(1-Assumptions!$C$8)),1,0) | X102: =IF(AND(U102=1,N102>=H102*(1-Assumptions!$C$8)),1,0) | Y102: =IF(ISNUMBER(Q102),1,0) | Z102: =IF(AND(K102=0,L102=0,Y102=0),1,0) | AA102: =IF(AND(Z102=1,G102<Assumptions!$C$6),1,0) | AB102: =IF(U102=0,"",IF(Y102=1,MAX(0,Q102-G102),IF(L102=1,MAX(0,R102-G102),MAX(0,Assumptions!$C$6-G102)))) | AC102: =IF(Y102=1,Q102-F102,"") | AD102: =IF(Y102=1,AC102^2,"") | AE102: =IF(Z102=1,(H102-M102)*I102,0) | AF102: =IF(G102<EDATE(Assumptions!$C$6,-12)+1,"prior_12m","last_12m") | AG102: =DATE(YEAR(G102),MONTH(G102),1)
A103: SPO-00051-1 | B103: SPO-00051 | C103: SUP-14 | D103: FLEET | E103: FLEET-06 | F103: 45578 | G103: 45592 | H103: 69 | I103: 34.91 | J103: 33 | K103: 1 | L103: 0 | M103: 0 | N103: 0 | O103: 0 | S103: =H103*I103 | T103: =H103*J103 | U103: =IF(AND(K103=0,G103<=Assumptions!$C$6),1,0) | V103: =IF(U103=1,IF(M103>0,IF(P103<=G103+Assumptions!$C$7,1,0),0),0) | W103: =IF(AND(U103=1,M103>=H103*(1-Assumptions!$C$8)),1,0) | X103: =IF(AND(U103=1,N103>=H103*(1-Assumptions!$C$8)),1,0) | Y103: =IF(ISNUMBER(Q103),1,0) | Z103: =IF(AND(K103=0,L103=0,Y103=0),1,0) | AA103: =IF(AND(Z103=1,G103<Assumptions!$C$6),1,0) | AB103: =IF(U103=0,"",IF(Y103=1,MAX(0,Q103-G103),IF(L103=1,MAX(0,R103-G103),MAX(0,Assumptions!$C$6-G103)))) | AC103: =IF(Y103=1,Q103-F103,"") | AD103: =IF(Y103=1,AC103^2,"") | AE103: =IF(Z103=1,(H103-M103)*I103,0) | AF103: =IF(G103<EDATE(Assumptions!$C$6,-12)+1,"prior_12m","last_12m") | AG103: =DATE(YEAR(G103),MONTH(G103),1)
A104: SPO-00052-1 | B104: SPO-00052 | C104: SUP-02 | D104: ELEC | E104: ELEC-03 | F104: 45578 | G104: 45594 | H104: 22 | I104: 98.84 | J104: 96 | K104: 0 | L104: 0 | M104: 22 | N104: 22 | O104: 0 | P104: 45592 | Q104: 45592 | R104: 45592 | S104: =H104*I104 | T104: =H104*J104 | U104: =IF(AND(K104=0,G104<=Assumptions!$C$6),1,0) | V104: =IF(U104=1,IF(M104>0,IF(P104<=G104+Assumptions!$C$7,1,0),0),0) | W104: =IF(AND(U104=1,M104>=H104*(1-Assumptions!$C$8)),1,0) | X104: =IF(AND(U104=1,N104>=H104*(1-Assumptions!$C$8)),1,0) | Y104: =IF(ISNUMBER(Q104),1,0) | Z104: =IF(AND(K104=0,L104=0,Y104=0),1,0) | AA104: =IF(AND(Z104=1,G104<Assumptions!$C$6),1,0) | AB104: =IF(U104=0,"",IF(Y104=1,MAX(0,Q104-G104),IF(L104=1,MAX(0,R104-G104),MAX(0,Assumptions!$C$6-G104)))) | AC104: =IF(Y104=1,Q104-F104,"") | AD104: =IF(Y104=1,AC104^2,"") | AE104: =IF(Z104=1,(H104-M104)*I104,0) | AF104: =IF(G104<EDATE(Assumptions!$C$6,-12)+1,"prior_12m","last_12m") | AG104: =DATE(YEAR(G104),MONTH(G104),1)
A105: SPO-00052-2 | B105: SPO-00052 | C105: SUP-02 | D105: ELEC | E105: ELEC-01 | F105: 45578 | G105: 45594 | H105: 30 | I105: 37.06 | J105: 38 | K105: 0 | L105: 0 | M105: 30 | N105: 30 | O105: 0 | P105: 45591 | Q105: 45591 | R105: 45591 | S105: =H105*I105 | T105: =H105*J105 | U105: =IF(AND(K105=0,G105<=Assumptions!$C$6),1,0) | V105: =IF(U105=1,IF(M105>0,IF(P105<=G105+Assumptions!$C$7,1,0),0),0) | W105: =IF(AND(U105=1,M105>=H105*(1-Assumptions!$C$8)),1,0) | X105: =IF(AND(U105=1,N105>=H105*(1-Assumptions!$C$8)),1,0) | Y105: =IF(ISNUMBER(Q105),1,0) | Z105: =IF(AND(K105=0,L105=0,Y105=0),1,0) | AA105: =IF(AND(Z105=1,G105<Assumptions!$C$6),1,0) | AB105: =IF(U105=0,"",IF(Y105=1,MAX(0,Q105-G105),IF(L105=1,MAX(0,R105-G105),MAX(0,Assumptions!$C$6-G105)))) | AC105: =IF(Y105=1,Q105-F105,"") | AD105: =IF(Y105=1,AC105^2,"") | AE105: =IF(Z105=1,(H105-M105)*I105,0) | AF105: =IF(G105<EDATE(Assumptions!$C$6,-12)+1,"prior_12m","last_12m") | AG105: =DATE(YEAR(G105),MONTH(G105),1)
A106: SPO-00053-1 | B106: SPO-00053 | C106: SUP-05 | D106: FLEET | E106: FLEET-02 | F106: 45578 | G106: 45592 | H106: 178 | I106: 7.34 | J106: 7.5 | K106: 0 | L106: 0 | M106: 178 | N106: 178 | O106: 0 | P106: 45589 | Q106: 45589 | R106: 45589 | S106: =H106*I106 | T106: =H106*J106 | U106: =IF(AND(K106=0,G106<=Assumptions!$C$6),1,0) | V106: =IF(U106=1,IF(M106>0,IF(P106<=G106+Assumptions!$C$7,1,0),0),0) | W106: =IF(AND(U106=1,M106>=H106*(1-Assumptions!$C$8)),1,0) | X106: =IF(AND(U106=1,N106>=H106*(1-Assumptions!$C$8)),1,0) | Y106: =IF(ISNUMBER(Q106),1,0) | Z106: =IF(AND(K106=0,L106=0,Y106=0),1,0) | AA106: =IF(AND(Z106=1,G106<Assumptions!$C$6),1,0) | AB106: =IF(U106=0,"",IF(Y106=1,MAX(0,Q106-G106),IF(L106=1,MAX(0,R106-G106),MAX(0,Assumptions!$C$6-G106)))) | AC106: =IF(Y106=1,Q106-F106,"") | AD106: =IF(Y106=1,AC106^2,"") | AE106: =IF(Z106=1,(H106-M106)*I106,0) | AF106: =IF(G106<EDATE(Assumptions!$C$6,-12)+1,"prior_12m","last_12m") | AG106: =DATE(YEAR(G106),MONTH(G106),1)
A107: SPO-00053-2 | B107: SPO-00053 | C107: SUP-05 | D107: FLEET | E107: FLEET-03 | F107: 45578 | G107: 45592 | H107: 69 | I107: 22.24 | J107: 21 | K107: 0 | L107: 0 | M107: 69 | N107: 69 | O107: 0 | P107: 45589 | Q107: 45589 | R107: 45589 | S107: =H107*I107 | T107: =H107*J107 | U107: =IF(AND(K107=0,G107<=Assumptions!$C$6),1,0) | V107: =IF(U107=1,IF(M107>0,IF(P107<=G107+Assumptions!$C$7,1,0),0),0) | W107: =IF(AND(U107=1,M107>=H107*(1-Assumptions!$C$8)),1,0) | X107: =IF(AND(U107=1,N107>=H107*(1-Assumptions!$C$8)),1,0) | Y107: =IF(ISNUMBER(Q107),1,0) | Z107: =IF(AND(K107=0,L107=0,Y107=0),1,0) | AA107: =IF(AND(Z107=1,G107<Assumptions!$C$6),1,0) | AB107: =IF(U107=0,"",IF(Y107=1,MAX(0,Q107-G107),IF(L107=1,MAX(0,R107-G107),MAX(0,Assumptions!$C$6-G107)))) | AC107: =IF(Y107=1,Q107-F107,"") | AD107: =IF(Y107=1,AC107^2,"") | AE107: =IF(Z107=1,(H107-M107)*I107,0) | AF107: =IF(G107<EDATE(Assumptions!$C$6,-12)+1,"prior_12m","last_12m") | AG107: =DATE(YEAR(G107),MONTH(G107),1)
A108: SPO-00054-1 | B108: SPO-00054 | C108: SUP-08 | D108: MRO | E108: MRO-03 | F108: 45578 | G108: 45589 | H108: 186 | I108: 8.76 | J108: 8.9 | K108: 0 | L108: 0 | M108: 186 | N108: 186 | O108: 0 | P108: 45585 | Q108: 45585 | R108: 45585 | S108: =H108*I108 | T108: =H108*J108 | U108: =IF(AND(K108=0,G108<=Assumptions!$C$6),1,0) | V108: =IF(U108=1,IF(M108>0,IF(P108<=G108+Assumptions!$C$7,1,0),0),0) | W108: =IF(AND(U108=1,M108>=H108*(1-Assumptions!$C$8)),1,0) | X108: =IF(AND(U108=1,N108>=H108*(1-Assumptions!$C$8)),1,0) | Y108: =IF(ISNUMBER(Q108),1,0) | Z108: =IF(AND(K108=0,L108=0,Y108=0),1,0) | AA108: =IF(AND(Z108=1,G108<Assumptions!$C$6),1,0) | AB108: =IF(U108=0,"",IF(Y108=1,MAX(0,Q108-G108),IF(L108=1,MAX(0,R108-G108),MAX(0,Assumptions!$C$6-G108)))) | AC108: =IF(Y108=1,Q108-F108,"") | AD108: =IF(Y108=1,AC108^2,"") | AE108: =IF(Z108=1,(H108-M108)*I108,0) | AF108: =IF(G108<EDATE(Assumptions!$C$6,-12)+1,"prior_12m","last_12m") | AG108: =DATE(YEAR(G108),MONTH(G108),1)
A109: SPO-00055-1 | B109: SPO-00055 | C109: SUP-04 | D109: FLEET | E109: FLEET-06 | F109: 45579 | G109: 45592 | H109: 45 | I109: 31.51 | J109: 33 | K109: 0 | L109: 0 | M109: 45 | N109: 45 | O109: 0 | P109: 45580 | Q109: 45580 | R109: 45580 | S109: =H109*I109 | T109: =H109*J109 | U109: =IF(AND(K109=0,G109<=Assumptions!$C$6),1,0) | V109: =IF(U109=1,IF(M109>0,IF(P109<=G109+Assumptions!$C$7,1,0),0),0) | W109: =IF(AND(U109=1,M109>=H109*(1-Assumptions!$C$8)),1,0) | X109: =IF(AND(U109=1,N109>=H109*(1-Assumptions!$C$8)),1,0) | Y109: =IF(ISNUMBER(Q109),1,0) | Z109: =IF(AND(K109=0,L109=0,Y109=0),1,0) | AA109: =IF(AND(Z109=1,G109<Assumptions!$C$6),1,0) | AB109: =IF(U109=0,"",IF(Y109=1,MAX(0,Q109-G109),IF(L109=1,MAX(0,R109-G109),MAX(0,Assumptions!$C$6-G109)))) | AC109: =IF(Y109=1,Q109-F109,"") | AD109: =IF(Y109=1,AC109^2,"") | AE109: =IF(Z109=1,(H109-M109)*I109,0) | AF109: =IF(G109<EDATE(Assumptions!$C$6,-12)+1,"prior_12m","last_12m") | AG109: =DATE(YEAR(G109),MONTH(G109),1)
A110: SPO-00055-2 | B110: SPO-00055 | C110: SUP-04 | D110: FLEET | E110: FLEET-03 | F110: 45579 | G110: 45592 | H110: 60 | I110: 20.19 | J110: 21 | K110: 0 | L110: 0 | M110: 60 | N110: 60 | O110: 0 | P110: 45582 | Q110: 45582 | R110: 45582 | S110: =H110*I110 | T110: =H110*J110 | U110: =IF(AND(K110=0,G110<=Assumptions!$C$6),1,0) | V110: =IF(U110=1,IF(M110>0,IF(P110<=G110+Assumptions!$C$7,1,0),0),0) | W110: =IF(AND(U110=1,M110>=H110*(1-Assumptions!$C$8)),1,0) | X110: =IF(AND(U110=1,N110>=H110*(1-Assumptions!$C$8)),1,0) | Y110: =IF(ISNUMBER(Q110),1,0) | Z110: =IF(AND(K110=0,L110=0,Y110=0),1,0) | AA110: =IF(AND(Z110=1,G110<Assumptions!$C$6),1,0) | AB110: =IF(U110=0,"",IF(Y110=1,MAX(0,Q110-G110),IF(L110=1,MAX(0,R110-G110),MAX(0,Assumptions!$C$6-G110)))) | AC110: =IF(Y110=1,Q110-F110,"") | AD110: =IF(Y110=1,AC110^2,"") | AE110: =IF(Z110=1,(H110-M110)*I110,0) | AF110: =IF(G110<EDATE(Assumptions!$C$6,-12)+1,"prior_12m","last_12m") | AG110: =DATE(YEAR(G110),MONTH(G110),1)
A111: SPO-00055-3 | B111: SPO-00055 | C111: SUP-04 | D111: FLEET | E111: FLEET-02 | F111: 45579 | G111: 45592 | H111: 94 | I111: 7.13 | J111: 7.5 | K111: 0 | L111: 0 | M111: 94 | N111: 94 | O111: 0 | P111: 45592 | Q111: 45592 | R111: 45592 | S111: =H111*I111 | T111: =H111*J111 | U111: =IF(AND(K111=0,G111<=Assumptions!$C$6),1,0) | V111: =IF(U111=1,IF(M111>0,IF(P111<=G111+Assumptions!$C$7,1,0),0),0) | W111: =IF(AND(U111=1,M111>=H111*(1-Assumptions!$C$8)),1,0) | X111: =IF(AND(U111=1,N111>=H111*(1-Assumptions!$C$8)),1,0) | Y111: =IF(ISNUMBER(Q111),1,0) | Z111: =IF(AND(K111=0,L111=0,Y111=0),1,0) | AA111: =IF(AND(Z111=1,G111<Assumptions!$C$6),1,0) | AB111: =IF(U111=0,"",IF(Y111=1,MAX(0,Q111-G111),IF(L111=1,MAX(0,R111-G111),MAX(0,Assumptions!$C$6-G111)))) | AC111: =IF(Y111=1,Q111-F111,"") | AD111: =IF(Y111=1,AC111^2,"") | AE111: =IF(Z111=1,(H111-M111)*I111,0) | AF111: =IF(G111<EDATE(Assumptions!$C$6,-12)+1,"prior_12m","last_12m") | AG111: =DATE(YEAR(G111),MONTH(G111),1)
A112: SPO-00055-4 | B112: SPO-00055 | C112: SUP-04 | D112: FLEET | E112: FLEET-07 | F112: 45579 | G112: 45592 | H112: 12 | I112: 118 | J112: 118 | K112: 0 | L112: 0 | M112: 12 | N112: 0 | O112: 0 | P112: 45595 | Q112: 45595 | R112: 45595 | S112: =H112*I112 | T112: =H112*J112 | U112: =IF(AND(K112=0,G112<=Assumptions!$C$6),1,0) | V112: =IF(U112=1,IF(M112>0,IF(P112<=G112+Assumptions!$C$7,1,0),0),0) | W112: =IF(AND(U112=1,M112>=H112*(1-Assumptions!$C$8)),1,0) | X112: =IF(AND(U112=1,N112>=H112*(1-Assumptions!$C$8)),1,0) | Y112: =IF(ISNUMBER(Q112),1,0) | Z112: =IF(AND(K112=0,L112=0,Y112=0),1,0) | AA112: =IF(AND(Z112=1,G112<Assumptions!$C$6),1,0) | AB112: =IF(U112=0,"",IF(Y112=1,MAX(0,Q112-G112),IF(L112=1,MAX(0,R112-G112),MAX(0,Assumptions!$C$6-G112)))) | AC112: =IF(Y112=1,Q112-F112,"") | AD112: =IF(Y112=1,AC112^2,"") | AE112: =IF(Z112=1,(H112-M112)*I112,0) | AF112: =IF(G112<EDATE(Assumptions!$C$6,-12)+1,"prior_12m","last_12m") | AG112: =DATE(YEAR(G112),MONTH(G112),1)
A113: SPO-00056-1 | B113: SPO-00056 | C113: SUP-09 | D113: CHEM | E113: CHEM-06 | F113: 45579 | G113: 45593 | H113: 5 | I113: 394.54 | J113: 380 | K113: 0 | L113: 0 | M113: 5 | N113: 5 | O113: 0 | P113: 45591 | Q113: 45591 | R113: 45591 | S113: =H113*I113 | T113: =H113*J113 | U113: =IF(AND(K113=0,G113<=Assumptions!$C$6),1,0) | V113: =IF(U113=1,IF(M113>0,IF(P113<=G113+Assumptions!$C$7,1,0),0),0) | W113: =IF(AND(U113=1,M113>=H113*(1-Assumptions!$C$8)),1,0) | X113: =IF(AND(U113=1,N113>=H113*(1-Assumptions!$C$8)),1,0) | Y113: =IF(ISNUMBER(Q113),1,0) | Z113: =IF(AND(K113=0,L113=0,Y113=0),1,0) | AA113: =IF(AND(Z113=1,G113<Assumptions!$C$6),1,0) | AB113: =IF(U113=0,"",IF(Y113=1,MAX(0,Q113-G113),IF(L113=1,MAX(0,R113-G113),MAX(0,Assumptions!$C$6-G113)))) | AC113: =IF(Y113=1,Q113-F113,"") | AD113: =IF(Y113=1,AC113^2,"") | AE113: =IF(Z113=1,(H113-M113)*I113,0) | AF113: =IF(G113<EDATE(Assumptions!$C$6,-12)+1,"prior_12m","last_12m") | AG113: =DATE(YEAR(G113),MONTH(G113),1)
A114: SPO-00056-2 | B114: SPO-00056 | C114: SUP-09 | D114: CHEM | E114: CHEM-02 | F114: 45579 | G114: 45593 | H114: 7 | I114: 412.96 | J114: 410 | K114: 0 | L114: 0 | M114: 7 | N114: 7 | O114: 0 | P114: 45592 | Q114: 45592 | R114: 45592 | S114: =H114*I114 | T114: =H114*J114 | U114: =IF(AND(K114=0,G114<=Assumptions!$C$6),1,0) | V114: =IF(U114=1,IF(M114>0,IF(P114<=G114+Assumptions!$C$7,1,0),0),0) | W114: =IF(AND(U114=1,M114>=H114*(1-Assumptions!$C$8)),1,0) | X114: =IF(AND(U114=1,N114>=H114*(1-Assumptions!$C$8)),1,0) | Y114: =IF(ISNUMBER(Q114),1,0) | Z114: =IF(AND(K114=0,L114=0,Y114=0),1,0) | AA114: =IF(AND(Z114=1,G114<Assumptions!$C$6),1,0) | AB114: =IF(U114=0,"",IF(Y114=1,MAX(0,Q114-G114),IF(L114=1,MAX(0,R114-G114),MAX(0,Assumptions!$C$6-G114)))) | AC114: =IF(Y114=1,Q114-F114,"") | AD114: =IF(Y114=1,AC114^2,"") | AE114: =IF(Z114=1,(H114-M114)*I114,0) | AF114: =IF(G114<EDATE(Assumptions!$C$6,-12)+1,"prior_12m","last_12m") | AG114: =DATE(YEAR(G114),MONTH(G114),1)
A115: SPO-00057-1 | B115: SPO-00057 | C115: SUP-11 | D115: PPE | E115: PPE-03 | F115: 45580 | G115: 45592 | H115: 59 | I115: 20.7 | J115: 21 | K115: 0 | L115: 0 | M115: 59 | N115: 59 | O115: 0 | P115: 45590 | Q115: 45590 | R115: 45590 | S115: =H115*I115 | T115: =H115*J115 | U115: =IF(AND(K115=0,G115<=Assumptions!$C$6),1,0) | V115: =IF(U115=1,IF(M115>0,IF(P115<=G115+Assumptions!$C$7,1,0),0),0) | W115: =IF(AND(U115=1,M115>=H115*(1-Assumptions!$C$8)),1,0) | X115: =IF(AND(U115=1,N115>=H115*(1-Assumptions!$C$8)),1,0) | Y115: =IF(ISNUMBER(Q115),1,0) | Z115: =IF(AND(K115=0,L115=0,Y115=0),1,0) | AA115: =IF(AND(Z115=1,G115<Assumptions!$C$6),1,0) | AB115: =IF(U115=0,"",IF(Y115=1,MAX(0,Q115-G115),IF(L115=1,MAX(0,R115-G115),MAX(0,Assumptions!$C$6-G115)))) | AC115: =IF(Y115=1,Q115-F115,"") | AD115: =IF(Y115=1,AC115^2,"") | AE115: =IF(Z115=1,(H115-M115)*I115,0) | AF115: =IF(G115<EDATE(Assumptions!$C$6,-12)+1,"prior_12m","last_12m") | AG115: =DATE(YEAR(G115),MONTH(G115),1)
... A149: SPO-00077-1 | B149: SPO-00077 | C149: SUP-11 | D149: PPE | E149: PPE-08 | F149: 45584 | G149: 45596 | H149: 38 | I149: 62.43 | J149: 64 | K149: 0 | L149: 0 | M149: 38 | N149: 20 | O149: 0 | P149: 45595 | Q149: 45606 | R149: 45606 | S149: =H149*I149 | T149: =H149*J149 | U149: =IF(AND(K149=0,G149<=Assumptions!$C$6),1,0) | V149: =IF(U149=1,IF(M149>0,IF(P149<=G149+Assumptions!$C$7,1,0),0),0) | W149: =IF(AND(U149=1,M149>=H149*(1-Assumptions!$C$8)),1,0) | X149: =IF(AND(U149=1,N149>=H149*(1-Assumptions!$C$8)),1,0) | Y149: =IF(ISNUMBER(Q149),1,0) | Z149: =IF(AND(K149=0,L149=0,Y149=0),1,0) | AA149: =IF(AND(Z149=1,G149<Assumptions!$C$6),1,0) | AB149: =IF(U149=0,"",IF(Y149=1,MAX(0,Q149-G149),IF(L149=1,MAX(0,R149-G149),MAX(0,Assumptions!$C$6-G149)))) | AC149: =IF(Y149=1,Q149-F149,"") | AD149: =IF(Y149=1,AC149^2,"") | AE149: =IF(Z149=1,(H149-M149)*I149,0) | AF149: =IF(G149<EDATE(Assumptions!$C$6,-12)+1,"prior_12m","last_12m") | AG149: =DATE(YEAR(G149),MONTH(G149),1)
A150: SPO-00078-1 | B150: SPO-00078 | C150: SUP-14 | D150: FLEET | E150: FLEET-01 | F150: 45584 | G150: 45598 | H150: 13 | I150: 67.02 | J150: 64 | K150: 1 | L150: 0 | M150: 0 | N150: 0 | O150: 0 | S150: =H150*I150 | T150: =H150*J150 | U150: =IF(AND(K150=0,G150<=Assumptions!$C$6),1,0) | V150: =IF(U150=1,IF(M150>0,IF(P150<=G150+Assumptions!$C$7,1,0),0),0) | W150: =IF(AND(U150=1,M150>=H150*(1-Assumptions!$C$8)),1,0) | X150: =IF(AND(U150=1,N150>=H150*(1-Assumptions!$C$8)),1,0) | Y150: =IF(ISNUMBER(Q150),1,0) | Z150: =IF(AND(K150=0,L150=0,Y150=0),1,0) | AA150: =IF(AND(Z150=1,G150<Assumptions!$C$6),1,0) | AB150: =IF(U150=0,"",IF(Y150=1,MAX(0,Q150-G150),IF(L150=1,MAX(0,R150-G150),MAX(0,Assumptions!$C$6-G150)))) | AC150: =IF(Y150=1,Q150-F150,"") | AD150: =IF(Y150=1,AC150^2,"") | AE150: =IF(Z150=1,(H150-M150)*I150,0) | AF150: =IF(G150<EDATE(Assumptions!$C$6,-12)+1,"prior_12m","last_12m") | AG150: =DATE(YEAR(G150),MONTH(G150),1)
A151: SPO-00078-2 | B151: SPO-00078 | C151: SUP-14 | D151: FLEET | E151: FLEET-04 | F151: 45584 | G151: 45598 | H151: 169 | I151: 8.41 | J151: 9 | K151: 0 | L151: 0 | M151: 169 | N151: 169 | O151: 0 | P151: 45596 | Q151: 45596 | R151: 45596 | S151: =H151*I151 | T151: =H151*J151 | U151: =IF(AND(K151=0,G151<=Assumptions!$C$6),1,0) | V151: =IF(U151=1,IF(M151>0,IF(P151<=G151+Assumptions!$C$7,1,0),0),0) | W151: =IF(AND(U151=1,M151>=H151*(1-Assumptions!$C$8)),1,0) | X151: =IF(AND(U151=1,N151>=H151*(1-Assumptions!$C$8)),1,0) | Y151: =IF(ISNUMBER(Q151),1,0) | Z151: =IF(AND(K151=0,L151=0,Y151=0),1,0) | AA151: =IF(AND(Z151=1,G151<Assumptions!$C$6),1,0) | AB151: =IF(U151=0,"",IF(Y151=1,MAX(0,Q151-G151),IF(L151=1,MAX(0,R151-G151),MAX(0,Assumptions!$C$6-G151)))) | AC151: =IF(Y151=1,Q151-F151,"") | AD151: =IF(Y151=1,AC151^2,"") | AE151: =IF(Z151=1,(H151-M151)*I151,0) | AF151: =IF(G151<EDATE(Assumptions!$C$6,-12)+1,"prior_12m","last_12m") | AG151: =DATE(YEAR(G151),MONTH(G151),1)
A152: SPO-00079-1 | B152: SPO-00079 | C152: SUP-11 | D152: PPE | E152: PPE-06 | F152: 45585 | G152: 45597 | H152: 12 | I152: 115.44 | J152: 115 | K152: 0 | L152: 0 | M152: 12 | N152: 12 | O152: 0 | P152: 45592 | Q152: 45592 | R152: 45592 | S152: =H152*I152 | T152: =H152*J152 | U152: =IF(AND(K152=0,G152<=Assumptions!$C$6),1,0) | V152: =IF(U152=1,IF(M152>0,IF(P152<=G152+Assumptions!$C$7,1,0),0),0) | W152: =IF(AND(U152=1,M152>=H152*(1-Assumptions!$C$8)),1,0) | X152: =IF(AND(U152=1,N152>=H152*(1-Assumptions!$C$8)),1,0) | Y152: =IF(ISNUMBER(Q152),1,0) | Z152: =IF(AND(K152=0,L152=0,Y152=0),1,0) | AA152: =IF(AND(Z152=1,G152<Assumptions!$C$6),1,0) | AB152: =IF(U152=0,"",IF(Y152=1,MAX(0,Q152-G152),IF(L152=1,MAX(0,R152-G152),MAX(0,Assumptions!$C$6-G152)))) | AC152: =IF(Y152=1,Q152-F152,"") | AD152: =IF(Y152=1,AC152^2,"") | AE152: =IF(Z152=1,(H152-M152)*I152,0) | AF152: =IF(G152<EDATE(Assumptions!$C$6,-12)+1,"prior_12m","last_12m") | AG152: =DATE(YEAR(G152),MONTH(G152),1)
A153: SPO-00079-2 | B153: SPO-00079 | C153: SUP-11 | D153: PPE | E153: PPE-05 | F153: 45585 | G153: 45597 | H153: 75 | I153: 10.51 | J153: 11 | K153: 0 | L153: 0 | M153: 75 | N153: 75 | O153: 0 | P153: 45594 | Q153: 45594 | R153: 45594 | S153: =H153*I153 | T153: =H153*J153 | U153: =IF(AND(K153=0,G153<=Assumptions!$C$6),1,0) | V153: =IF(U153=1,IF(M153>0,IF(P153<=G153+Assumptions!$C$7,1,0),0),0) | W153: =IF(AND(U153=1,M153>=H153*(1-Assumptions!$C$8)),1,0) | X153: =IF(AND(U153=1,N153>=H153*(1-Assumptions!$C$8)),1,0) | Y153: =IF(ISNUMBER(Q153),1,0) | Z153: =IF(AND(K153=0,L153=0,Y153=0),1,0) | AA153: =IF(AND(Z153=1,G153<Assumptions!$C$6),1,0) | AB153: =IF(U153=0,"",IF(Y153=1,MAX(0,Q153-G153),IF(L153=1,MAX(0,R153-G153),MAX(0,Assumptions!$C$6-G153)))) | AC153: =IF(Y153=1,Q153-F153,"") | AD153: =IF(Y153=1,AC153^2,"") | AE153: =IF(Z153=1,(H153-M153)*I153,0) | AF153: =IF(G153<EDATE(Assumptions!$C$6,-12)+1,"prior_12m","last_12m") | AG153: =DATE(YEAR(G153),MONTH(G153),1)
A154: SPO-00079-3 | B154: SPO-00079 | C154: SUP-11 | D154: PPE | E154: PPE-03 | F154: 45585 | G154: 45597 | H154: 44 | I154: 21.86 | J154: 21 | K154: 0 | L154: 0 | M154: 44 | N154: 44 | O154: 0 | P154: 45596 | Q154: 45596 | R154: 45596 | S154: =H154*I154 | T154: =H154*J154 | U154: =IF(AND(K154=0,G154<=Assumptions!$C$6),1,0) | V154: =IF(U154=1,IF(M154>0,IF(P154<=G154+Assumptions!$C$7,1,0),0),0) | W154: =IF(AND(U154=1,M154>=H154*(1-Assumptions!$C$8)),1,0) | X154: =IF(AND(U154=1,N154>=H154*(1-Assumptions!$C$8)),1,0) | Y154: =IF(ISNUMBER(Q154),1,0) | Z154: =IF(AND(K154=0,L154=0,Y154=0),1,0) | AA154: =IF(AND(Z154=1,G154<Assumptions!$C$6),1,0) | AB154: =IF(U154=0,"",IF(Y154=1,MAX(0,Q154-G154),IF(L154=1,MAX(0,R154-G154),MAX(0,Assumptions!$C$6-G154)))) | AC154: =IF(Y154=1,Q154-F154,"") | AD154: =IF(Y154=1,AC154^2,"") | AE154: =IF(Z154=1,(H154-M154)*I154,0) | AF154: =IF(G154<EDATE(Assumptions!$C$6,-12)+1,"prior_12m","last_12m") | AG154: =DATE(YEAR(G154),MONTH(G154),1)
A155: SPO-00080-1 | B155: SPO-00080 | C155: SUP-09 | D155: CHEM | E155: CHEM-06 | F155: 45585 | G155: 45599 | H155: 2 | I155: 380.5 | J155: 380 | K155: 0 | L155: 0 | M155: 2 | N155: 2 | O155: 0 | P155: 45597 | Q155: 45597 | R155: 45597 | S155: =H155*I155 | T155: =H155*J155 | U155: =IF(AND(K155=0,G155<=Assumptions!$C$6),1,0) | V155: =IF(U155=1,IF(M155>0,IF(P155<=G155+Assumptions!$C$7,1,0),0),0) | W155: =IF(AND(U155=1,M155>=H155*(1-Assumptions!$C$8)),1,0) | X155: =IF(AND(U155=1,N155>=H155*(1-Assumptions!$C$8)),1,0) | Y155: =IF(ISNUMBER(Q155),1,0) | Z155: =IF(AND(K155=0,L155=0,Y155=0),1,0) | AA155: =IF(AND(Z155=1,G155<Assumptions!$C$6),1,0) | AB155: =IF(U155=0,"",IF(Y155=1,MAX(0,Q155-G155),IF(L155=1,MAX(0,R155-G155),MAX(0,Assumptions!$C$6-G155)))) | AC155: =IF(Y155=1,Q155-F155,"") | AD155: =IF(Y155=1,AC155^2,"") | AE155: =IF(Z155=1,(H155-M155)*I155,0) | AF155: =IF(G155<EDATE(Assumptions!$C$6,-12)+1,"prior_12m","last_12m") | AG155: =DATE(YEAR(G155),MONTH(G155),1)
A156: SPO-00080-2 | B156: SPO-00080 | C156: SUP-09 | D156: CHEM | E156: CHEM-01 | F156: 45585 | G156: 45599 | H156: 4 | I156: 650.17 | J156: 640 | K156: 0 | L156: 0 | M156: 4 | N156: 0 | O156: 0 | P156: 45600 | Q156: 45600 | R156: 45600 | S156: =H156*I156 | T156: =H156*J156 | U156: =IF(AND(K156=0,G156<=Assumptions!$C$6),1,0) | V156: =IF(U156=1,IF(M156>0,IF(P156<=G156+Assumptions!$C$7,1,0),0),0) | W156: =IF(AND(U156=1,M156>=H156*(1-Assumptions!$C$8)),1,0) | X156: =IF(AND(U156=1,N156>=H156*(1-Assumptions!$C$8)),1,0) | Y156: =IF(ISNUMBER(Q156),1,0) | Z156: =IF(AND(K156=0,L156=0,Y156=0),1,0) | AA156: =IF(AND(Z156=1,G156<Assumptions!$C$6),1,0) | AB156: =IF(U156=0,"",IF(Y156=1,MAX(0,Q156-G156),IF(L156=1,MAX(0,R156-G156),MAX(0,Assumptions!$C$6-G156)))) | AC156: =IF(Y156=1,Q156-F156,"") | AD156: =IF(Y156=1,AC156^2,"") | AE156: =IF(Z156=1,(H156-M156)*I156,0) | AF156: =IF(G156<EDATE(Assumptions!$C$6,-12)+1,"prior_12m","last_12m") | AG156: =DATE(YEAR(G156),MONTH(G156),1)
A157: SPO-00080-3 | B157: SPO-00080 | C157: SUP-09 | D157: CHEM | E157: CHEM-04 | F157: 45585 | G157: 45599 | H157: 3 | I157: 849.27 | J157: 820 | K157: 0 | L157: 0 | M157: 3 | N157: 3 | O157: 0 | P157: 45598 | Q157: 45598 | R157: 45598 | S157: =H157*I157 | T157: =H157*J157 | U157: =IF(AND(K157=0,G157<=Assumptions!$C$6),1,0) | V157: =IF(U157=1,IF(M157>0,IF(P157<=G157+Assumptions!$C$7,1,0),0),0) | W157: =IF(AND(U157=1,M157>=H157*(1-Assumptions!$C$8)),1,0) | X157: =IF(AND(U157=1,N157>=H157*(1-Assumptions!$C$8)),1,0) | Y157: =IF(ISNUMBER(Q157),1,0) | Z157: =IF(AND(K157=0,L157=0,Y157=0),1,0) | AA157: =IF(AND(Z157=1,G157<Assumptions!$C$6),1,0) | AB157: =IF(U157=0,"",IF(Y157=1,MAX(0,Q157-G157),IF(L157=1,MAX(0,R157-G157),MAX(0,Assumptions!$C$6-G157)))) | AC157: =IF(Y157=1,Q157-F157,"") | AD157: =IF(Y157=1,AC157^2,"") | AE157: =IF(Z157=1,(H157-M157)*I157,0) | AF157: =IF(G157<EDATE(Assumptions!$C$6,-12)+1,"prior_12m","last_12m") | AG157: =DATE(YEAR(G157),MONTH(G157),1)
A158: SPO-00081-1 | B158: SPO-00081 | C158: SUP-12 | D158: IT | E158: IT-08 | F158: 45585 | G158: 45595 | H158: 6 | I158: 272.44 | J158: 245 | K158: 0 | L158: 0 | M158: 6 | N158: 6 | O158: 0 | P158: 45590 | Q158: 45590 | R158: 45590 | S158: =H158*I158 | T158: =H158*J158 | U158: =IF(AND(K158=0,G158<=Assumptions!$C$6),1,0) | V158: =IF(U158=1,IF(M158>0,IF(P158<=G158+Assumptions!$C$7,1,0),0),0) | W158: =IF(AND(U158=1,M158>=H158*(1-Assumptions!$C$8)),1,0) | X158: =IF(AND(U158=1,N158>=H158*(1-Assumptions!$C$8)),1,0) | Y158: =IF(ISNUMBER(Q158),1,0) | Z158: =IF(AND(K158=0,L158=0,Y158=0),1,0) | AA158: =IF(AND(Z158=1,G158<Assumptions!$C$6),1,0) | AB158: =IF(U158=0,"",IF(Y158=1,MAX(0,Q158-G158),IF(L158=1,MAX(0,R158-G158),MAX(0,Assumptions!$C$6-G158)))) | AC158: =IF(Y158=1,Q158-F158,"") | AD158: =IF(Y158=1,AC158^2,"") | AE158: =IF(Z158=1,(H158-M158)*I158,0) | AF158: =IF(G158<EDATE(Assumptions!$C$6,-12)+1,"prior_12m","last_12m") | AG158: =DATE(YEAR(G158),MONTH(G158),1)
A159: SPO-00081-2 | B159: SPO-00081 | C159: SUP-12 | D159: IT | E159: IT-04 | F159: 45585 | G159: 45595 | H159: 147 | I159: 13.79 | J159: 12 | K159: 0 | L159: 0 | M159: 147 | N159: 147 | O159: 0 | P159: 45590 | Q159: 45590 | R159: 45590 | S159: =H159*I159 | T159: =H159*J159 | U159: =IF(AND(K159=0,G159<=Assumptions!$C$6),1,0) | V159: =IF(U159=1,IF(M159>0,IF(P159<=G159+Assumptions!$C$7,1,0),0),0) | W159: =IF(AND(U159=1,M159>=H159*(1-Assumptions!$C$8)),1,0) | X159: =IF(AND(U159=1,N159>=H159*(1-Assumptions!$C$8)),1,0) | Y159: =IF(ISNUMBER(Q159),1,0) | Z159: =IF(AND(K159=0,L159=0,Y159=0),1,0) | AA159: =IF(AND(Z159=1,G159<Assumptions!$C$6),1,0) | AB159: =IF(U159=0,"",IF(Y159=1,MAX(0,Q159-G159),IF(L159=1,MAX(0,R159-G159),MAX(0,Assumptions!$C$6-G159)))) | AC159: =IF(Y159=1,Q159-F159,"") | AD159: =IF(Y159=1,AC159^2,"") | AE159: =IF(Z159=1,(H159-M159)*I159,0) | AF159: =IF(G159<EDATE(Assumptions!$C$6,-12)+1,"prior_12m","last_12m") | AG159: =DATE(YEAR(G159),MONTH(G159),1)
A160: SPO-00082-1 | B160: SPO-00082 | C160: SUP-02 | D160: ELEC | E160: ELEC-08 | F160: 45586 | G160: 45602 | H160: 53 | I160: 17.39 | J160: 18 | K160: 0 | L160: 0 | M160: 53 | N160: 53 | O160: 0 | P160: 45600 | Q160: 45600 | R160: 45600 | S160: =H160*I160 | T160: =H160*J160 | U160: =IF(AND(K160=0,G160<=Assumptions!$C$6),1,0) | V160: =IF(U160=1,IF(M160>0,IF(P160<=G160+Assumptions!$C$7,1,0),0),0) | W160: =IF(AND(U160=1,M160>=H160*(1-Assumptions!$C$8)),1,0) | X160: =IF(AND(U160=1,N160>=H160*(1-Assumptions!$C$8)),1,0) | Y160: =IF(ISNUMBER(Q160),1,0) | Z160: =IF(AND(K160=0,L160=0,Y160=0),1,0) | AA160: =IF(AND(Z160=1,G160<Assumptions!$C$6),1,0) | AB160: =IF(U160=0,"",IF(Y160=1,MAX(0,Q160-G160),IF(L160=1,MAX(0,R160-G160),MAX(0,Assumptions!$C$6-G160)))) | AC160: =IF(Y160=1,Q160-F160,"") | AD160: =IF(Y160=1,AC160^2,"") | AE160: =IF(Z160=1,(H160-M160)*I160,0) | AF160: =IF(G160<EDATE(Assumptions!$C$6,-12)+1,"prior_12m","last_12m") | AG160: =DATE(YEAR(G160),MONTH(G160),1)
A161: SPO-00082-2 | B161: SPO-00082 | C161: SUP-02 | D161: ELEC | E161: ELEC-07 | F161: 45586 | G161: 45602 | H161: 196 | I161: 9.66 | J161: 9.8 | K161: 0 | L161: 0 | M161: 196 | N161: 196 | O161: 0 | P161: 45597 | Q161: 45597 | R161: 45597 | S161: =H161*I161 | T161: =H161*J161 | U161: =IF(AND(K161=0,G161<=Assumptions!$C$6),1,0) | V161: =IF(U161=1,IF(M161>0,IF(P161<=G161+Assumptions!$C$7,1,0),0),0) | W161: =IF(AND(U161=1,M161>=H161*(1-Assumptions!$C$8)),1,0) | X161: =IF(AND(U161=1,N161>=H161*(1-Assumptions!$C$8)),1,0) | Y161: =IF(ISNUMBER(Q161),1,0) | Z161: =IF(AND(K161=0,L161=0,Y161=0),1,0) | AA161: =IF(AND(Z161=1,G161<Assumptions!$C$6),1,0) | AB161: =IF(U161=0,"",IF(Y161=1,MAX(0,Q161-G161),IF(L161=1,MAX(0,R161-G161),MAX(0,Assumptions!$C$6-G161)))) | AC161: =IF(Y161=1,Q161-F161,"") | AD161: =IF(Y161=1,AC161^2,"") | AE161: =IF(Z161=1,(H161-M161)*I161,0) | AF161: =IF(G161<EDATE(Assumptions!$C$6,-12)+1,"prior_12m","last_12m") | AG161: =DATE(YEAR(G161),MONTH(G161),1)
A162: SPO-00082-3 | B162: SPO-00082 | C162: SUP-02 | D162: ELEC | E162: ELEC-05 | F162: 45586 | G162: 45602 | H162: 406 | I162: 11.7 | J162: 11.5 | K162: 0 | L162: 0 | M162: 406 | N162: 406 | O162: 0 | P162: 45601 | Q162: 45601 | R162: 45601 | S162: =H162*I162 | T162: =H162*J162 | U162: =IF(AND(K162=0,G162<=Assumptions!$C$6),1,0) | V162: =IF(U162=1,IF(M162>0,IF(P162<=G162+Assumptions!$C$7,1,0),0),0) | W162: =IF(AND(U162=1,M162>=H162*(1-Assumptions!$C$8)),1,0) | X162: =IF(AND(U162=1,N162>=H162*(1-Assumptions!$C$8)),1,0) | Y162: =IF(ISNUMBER(Q162),1,0) | Z162: =IF(AND(K162=0,L162=0,Y162=0),1,0) | AA162: =IF(AND(Z162=1,G162<Assumptions!$C$6),1,0) | AB162: =IF(U162=0,"",IF(Y162=1,MAX(0,Q162-G162),IF(L162=1,MAX(0,R162-G162),MAX(0,Assumptions!$C$6-G162)))) | AC162: =IF(Y162=1,Q162-F162,"") | AD162: =IF(Y162=1,AC162^2,"") | AE162: =IF(Z162=1,(H162-M162)*I162,0) | AF162: =IF(G162<EDATE(Assumptions!$C$6,-12)+1,"prior_12m","last_12m") | AG162: =DATE(YEAR(G162),MONTH(G162),1)
... A228: SPO-00121-1 | B228: SPO-00121 | C228: SUP-14 | D228: FLEET | E228: FLEET-06 | F228: 45597 | G228: 45611 | H228: 72 | I228: 33.67 | J228: 33 | K228: 0 | L228: 0 | M228: 72 | N228: 72 | O228: 0 | P228: 45605 | Q228: 45605 | R228: 45605 | S228: =H228*I228 | T228: =H228*J228 | U228: =IF(AND(K228=0,G228<=Assumptions!$C$6),1,0) | V228: =IF(U228=1,IF(M228>0,IF(P228<=G228+Assumptions!$C$7,1,0),0),0) | W228: =IF(AND(U228=1,M228>=H228*(1-Assumptions!$C$8)),1,0) | X228: =IF(AND(U228=1,N228>=H228*(1-Assumptions!$C$8)),1,0) | Y228: =IF(ISNUMBER(Q228),1,0) | Z228: =IF(AND(K228=0,L228=0,Y228=0),1,0) | AA228: =IF(AND(Z228=1,G228<Assumptions!$C$6),1,0) | AB228: =IF(U228=0,"",IF(Y228=1,MAX(0,Q228-G228),IF(L228=1,MAX(0,R228-G228),MAX(0,Assumptions!$C$6-G228)))) | AC228: =IF(Y228=1,Q228-F228,"") | AD228: =IF(Y228=1,AC228^2,"") | AE228: =IF(Z228=1,(H228-M228)*I228,0) | AF228: =IF(G228<EDATE(Assumptions!$C$6,-12)+1,"prior_12m","last_12m") | AG228: =DATE(YEAR(G228),MONTH(G228),1)
A229: SPO-00121-2 | B229: SPO-00121 | C229: SUP-14 | D229: FLEET | E229: FLEET-04 | F229: 45597 | G229: 45611 | H229: 118 | I229: 8.66 | J229: 9 | K229: 0 | L229: 1 | M229: 60 | N229: 60 | O229: 0 | P229: 45609 | R229: 45609 | S229: =H229*I229 | T229: =H229*J229 | U229: =IF(AND(K229=0,G229<=Assumptions!$C$6),1,0) | V229: =IF(U229=1,IF(M229>0,IF(P229<=G229+Assumptions!$C$7,1,0),0),0) | W229: =IF(AND(U229=1,M229>=H229*(1-Assumptions!$C$8)),1,0) | X229: =IF(AND(U229=1,N229>=H229*(1-Assumptions!$C$8)),1,0) | Y229: =IF(ISNUMBER(Q229),1,0) | Z229: =IF(AND(K229=0,L229=0,Y229=0),1,0) | AA229: =IF(AND(Z229=1,G229<Assumptions!$C$6),1,0) | AB229: =IF(U229=0,"",IF(Y229=1,MAX(0,Q229-G229),IF(L229=1,MAX(0,R229-G229),MAX(0,Assumptions!$C$6-G229)))) | AC229: =IF(Y229=1,Q229-F229,"") | AD229: =IF(Y229=1,AC229^2,"") | AE229: =IF(Z229=1,(H229-M229)*I229,0) | AF229: =IF(G229<EDATE(Assumptions!$C$6,-12)+1,"prior_12m","last_12m") | AG229: =DATE(YEAR(G229),MONTH(G229),1)
A230: SPO-00121-3 | B230: SPO-00121 | C230: SUP-14 | D230: FLEET | E230: FLEET-08 | F230: 45597 | G230: 45611 | H230: 153 | I230: 6.57 | J230: 6.4 | K230: 0 | L230: 0 | M230: 153 | N230: 153 | O230: 0 | P230: 45609 | Q230: 45609 | R230: 45609 | S230: =H230*I230 | T230: =H230*J230 | U230: =IF(AND(K230=0,G230<=Assumptions!$C$6),1,0) | V230: =IF(U230=1,IF(M230>0,IF(P230<=G230+Assumptions!$C$7,1,0),0),0) | W230: =IF(AND(U230=1,M230>=H230*(1-Assumptions!$C$8)),1,0) | X230: =IF(AND(U230=1,N230>=H230*(1-Assumptions!$C$8)),1,0) | Y230: =IF(ISNUMBER(Q230),1,0) | Z230: =IF(AND(K230=0,L230=0,Y230=0),1,0) | AA230: =IF(AND(Z230=1,G230<Assumptions!$C$6),1,0) | AB230: =IF(U230=0,"",IF(Y230=1,MAX(0,Q230-G230),IF(L230=1,MAX(0,R230-G230),MAX(0,Assumptions!$C$6-G230)))) | AC230: =IF(Y230=1,Q230-F230,"") | AD230: =IF(Y230=1,AC230^2,"") | AE230: =IF(Z230=1,(H230-M230)*I230,0) | AF230: =IF(G230<EDATE(Assumptions!$C$6,-12)+1,"prior_12m","last_12m") | AG230: =DATE(YEAR(G230),MONTH(G230),1)
A231: SPO-00122-1 | B231: SPO-00122 | C231: SUP-05 | D231: FLEET | E231: FLEET-06 | F231: 45597 | G231: 45611 | H231: 35 | I231: 33.5 | J231: 33 | K231: 0 | L231: 0 | M231: 35 | N231: 35 | O231: 0 | P231: 45608 | Q231: 45608 | R231: 45608 | S231: =H231*I231 | T231: =H231*J231 | U231: =IF(AND(K231=0,G231<=Assumptions!$C$6),1,0) | V231: =IF(U231=1,IF(M231>0,IF(P231<=G231+Assumptions!$C$7,1,0),0),0) | W231: =IF(AND(U231=1,M231>=H231*(1-Assumptions!$C$8)),1,0) | X231: =IF(AND(U231=1,N231>=H231*(1-Assumptions!$C$8)),1,0) | Y231: =IF(ISNUMBER(Q231),1,0) | Z231: =IF(AND(K231=0,L231=0,Y231=0),1,0) | AA231: =IF(AND(Z231=1,G231<Assumptions!$C$6),1,0) | AB231: =IF(U231=0,"",IF(Y231=1,MAX(0,Q231-G231),IF(L231=1,MAX(0,R231-G231),MAX(0,Assumptions!$C$6-G231)))) | AC231: =IF(Y231=1,Q231-F231,"") | AD231: =IF(Y231=1,AC231^2,"") | AE231: =IF(Z231=1,(H231-M231)*I231,0) | AF231: =IF(G231<EDATE(Assumptions!$C$6,-12)+1,"prior_12m","last_12m") | AG231: =DATE(YEAR(G231),MONTH(G231),1)
A232: SPO-00123-1 | B232: SPO-00123 | C232: SUP-08 | D232: MRO | E232: MRO-03 | F232: 45597 | G232: 45608 | H232: 215 | I232: 8.78 | J232: 8.9 | K232: 0 | L232: 0 | M232: 215 | N232: 215 | O232: 0 | P232: 45603 | Q232: 45603 | R232: 45603 | S232: =H232*I232 | T232: =H232*J232 | U232: =IF(AND(K232=0,G232<=Assumptions!$C$6),1,0) | V232: =IF(U232=1,IF(M232>0,IF(P232<=G232+Assumptions!$C$7,1,0),0),0) | W232: =IF(AND(U232=1,M232>=H232*(1-Assumptions!$C$8)),1,0) | X232: =IF(AND(U232=1,N232>=H232*(1-Assumptions!$C$8)),1,0) | Y232: =IF(ISNUMBER(Q232),1,0) | Z232: =IF(AND(K232=0,L232=0,Y232=0),1,0) | AA232: =IF(AND(Z232=1,G232<Assumptions!$C$6),1,0) | AB232: =IF(U232=0,"",IF(Y232=1,MAX(0,Q232-G232),IF(L232=1,MAX(0,R232-G232),MAX(0,Assumptions!$C$6-G232)))) | AC232: =IF(Y232=1,Q232-F232,"") | AD232: =IF(Y232=1,AC232^2,"") | AE232: =IF(Z232=1,(H232-M232)*I232,0) | AF232: =IF(G232<EDATE(Assumptions!$C$6,-12)+1,"prior_12m","last_12m") | AG232: =DATE(YEAR(G232),MONTH(G232),1)
A233: SPO-00124-1 | B233: SPO-00124 | C233: SUP-12 | D233: IT | E233: IT-03 | F233: 45598 | G233: 45608 | H233: 31 | I233: 42.58 | J233: 38 | K233: 1 | L233: 0 | M233: 0 | N233: 0 | O233: 0 | S233: =H233*I233 | T233: =H233*J233 | U233: =IF(AND(K233=0,G233<=Assumptions!$C$6),1,0) | V233: =IF(U233=1,IF(M233>0,IF(P233<=G233+Assumptions!$C$7,1,0),0),0) | W233: =IF(AND(U233=1,M233>=H233*(1-Assumptions!$C$8)),1,0) | X233: =IF(AND(U233=1,N233>=H233*(1-Assumptions!$C$8)),1,0) | Y233: =IF(ISNUMBER(Q233),1,0) | Z233: =IF(AND(K233=0,L233=0,Y233=0),1,0) | AA233: =IF(AND(Z233=1,G233<Assumptions!$C$6),1,0) | AB233: =IF(U233=0,"",IF(Y233=1,MAX(0,Q233-G233),IF(L233=1,MAX(0,R233-G233),MAX(0,Assumptions!$C$6-G233)))) | AC233: =IF(Y233=1,Q233-F233,"") | AD233: =IF(Y233=1,AC233^2,"") | AE233: =IF(Z233=1,(H233-M233)*I233,0) | AF233: =IF(G233<EDATE(Assumptions!$C$6,-12)+1,"prior_12m","last_12m") | AG233: =DATE(YEAR(G233),MONTH(G233),1)
A234: SPO-00124-2 | B234: SPO-00124 | C234: SUP-12 | D234: IT | E234: IT-05 | F234: 45598 | G234: 45608 | H234: 7 | I234: 731.18 | J234: 640 | K234: 0 | L234: 0 | M234: 7 | N234: 7 | O234: 0 | P234: 45608 | Q234: 45608 | R234: 45608 | S234: =H234*I234 | T234: =H234*J234 | U234: =IF(AND(K234=0,G234<=Assumptions!$C$6),1,0) | V234: =IF(U234=1,IF(M234>0,IF(P234<=G234+Assumptions!$C$7,1,0),0),0) | W234: =IF(AND(U234=1,M234>=H234*(1-Assumptions!$C$8)),1,0) | X234: =IF(AND(U234=1,N234>=H234*(1-Assumptions!$C$8)),1,0) | Y234: =IF(ISNUMBER(Q234),1,0) | Z234: =IF(AND(K234=0,L234=0,Y234=0),1,0) | AA234: =IF(AND(Z234=1,G234<Assumptions!$C$6),1,0) | AB234: =IF(U234=0,"",IF(Y234=1,MAX(0,Q234-G234),IF(L234=1,MAX(0,R234-G234),MAX(0,Assumptions!$C$6-G234)))) | AC234: =IF(Y234=1,Q234-F234,"") | AD234: =IF(Y234=1,AC234^2,"") | AE234: =IF(Z234=1,(H234-M234)*I234,0) | AF234: =IF(G234<EDATE(Assumptions!$C$6,-12)+1,"prior_12m","last_12m") | AG234: =DATE(YEAR(G234),MONTH(G234),1)
A235: SPO-00125-1 | B235: SPO-00125 | C235: SUP-14 | D235: FLEET | E235: FLEET-04 | F235: 45598 | G235: 45612 | H235: 207 | I235: 8.97 | J235: 9 | K235: 0 | L235: 0 | M235: 207 | N235: 207 | O235: 0 | P235: 45604 | Q235: 45604 | R235: 45604 | S235: =H235*I235 | T235: =H235*J235 | U235: =IF(AND(K235=0,G235<=Assumptions!$C$6),1,0) | V235: =IF(U235=1,IF(M235>0,IF(P235<=G235+Assumptions!$C$7,1,0),0),0) | W235: =IF(AND(U235=1,M235>=H235*(1-Assumptions!$C$8)),1,0) | X235: =IF(AND(U235=1,N235>=H235*(1-Assumptions!$C$8)),1,0) | Y235: =IF(ISNUMBER(Q235),1,0) | Z235: =IF(AND(K235=0,L235=0,Y235=0),1,0) | AA235: =IF(AND(Z235=1,G235<Assumptions!$C$6),1,0) | AB235: =IF(U235=0,"",IF(Y235=1,MAX(0,Q235-G235),IF(L235=1,MAX(0,R235-G235),MAX(0,Assumptions!$C$6-G235)))) | AC235: =IF(Y235=1,Q235-F235,"") | AD235: =IF(Y235=1,AC235^2,"") | AE235: =IF(Z235=1,(H235-M235)*I235,0) | AF235: =IF(G235<EDATE(Assumptions!$C$6,-12)+1,"prior_12m","last_12m") | AG235: =DATE(YEAR(G235),MONTH(G235),1)
A236: SPO-00126-1 | B236: SPO-00126 | C236: SUP-05 | D236: FLEET | E236: FLEET-03 | F236: 45598 | G236: 45612 | H236: 115 | I236: 21.45 | J236: 21 | K236: 0 | L236: 0 | M236: 115 | N236: 115 | O236: 0 | P236: 45609 | Q236: 45609 | R236: 45609 | S236: =H236*I236 | T236: =H236*J236 | U236: =IF(AND(K236=0,G236<=Assumptions!$C$6),1,0) | V236: =IF(U236=1,IF(M236>0,IF(P236<=G236+Assumptions!$C$7,1,0),0),0) | W236: =IF(AND(U236=1,M236>=H236*(1-Assumptions!$C$8)),1,0) | X236: =IF(AND(U236=1,N236>=H236*(1-Assumptions!$C$8)),1,0) | Y236: =IF(ISNUMBER(Q236),1,0) | Z236: =IF(AND(K236=0,L236=0,Y236=0),1,0) | AA236: =IF(AND(Z236=1,G236<Assumptions!$C$6),1,0) | AB236: =IF(U236=0,"",IF(Y236=1,MAX(0,Q236-G236),IF(L236=1,MAX(0,R236-G236),MAX(0,Assumptions!$C$6-G236)))) | AC236: =IF(Y236=1,Q236-F236,"") | AD236: =IF(Y236=1,AC236^2,"") | AE236: =IF(Z236=1,(H236-M236)*I236,0) | AF236: =IF(G236<EDATE(Assumptions!$C$6,-12)+1,"prior_12m","last_12m") | AG236: =DATE(YEAR(G236),MONTH(G236),1)
A237: SPO-00126-2 | B237: SPO-00126 | C237: SUP-05 | D237: FLEET | E237: FLEET-01 | F237: 45598 | G237: 45612 | H237: 13 | I237: 63.55 | J237: 64 | K237: 0 | L237: 0 | M237: 13 | N237: 13 | O237: 0 | P237: 45612 | Q237: 45612 | R237: 45612 | S237: =H237*I237 | T237: =H237*J237 | U237: =IF(AND(K237=0,G237<=Assumptions!$C$6),1,0) | V237: =IF(U237=1,IF(M237>0,IF(P237<=G237+Assumptions!$C$7,1,0),0),0) | W237: =IF(AND(U237=1,M237>=H237*(1-Assumptions!$C$8)),1,0) | X237: =IF(AND(U237=1,N237>=H237*(1-Assumptions!$C$8)),1,0) | Y237: =IF(ISNUMBER(Q237),1,0) | Z237: =IF(AND(K237=0,L237=0,Y237=0),1,0) | AA237: =IF(AND(Z237=1,G237<Assumptions!$C$6),1,0) | AB237: =IF(U237=0,"",IF(Y237=1,MAX(0,Q237-G237),IF(L237=1,MAX(0,R237-G237),MAX(0,Assumptions!$C$6-G237)))) | AC237: =IF(Y237=1,Q237-F237,"") | AD237: =IF(Y237=1,AC237^2,"") | AE237: =IF(Z237=1,(H237-M237)*I237,0) | AF237: =IF(G237<EDATE(Assumptions!$C$6,-12)+1,"prior_12m","last_12m") | AG237: =DATE(YEAR(G237),MONTH(G237),1)
A238: SPO-00126-3 | B238: SPO-00126 | C238: SUP-05 | D238: FLEET | E238: FLEET-07 | F238: 45598 | G238: 45612 | H238: 9 | I238: 114.38 | J238: 118 | K238: 0 | L238: 0 | M238: 9 | N238: 0 | O238: 0 | P238: 45613 | Q238: 45613 | R238: 45613 | S238: =H238*I238 | T238: =H238*J238 | U238: =IF(AND(K238=0,G238<=Assumptions!$C$6),1,0) | V238: =IF(U238=1,IF(M238>0,IF(P238<=G238+Assumptions!$C$7,1,0),0),0) | W238: =IF(AND(U238=1,M238>=H238*(1-Assumptions!$C$8)),1,0) | X238: =IF(AND(U238=1,N238>=H238*(1-Assumptions!$C$8)),1,0) | Y238: =IF(ISNUMBER(Q238),1,0) | Z238: =IF(AND(K238=0,L238=0,Y238=0),1,0) | AA238: =IF(AND(Z238=1,G238<Assumptions!$C$6),1,0) | AB238: =IF(U238=0,"",IF(Y238=1,MAX(0,Q238-G238),IF(L238=1,MAX(0,R238-G238),MAX(0,Assumptions!$C$6-G238)))) | AC238: =IF(Y238=1,Q238-F238,"") | AD238: =IF(Y238=1,AC238^2,"") | AE238: =IF(Z238=1,(H238-M238)*I238,0) | AF238: =IF(G238<EDATE(Assumptions!$C$6,-12)+1,"prior_12m","last_12m") | AG238: =DATE(YEAR(G238),MONTH(G238),1)
A239: SPO-00126-4 | B239: SPO-00126 | C239: SUP-05 | D239: FLEET | E239: FLEET-02 | F239: 45598 | G239: 45612 | H239: 200 | I239: 7.25 | J239: 7.5 | K239: 0 | L239: 0 | M239: 200 | N239: 200 | O239: 0 | P239: 45607 | Q239: 45607 | R239: 45607 | S239: =H239*I239 | T239: =H239*J239 | U239: =IF(AND(K239=0,G239<=Assumptions!$C$6),1,0) | V239: =IF(U239=1,IF(M239>0,IF(P239<=G239+Assumptions!$C$7,1,0),0),0) | W239: =IF(AND(U239=1,M239>=H239*(1-Assumptions!$C$8)),1,0) | X239: =IF(AND(U239=1,N239>=H239*(1-Assumptions!$C$8)),1,0) | Y239: =IF(ISNUMBER(Q239),1,0) | Z239: =IF(AND(K239=0,L239=0,Y239=0),1,0) | AA239: =IF(AND(Z239=1,G239<Assumptions!$C$6),1,0) | AB239: =IF(U239=0,"",IF(Y239=1,MAX(0,Q239-G239),IF(L239=1,MAX(0,R239-G239),MAX(0,Assumptions!$C$6-G239)))) | AC239: =IF(Y239=1,Q239-F239,"") | AD239: =IF(Y239=1,AC239^2,"") | AE239: =IF(Z239=1,(H239-M239)*I239,0) | AF239: =IF(G239<EDATE(Assumptions!$C$6,-12)+1,"prior_12m","last_12m") | AG239: =DATE(YEAR(G239),MONTH(G239),1)
A240: SPO-00127-1 | B240: SPO-00127 | C240: SUP-10 | D240: PPE | E240: PPE-03 | F240: 45599 | G240: 45612 | H240: 86 | I240: 20.95 | J240: 21 | K240: 0 | L240: 0 | M240: 86 | N240: 86 | O240: 0 | P240: 45609 | Q240: 45609 | R240: 45609 | S240: =H240*I240 | T240: =H240*J240 | U240: =IF(AND(K240=0,G240<=Assumptions!$C$6),1,0) | V240: =IF(U240=1,IF(M240>0,IF(P240<=G240+Assumptions!$C$7,1,0),0),0) | W240: =IF(AND(U240=1,M240>=H240*(1-Assumptions!$C$8)),1,0) | X240: =IF(AND(U240=1,N240>=H240*(1-Assumptions!$C$8)),1,0) | Y240: =IF(ISNUMBER(Q240),1,0) | Z240: =IF(AND(K240=0,L240=0,Y240=0),1,0) | AA240: =IF(AND(Z240=1,G240<Assumptions!$C$6),1,0) | AB240: =IF(U240=0,"",IF(Y240=1,MAX(0,Q240-G240),IF(L240=1,MAX(0,R240-G240),MAX(0,Assumptions!$C$6-G240)))) | AC240: =IF(Y240=1,Q240-F240,"") | AD240: =IF(Y240=1,AC240^2,"") | AE240: =IF(Z240=1,(H240-M240)*I240,0) | AF240: =IF(G240<EDATE(Assumptions!$C$6,-12)+1,"prior_12m","last_12m") | AG240: =DATE(YEAR(G240),MONTH(G240),1)
A241: SPO-00128-1 | B241: SPO-00128 | C241: SUP-12 | D241: IT | E241: IT-07 | F241: 45599 | G241: 45609 | H241: 17 | I241: 84.6 | J241: 74 | K241: 0 | L241: 0 | M241: 17 | N241: 17 | O241: 0 | P241: 45606 | Q241: 45606 | R241: 45606 | S241: =H241*I241 | T241: =H241*J241 | U241: =IF(AND(K241=0,G241<=Assumptions!$C$6),1,0) | V241: =IF(U241=1,IF(M241>0,IF(P241<=G241+Assumptions!$C$7,1,0),0),0) | W241: =IF(AND(U241=1,M241>=H241*(1-Assumptions!$C$8)),1,0) | X241: =IF(AND(U241=1,N241>=H241*(1-Assumptions!$C$8)),1,0) | Y241: =IF(ISNUMBER(Q241),1,0) | Z241: =IF(AND(K241=0,L241=0,Y241=0),1,0) | AA241: =IF(AND(Z241=1,G241<Assumptions!$C$6),1,0) | AB241: =IF(U241=0,"",IF(Y241=1,MAX(0,Q241-G241),IF(L241=1,MAX(0,R241-G241),MAX(0,Assumptions!$C$6-G241)))) | AC241: =IF(Y241=1,Q241-F241,"") | AD241: =IF(Y241=1,AC241^2,"") | AE241: =IF(Z241=1,(H241-M241)*I241,0) | AF241: =IF(G241<EDATE(Assumptions!$C$6,-12)+1,"prior_12m","last_12m") | AG241: =DATE(YEAR(G241),MONTH(G241),1)
A242: SPO-00129-1 | B242: SPO-00129 | C242: SUP-14 | D242: FLEET | E242: FLEET-06 | F242: 45599 | G242: 45613 | H242: 56 | I242: 33.36 | J242: 33 | K242: 0 | L242: 0 | M242: 56 | N242: 34 | O242: 0 | P242: 45608 | Q242: 45624 | R242: 45624 | S242: =H242*I242 | T242: =H242*J242 | U242: =IF(AND(K242=0,G242<=Assumptions!$C$6),1,0) | V242: =IF(U242=1,IF(M242>0,IF(P242<=G242+Assumptions!$C$7,1,0),0),0) | W242: =IF(AND(U242=1,M242>=H242*(1-Assumptions!$C$8)),1,0) | X242: =IF(AND(U242=1,N242>=H242*(1-Assumptions!$C$8)),1,0) | Y242: =IF(ISNUMBER(Q242),1,0) | Z242: =IF(AND(K242=0,L242=0,Y242=0),1,0) | AA242: =IF(AND(Z242=1,G242<Assumptions!$C$6),1,0) | AB242: =IF(U242=0,"",IF(Y242=1,MAX(0,Q242-G242),IF(L242=1,MAX(0,R242-G242),MAX(0,Assumptions!$C$6-G242)))) | AC242: =IF(Y242=1,Q242-F242,"") | AD242: =IF(Y242=1,AC242^2,"") | AE242: =IF(Z242=1,(H242-M242)*I242,0) | AF242: =IF(G242<EDATE(Assumptions!$C$6,-12)+1,"prior_12m","last_12m") | AG242: =DATE(YEAR(G242),MONTH(G242),1)
A243: SPO-00130-1 | B243: SPO-00130 | C243: SUP-10 | D243: PPE | E243: PPE-04 | F243: 45599 | G243: 45612 | H243: 76 | I243: 25.51 | J243: 26 | K243: 0 | L243: 0 | M243: 76 | N243: 76 | O243: 0 | P243: 45610 | Q243: 45610 | R243: 45610 | S243: =H243*I243 | T243: =H243*J243 | U243: =IF(AND(K243=0,G243<=Assumptions!$C$6),1,0) | V243: =IF(U243=1,IF(M243>0,IF(P243<=G243+Assumptions!$C$7,1,0),0),0) | W243: =IF(AND(U243=1,M243>=H243*(1-Assumptions!$C$8)),1,0) | X243: =IF(AND(U243=1,N243>=H243*(1-Assumptions!$C$8)),1,0) | Y243: =IF(ISNUMBER(Q243),1,0) | Z243: =IF(AND(K243=0,L243=0,Y243=0),1,0) | AA243: =IF(AND(Z243=1,G243<Assumptions!$C$6),1,0) | AB243: =IF(U243=0,"",IF(Y243=1,MAX(0,Q243-G243),IF(L243=1,MAX(0,R243-G243),MAX(0,Assumptions!$C$6-G243)))) | AC243: =IF(Y243=1,Q243-F243,"") | AD243: =IF(Y243=1,AC243^2,"") | AE243: =IF(Z243=1,(H243-M243)*I243,0) | AF243: =IF(G243<EDATE(Assumptions!$C$6,-12)+1,"prior_12m","last_12m") | AG243: =DATE(YEAR(G243),MONTH(G243),1)
A244: SPO-00131-1 | B244: SPO-00131 | C244: SUP-13 | D244: IT | E244: IT-07 | F244: 45600 | G244: 45611 | H244: 34 | I244: 72.85 | J244: 74 | K244: 0 | L244: 0 | M244: 34 | N244: 34 | O244: 0 | P244: 45604 | Q244: 45604 | R244: 45604 | S244: =H244*I244 | T244: =H244*J244 | U244: =IF(AND(K244=0,G244<=Assumptions!$C$6),1,0) | V244: =IF(U244=1,IF(M244>0,IF(P244<=G244+Assumptions!$C$7,1,0),0),0) | W244: =IF(AND(U244=1,M244>=H244*(1-Assumptions!$C$8)),1,0) | X244: =IF(AND(U244=1,N244>=H244*(1-Assumptions!$C$8)),1,0) | Y244: =IF(ISNUMBER(Q244),1,0) | Z244: =IF(AND(K244=0,L244=0,Y244=0),1,0) | AA244: =IF(AND(Z244=1,G244<Assumptions!$C$6),1,0) | AB244: =IF(U244=0,"",IF(Y244=1,MAX(0,Q244-G244),IF(L244=1,MAX(0,R244-G244),MAX(0,Assumptions!$C$6-G244)))) | AC244: =IF(Y244=1,Q244-F244,"") | AD244: =IF(Y244=1,AC244^2,"") | AE244: =IF(Z244=1,(H244-M244)*I244,0) | AF244: =IF(G244<EDATE(Assumptions!$C$6,-12)+1,"prior_12m","last_12m") | AG244: =DATE(YEAR(G244),MONTH(G244),1)
A245: SPO-00131-2 | B245: SPO-00131 | C245: SUP-13 | D245: IT | E245: IT-01 | F245: 45600 | G245: 45611 | H245: 8 | I245: 197.84 | J245: 189 | K245: 0 | L245: 0 | M245: 8 | N245: 8 | O245: 0 | P245: 45607 | Q245: 45607 | R245: 45607 | S245: =H245*I245 | T245: =H245*J245 | U245: =IF(AND(K245=0,G245<=Assumptions!$C$6),1,0) | V245: =IF(U245=1,IF(M245>0,IF(P245<=G245+Assumptions!$C$7,1,0),0),0) | W245: =IF(AND(U245=1,M245>=H245*(1-Assumptions!$C$8)),1,0) | X245: =IF(AND(U245=1,N245>=H245*(1-Assumptions!$C$8)),1,0) | Y245: =IF(ISNUMBER(Q245),1,0) | Z245: =IF(AND(K245=0,L245=0,Y245=0),1,0) | AA245: =IF(AND(Z245=1,G245<Assumptions!$C$6),1,0) | AB245: =IF(U245=0,"",IF(Y245=1,MAX(0,Q245-G245),IF(L245=1,MAX(0,R245-G245),MAX(0,Assumptions!$C$6-G245)))) | AC245: =IF(Y245=1,Q245-F245,"") | AD245: =IF(Y245=1,AC245^2,"") | AE245: =IF(Z245=1,(H245-M245)*I245,0) | AF245: =IF(G245<EDATE(Assumptions!$C$6,-12)+1,"prior_12m","last_12m") | AG245: =DATE(YEAR(G245),MONTH(G245),1)
... A249: SPO-00135-1 | B249: SPO-00135 | C249: SUP-07 | D249: MRO | E249: MRO-03 | F249: 45601 | G249: 45611 | H249: 130 | I249: 8.91 | J249: 8.9 | K249: 0 | L249: 0 | M249: 130 | N249: 130 | O249: 0 | P249: 45606 | Q249: 45606 | R249: 45606 | S249: =H249*I249 | T249: =H249*J249 | U249: =IF(AND(K249=0,G249<=Assumptions!$C$6),1,0) | V249: =IF(U249=1,IF(M249>0,IF(P249<=G249+Assumptions!$C$7,1,0),0),0) | W249: =IF(AND(U249=1,M249>=H249*(1-Assumptions!$C$8)),1,0) | X249: =IF(AND(U249=1,N249>=H249*(1-Assumptions!$C$8)),1,0) | Y249: =IF(ISNUMBER(Q249),1,0) | Z249: =IF(AND(K249=0,L249=0,Y249=0),1,0) | AA249: =IF(AND(Z249=1,G249<Assumptions!$C$6),1,0) | AB249: =IF(U249=0,"",IF(Y249=1,MAX(0,Q249-G249),IF(L249=1,MAX(0,R249-G249),MAX(0,Assumptions!$C$6-G249)))) | AC249: =IF(Y249=1,Q249-F249,"") | AD249: =IF(Y249=1,AC249^2,"") | AE249: =IF(Z249=1,(H249-M249)*I249,0) | AF249: =IF(G249<EDATE(Assumptions!$C$6,-12)+1,"prior_12m","last_12m") | AG249: =DATE(YEAR(G249),MONTH(G249),1)
A250: SPO-00135-2 | B250: SPO-00135 | C250: SUP-07 | D250: MRO | E250: MRO-01 | F250: 45601 | G250: 45611 | H250: 57 | I250: 51.96 | J250: 52 | K250: 0 | L250: 1 | M250: 37 | N250: 37 | O250: 0 | P250: 45611 | R250: 45611 | S250: =H250*I250 | T250: =H250*J250 | U250: =IF(AND(K250=0,G250<=Assumptions!$C$6),1,0) | V250: =IF(U250=1,IF(M250>0,IF(P250<=G250+Assumptions!$C$7,1,0),0),0) | W250: =IF(AND(U250=1,M250>=H250*(1-Assumptions!$C$8)),1,0) | X250: =IF(AND(U250=1,N250>=H250*(1-Assumptions!$C$8)),1,0) | Y250: =IF(ISNUMBER(Q250),1,0) | Z250: =IF(AND(K250=0,L250=0,Y250=0),1,0) | AA250: =IF(AND(Z250=1,G250<Assumptions!$C$6),1,0) | AB250: =IF(U250=0,"",IF(Y250=1,MAX(0,Q250-G250),IF(L250=1,MAX(0,R250-G250),MAX(0,Assumptions!$C$6-G250)))) | AC250: =IF(Y250=1,Q250-F250,"") | AD250: =IF(Y250=1,AC250^2,"") | AE250: =IF(Z250=1,(H250-M250)*I250,0) | AF250: =IF(G250<EDATE(Assumptions!$C$6,-12)+1,"prior_12m","last_12m") | AG250: =DATE(YEAR(G250),MONTH(G250),1)
...

Sheet Syn_Suppliers
A1: Synthetic supplier master
A2: SYNTHETIC DEMONSTRATION DATA - not real suppliers or real performance
A4: supplier_id | B4: supplier_name | C4: primary_category_id | D4: categories_served | E4: design_note
A5: SUP-01 | B5: Synthetic Supplier 01 | C5: ELEC | D5: ELEC | E5: Largest electrical supplier; delivery deteriorates in year 2
A6: SUP-02 | B6: Synthetic Supplier 02 | C6: ELEC | D6: ELEC | E6: Reliable electrical alternative with spare share
A7: SUP-03 | B7: Synthetic Supplier 03 | C7: ELEC | D7: ELEC | E7: Very few orders: tests the insufficient-evidence rule
A8: SUP-04 | B8: Synthetic Supplier 04 | C8: FLEET | D8: FLEET | E8: Chronically late fleet supplier with unstable lead times
A9: SUP-05 | B9: Synthetic Supplier 05 | C9: FLEET | D9: FLEET | E9: Reliable fleet supplier
A10: SUP-06 | B10: Synthetic Supplier 06 | C10: MRO | D10: MRO | E10: Excellent MRO supplier holding a large category share
A11: SUP-07 | B11: Synthetic Supplier 07 | C11: MRO | D11: MRO | E11: Frequent split and short shipments
A12: SUP-08 | B12: Synthetic Supplier 08 | C12: MRO | D12: MRO, PPE | E12: Generalist serving MRO and PPE
A13: SUP-09 | B13: Synthetic Supplier 09 | C13: CHEM | D13: CHEM | E13: Sole source for water treatment chemicals: good performance, high dependency
A14: SUP-10 | B14: Synthetic Supplier 10 | C14: PPE | D14: PPE | E14: Low price but recurring quality rejections
A15: SUP-11 | B15: Synthetic Supplier 11 | C15: PPE | D15: PPE | E15: Reliable PPE supplier
... A18: SUP-14 | B18: Synthetic Supplier 14 | C18: FLEET | D18: FLEET | E18: Mid-performing fleet supplier with occasional quality issues

Sheet Supplier_Summary
A1: Supplier delivery, quality and spend summary
A2: SYNTHETIC DEMONSTRATION DATA - not real suppliers or real performance. Every metric is a live formula over Syn_Lines.
A3: Measured per PO line. Only due lines (not cancelled, promised on/before the as-of date) enter delivery rates; unreceived due lines count as late.
A4: Supplier ID | B4: Due lines | C4: OTIF lines | D4: OTIF rate | E4: On-time rate | F4: In-full rate | G4: Late lines | H4: Avg days late (all due lines) | I4: Completed lines | J4: Avg lead time (days) | K4: Lead-time SD (days) | L4: Received qty | M4: Rejected qty | N4: Reject rate | O4: Spend (ordered value) | P4: Value at contract price | Q4: PPV vs contract | R4: Share of total spend | S4: Open lines | T4: Overdue lines | U4: Overdue open value | V4: Due lines prior 12m | W4: OTIF prior 12m | X4: Due lines last 12m | Y4: OTIF last 12m | Z4: OTIF change (pts) | AA4: Lines closed short
A5: SUP-01 | B5: =COUNTIFS(Syn_Lines!$C$2:$C$4838,$A5,Syn_Lines!$U$2:$U$4838,1) | C5: =COUNTIFS(Syn_Lines!$C$2:$C$4838,$A5,Syn_Lines!$X$2:$X$4838,1) | D5: =IF(B5>0,C5/B5,"") | E5: =IF(B5>0,COUNTIFS(Syn_Lines!$C$2:$C$4838,$A5,Syn_Lines!$V$2:$V$4838,1)/B5,"") | F5: =IF(B5>0,COUNTIFS(Syn_Lines!$C$2:$C$4838,$A5,Syn_Lines!$W$2:$W$4838,1)/B5,"") | G5: =COUNTIFS(Syn_Lines!$C$2:$C$4838,$A5,Syn_Lines!$U$2:$U$4838,1,Syn_Lines!$AB$2:$AB$4838,">0") | H5: =IF(B5>0,AVERAGEIFS(Syn_Lines!$AB$2:$AB$4838,Syn_Lines!$C$2:$C$4838,$A5,Syn_Lines!$U$2:$U$4838,1),"") | I5: =COUNTIFS(Syn_Lines!$C$2:$C$4838,$A5,Syn_Lines!$Y$2:$Y$4838,1) | J5: =IF(I5>0,AVERAGEIFS(Syn_Lines!$AC$2:$AC$4838,Syn_Lines!$C$2:$C$4838,$A5,Syn_Lines!$Y$2:$Y$4838,1),"") | K5: =IF(I5>1,SQRT(MAX(0,(SUMIFS(Syn_Lines!$AD$2:$AD$4838,Syn_Lines!$C$2:$C$4838,$A5,Syn_Lines!$Y$2:$Y$4838,1)-I5*J5^2)/(I5-1))),"") | L5: =SUMIFS(Syn_Lines!$M$2:$M$4838,Syn_Lines!$C$2:$C$4838,$A5,Syn_Lines!$K$2:$K$4838,0) | M5: =SUMIFS(Syn_Lines!$O$2:$O$4838,Syn_Lines!$C$2:$C$4838,$A5,Syn_Lines!$K$2:$K$4838,0) | N5: =IF(L5>0,M5/L5,"") | O5: =SUMIFS(Syn_Lines!$S$2:$S$4838,Syn_Lines!$C$2:$C$4838,$A5,Syn_Lines!$K$2:$K$4838,0) | P5: =SUMIFS(Syn_Lines!$T$2:$T$4838,Syn_Lines!$C$2:$C$4838,$A5,Syn_Lines!$K$2:$K$4838,0) | Q5: =IF(P5>0,O5/P5-1,"") | R5: =O5/SUM($O$5:$O$18) | S5: =COUNTIFS(Syn_Lines!$C$2:$C$4838,$A5,Syn_Lines!$Z$2:$Z$4838,1) | T5: =COUNTIFS(Syn_Lines!$C$2:$C$4838,$A5,Syn_Lines!$AA$2:$AA$4838,1) | U5: =SUMIFS(Syn_Lines!$AE$2:$AE$4838,Syn_Lines!$C$2:$C$4838,$A5,Syn_Lines!$AA$2:$AA$4838,1) | V5: =COUNTIFS(Syn_Lines!$C$2:$C$4838,$A5,Syn_Lines!$U$2:$U$4838,1,Syn_Lines!$AF$2:$AF$4838,"prior_12m") | W5: =IF(V5>0,COUNTIFS(Syn_Lines!$C$2:$C$4838,$A5,Syn_Lines!$X$2:$X$4838,1,Syn_Lines!$AF$2:$AF$4838,"prior_12m")/V5,"") | X5: =COUNTIFS(Syn_Lines!$C$2:$C$4838,$A5,Syn_Lines!$U$2:$U$4838,1,Syn_Lines!$AF$2:$AF$4838,"last_12m") | Y5: =IF(X5>0,COUNTIFS(Syn_Lines!$C$2:$C$4838,$A5,Syn_Lines!$X$2:$X$4838,1,Syn_Lines!$AF$2:$AF$4838,"last_12m")/X5,"") | Z5: =IF(OR(W5="",Y5=""),"",Y5-W5) | AA5: =COUNTIFS(Syn_Lines!$C$2:$C$4838,$A5,Syn_Lines!$L$2:$L$4838,1)
A6: SUP-02 | B6: =COUNTIFS(Syn_Lines!$C$2:$C$4838,$A6,Syn_Lines!$U$2:$U$4838,1) | C6: =COUNTIFS(Syn_Lines!$C$2:$C$4838,$A6,Syn_Lines!$X$2:$X$4838,1) | D6: =IF(B6>0,C6/B6,"") | E6: =IF(B6>0,COUNTIFS(Syn_Lines!$C$2:$C$4838,$A6,Syn_Lines!$V$2:$V$4838,1)/B6,"") | F6: =IF(B6>0,COUNTIFS(Syn_Lines!$C$2:$C$4838,$A6,Syn_Lines!$W$2:$W$4838,1)/B6,"") | G6: =COUNTIFS(Syn_Lines!$C$2:$C$4838,$A6,Syn_Lines!$U$2:$U$4838,1,Syn_Lines!$AB$2:$AB$4838,">0") | H6: =IF(B6>0,AVERAGEIFS(Syn_Lines!$AB$2:$AB$4838,Syn_Lines!$C$2:$C$4838,$A6,Syn_Lines!$U$2:$U$4838,1),"") | I6: =COUNTIFS(Syn_Lines!$C$2:$C$4838,$A6,Syn_Lines!$Y$2:$Y$4838,1) | J6: =IF(I6>0,AVERAGEIFS(Syn_Lines!$AC$2:$AC$4838,Syn_Lines!$C$2:$C$4838,$A6,Syn_Lines!$Y$2:$Y$4838,1),"") | K6: =IF(I6>1,SQRT(MAX(0,(SUMIFS(Syn_Lines!$AD$2:$AD$4838,Syn_Lines!$C$2:$C$4838,$A6,Syn_Lines!$Y$2:$Y$4838,1)-I6*J6^2)/(I6-1))),"") | L6: =SUMIFS(Syn_Lines!$M$2:$M$4838,Syn_Lines!$C$2:$C$4838,$A6,Syn_Lines!$K$2:$K$4838,0) | M6: =SUMIFS(Syn_Lines!$O$2:$O$4838,Syn_Lines!$C$2:$C$4838,$A6,Syn_Lines!$K$2:$K$4838,0) | N6: =IF(L6>0,M6/L6,"") | O6: =SUMIFS(Syn_Lines!$S$2:$S$4838,Syn_Lines!$C$2:$C$4838,$A6,Syn_Lines!$K$2:$K$4838,0) | P6: =SUMIFS(Syn_Lines!$T$2:$T$4838,Syn_Lines!$C$2:$C$4838,$A6,Syn_Lines!$K$2:$K$4838,0) | Q6: =IF(P6>0,O6/P6-1,"") | R6: =O6/SUM($O$5:$O$18) | S6: =COUNTIFS(Syn_Lines!$C$2:$C$4838,$A6,Syn_Lines!$Z$2:$Z$4838,1) | T6: =COUNTIFS(Syn_Lines!$C$2:$C$4838,$A6,Syn_Lines!$AA$2:$AA$4838,1) | U6: =SUMIFS(Syn_Lines!$AE$2:$AE$4838,Syn_Lines!$C$2:$C$4838,$A6,Syn_Lines!$AA$2:$AA$4838,1) | V6: =COUNTIFS(Syn_Lines!$C$2:$C$4838,$A6,Syn_Lines!$U$2:$U$4838,1,Syn_Lines!$AF$2:$AF$4838,"prior_12m") | W6: =IF(V6>0,COUNTIFS(Syn_Lines!$C$2:$C$4838,$A6,Syn_Lines!$X$2:$X$4838,1,Syn_Lines!$AF$2:$AF$4838,"prior_12m")/V6,"") | X6: =COUNTIFS(Syn_Lines!$C$2:$C$4838,$A6,Syn_Lines!$U$2:$U$4838,1,Syn_Lines!$AF$2:$AF$4838,"last_12m") | Y6: =IF(X6>0,COUNTIFS(Syn_Lines!$C$2:$C$4838,$A6,Syn_Lines!$X$2:$X$4838,1,Syn_Lines!$AF$2:$AF$4838,"last_12m")/X6,"") | Z6: =IF(OR(W6="",Y6=""),"",Y6-W6) | AA6: =COUNTIFS(Syn_Lines!$C$2:$C$4838,$A6,Syn_Lines!$L$2:$L$4838,1)
A7: SUP-03 | B7: =COUNTIFS(Syn_Lines!$C$2:$C$4838,$A7,Syn_Lines!$U$2:$U$4838,1) | C7: =COUNTIFS(Syn_Lines!$C$2:$C$4838,$A7,Syn_Lines!$X$2:$X$4838,1) | D7: =IF(B7>0,C7/B7,"") | E7: =IF(B7>0,COUNTIFS(Syn_Lines!$C$2:$C$4838,$A7,Syn_Lines!$V$2:$V$4838,1)/B7,"") | F7: =IF(B7>0,COUNTIFS(Syn_Lines!$C$2:$C$4838,$A7,Syn_Lines!$W$2:$W$4838,1)/B7,"") | G7: =COUNTIFS(Syn_Lines!$C$2:$C$4838,$A7,Syn_Lines!$U$2:$U$4838,1,Syn_Lines!$AB$2:$AB$4838,">0") | H7: =IF(B7>0,AVERAGEIFS(Syn_Lines!$AB$2:$AB$4838,Syn_Lines!$C$2:$C$4838,$A7,Syn_Lines!$U$2:$U$4838,1),"") | I7: =COUNTIFS(Syn_Lines!$C$2:$C$4838,$A7,Syn_Lines!$Y$2:$Y$4838,1) | J7: =IF(I7>0,AVERAGEIFS(Syn_Lines!$AC$2:$AC$4838,Syn_Lines!$C$2:$C$4838,$A7,Syn_Lines!$Y$2:$Y$4838,1),"") | K7: =IF(I7>1,SQRT(MAX(0,(SUMIFS(Syn_Lines!$AD$2:$AD$4838,Syn_Lines!$C$2:$C$4838,$A7,Syn_Lines!$Y$2:$Y$4838,1)-I7*J7^2)/(I7-1))),"") | L7: =SUMIFS(Syn_Lines!$M$2:$M$4838,Syn_Lines!$C$2:$C$4838,$A7,Syn_Lines!$K$2:$K$4838,0) | M7: =SUMIFS(Syn_Lines!$O$2:$O$4838,Syn_Lines!$C$2:$C$4838,$A7,Syn_Lines!$K$2:$K$4838,0) | N7: =IF(L7>0,M7/L7,"") | O7: =SUMIFS(Syn_Lines!$S$2:$S$4838,Syn_Lines!$C$2:$C$4838,$A7,Syn_Lines!$K$2:$K$4838,0) | P7: =SUMIFS(Syn_Lines!$T$2:$T$4838,Syn_Lines!$C$2:$C$4838,$A7,Syn_Lines!$K$2:$K$4838,0) | Q7: =IF(P7>0,O7/P7-1,"") | R7: =O7/SUM($O$5:$O$18) | S7: =COUNTIFS(Syn_Lines!$C$2:$C$4838,$A7,Syn_Lines!$Z$2:$Z$4838,1) | T7: =COUNTIFS(Syn_Lines!$C$2:$C$4838,$A7,Syn_Lines!$AA$2:$AA$4838,1) | U7: =SUMIFS(Syn_Lines!$AE$2:$AE$4838,Syn_Lines!$C$2:$C$4838,$A7,Syn_Lines!$AA$2:$AA$4838,1) | V7: =COUNTIFS(Syn_Lines!$C$2:$C$4838,$A7,Syn_Lines!$U$2:$U$4838,1,Syn_Lines!$AF$2:$AF$4838,"prior_12m") | W7: =IF(V7>0,COUNTIFS(Syn_Lines!$C$2:$C$4838,$A7,Syn_Lines!$X$2:$X$4838,1,Syn_Lines!$AF$2:$AF$4838,"prior_12m")/V7,"") | X7: =COUNTIFS(Syn_Lines!$C$2:$C$4838,$A7,Syn_Lines!$U$2:$U$4838,1,Syn_Lines!$AF$2:$AF$4838,"last_12m") | Y7: =IF(X7>0,COUNTIFS(Syn_Lines!$C$2:$C$4838,$A7,Syn_Lines!$X$2:$X$4838,1,Syn_Lines!$AF$2:$AF$4838,"last_12m")/X7,"") | Z7: =IF(OR(W7="",Y7=""),"",Y7-W7) | AA7: =COUNTIFS(Syn_Lines!$C$2:$C$4838,$A7,Syn_Lines!$L$2:$L$4838,1)
A8: SUP-04 | B8: =COUNTIFS(Syn_Lines!$C$2:$C$4838,$A8,Syn_Lines!$U$2:$U$4838,1) | C8: =COUNTIFS(Syn_Lines!$C$2:$C$4838,$A8,Syn_Lines!$X$2:$X$4838,1) | D8: =IF(B8>0,C8/B8,"") | E8: =IF(B8>0,COUNTIFS(Syn_Lines!$C$2:$C$4838,$A8,Syn_Lines!$V$2:$V$4838,1)/B8,"") | F8: =IF(B8>0,COUNTIFS(Syn_Lines!$C$2:$C$4838,$A8,Syn_Lines!$W$2:$W$4838,1)/B8,"") | G8: =COUNTIFS(Syn_Lines!$C$2:$C$4838,$A8,Syn_Lines!$U$2:$U$4838,1,Syn_Lines!$AB$2:$AB$4838,">0") | H8: =IF(B8>0,AVERAGEIFS(Syn_Lines!$AB$2:$AB$4838,Syn_Lines!$C$2:$C$4838,$A8,Syn_Lines!$U$2:$U$4838,1),"") | I8: =COUNTIFS(Syn_Lines!$C$2:$C$4838,$A8,Syn_Lines!$Y$2:$Y$4838,1) | J8: =IF(I8>0,AVERAGEIFS(Syn_Lines!$AC$2:$AC$4838,Syn_Lines!$C$2:$C$4838,$A8,Syn_Lines!$Y$2:$Y$4838,1),"") | K8: =IF(I8>1,SQRT(MAX(0,(SUMIFS(Syn_Lines!$AD$2:$AD$4838,Syn_Lines!$C$2:$C$4838,$A8,Syn_Lines!$Y$2:$Y$4838,1)-I8*J8^2)/(I8-1))),"") | L8: =SUMIFS(Syn_Lines!$M$2:$M$4838,Syn_Lines!$C$2:$C$4838,$A8,Syn_Lines!$K$2:$K$4838,0) | M8: =SUMIFS(Syn_Lines!$O$2:$O$4838,Syn_Lines!$C$2:$C$4838,$A8,Syn_Lines!$K$2:$K$4838,0) | N8: =IF(L8>0,M8/L8,"") | O8: =SUMIFS(Syn_Lines!$S$2:$S$4838,Syn_Lines!$C$2:$C$4838,$A8,Syn_Lines!$K$2:$K$4838,0) | P8: =SUMIFS(Syn_Lines!$T$2:$T$4838,Syn_Lines!$C$2:$C$4838,$A8,Syn_Lines!$K$2:$K$4838,0) | Q8: =IF(P8>0,O8/P8-1,"") | R8: =O8/SUM($O$5:$O$18) | S8: =COUNTIFS(Syn_Lines!$C$2:$C$4838,$A8,Syn_Lines!$Z$2:$Z$4838,1) | T8: =COUNTIFS(Syn_Lines!$C$2:$C$4838,$A8,Syn_Lines!$AA$2:$AA$4838,1) | U8: =SUMIFS(Syn_Lines!$AE$2:$AE$4838,Syn_Lines!$C$2:$C$4838,$A8,Syn_Lines!$AA$2:$AA$4838,1) | V8: =COUNTIFS(Syn_Lines!$C$2:$C$4838,$A8,Syn_Lines!$U$2:$U$4838,1,Syn_Lines!$AF$2:$AF$4838,"prior_12m") | W8: =IF(V8>0,COUNTIFS(Syn_Lines!$C$2:$C$4838,$A8,Syn_Lines!$X$2:$X$4838,1,Syn_Lines!$AF$2:$AF$4838,"prior_12m")/V8,"") | X8: =COUNTIFS(Syn_Lines!$C$2:$C$4838,$A8,Syn_Lines!$U$2:$U$4838,1,Syn_Lines!$AF$2:$AF$4838,"last_12m") | Y8: =IF(X8>0,COUNTIFS(Syn_Lines!$C$2:$C$4838,$A8,Syn_Lines!$X$2:$X$4838,1,Syn_Lines!$AF$2:$AF$4838,"last_12m")/X8,"") | Z8: =IF(OR(W8="",Y8=""),"",Y8-W8) | AA8: =COUNTIFS(Syn_Lines!$C$2:$C$4838,$A8,Syn_Lines!$L$2:$L$4838,1)
A9: SUP-05 | B9: =COUNTIFS(Syn_Lines!$C$2:$C$4838,$A9,Syn_Lines!$U$2:$U$4838,1) | C9: =COUNTIFS(Syn_Lines!$C$2:$C$4838,$A9,Syn_Lines!$X$2:$X$4838,1) | D9: =IF(B9>0,C9/B9,"") | E9: =IF(B9>0,COUNTIFS(Syn_Lines!$C$2:$C$4838,$A9,Syn_Lines!$V$2:$V$4838,1)/B9,"") | F9: =IF(B9>0,COUNTIFS(Syn_Lines!$C$2:$C$4838,$A9,Syn_Lines!$W$2:$W$4838,1)/B9,"") | G9: =COUNTIFS(Syn_Lines!$C$2:$C$4838,$A9,Syn_Lines!$U$2:$U$4838,1,Syn_Lines!$AB$2:$AB$4838,">0") | H9: =IF(B9>0,AVERAGEIFS(Syn_Lines!$AB$2:$AB$4838,Syn_Lines!$C$2:$C$4838,$A9,Syn_Lines!$U$2:$U$4838,1),"") | I9: =COUNTIFS(Syn_Lines!$C$2:$C$4838,$A9,Syn_Lines!$Y$2:$Y$4838,1) | J9: =IF(I9>0,AVERAGEIFS(Syn_Lines!$AC$2:$AC$4838,Syn_Lines!$C$2:$C$4838,$A9,Syn_Lines!$Y$2:$Y$4838,1),"") | K9: =IF(I9>1,SQRT(MAX(0,(SUMIFS(Syn_Lines!$AD$2:$AD$4838,Syn_Lines!$C$2:$C$4838,$A9,Syn_Lines!$Y$2:$Y$4838,1)-I9*J9^2)/(I9-1))),"") | L9: =SUMIFS(Syn_Lines!$M$2:$M$4838,Syn_Lines!$C$2:$C$4838,$A9,Syn_Lines!$K$2:$K$4838,0) | M9: =SUMIFS(Syn_Lines!$O$2:$O$4838,Syn_Lines!$C$2:$C$4838,$A9,Syn_Lines!$K$2:$K$4838,0) | N9: =IF(L9>0,M9/L9,"") | O9: =SUMIFS(Syn_Lines!$S$2:$S$4838,Syn_Lines!$C$2:$C$4838,$A9,Syn_Lines!$K$2:$K$4838,0) | P9: =SUMIFS(Syn_Lines!$T$2:$T$4838,Syn_Lines!$C$2:$C$4838,$A9,Syn_Lines!$K$2:$K$4838,0) | Q9: =IF(P9>0,O9/P9-1,"") | R9: =O9/SUM($O$5:$O$18) | S9: =COUNTIFS(Syn_Lines!$C$2:$C$4838,$A9,Syn_Lines!$Z$2:$Z$4838,1) | T9: =COUNTIFS(Syn_Lines!$C$2:$C$4838,$A9,Syn_Lines!$AA$2:$AA$4838,1) | U9: =SUMIFS(Syn_Lines!$AE$2:$AE$4838,Syn_Lines!$C$2:$C$4838,$A9,Syn_Lines!$AA$2:$AA$4838,1) | V9: =COUNTIFS(Syn_Lines!$C$2:$C$4838,$A9,Syn_Lines!$U$2:$U$4838,1,Syn_Lines!$AF$2:$AF$4838,"prior_12m") | W9: =IF(V9>0,COUNTIFS(Syn_Lines!$C$2:$C$4838,$A9,Syn_Lines!$X$2:$X$4838,1,Syn_Lines!$AF$2:$AF$4838,"prior_12m")/V9,"") | X9: =COUNTIFS(Syn_Lines!$C$2:$C$4838,$A9,Syn_Lines!$U$2:$U$4838,1,Syn_Lines!$AF$2:$AF$4838,"last_12m") | Y9: =IF(X9>0,COUNTIFS(Syn_Lines!$C$2:$C$4838,$A9,Syn_Lines!$X$2:$X$4838,1,Syn_Lines!$AF$2:$AF$4838,"last_12m")/X9,"") | Z9: =IF(OR(W9="",Y9=""),"",Y9-W9) | AA9: =COUNTIFS(Syn_Lines!$C$2:$C$4838,$A9,Syn_Lines!$L$2:$L$4838,1)
A10: SUP-06 | B10: =COUNTIFS(Syn_Lines!$C$2:$C$4838,$A10,Syn_Lines!$U$2:$U$4838,1) | C10: =COUNTIFS(Syn_Lines!$C$2:$C$4838,$A10,Syn_Lines!$X$2:$X$4838,1) | D10: =IF(B10>0,C10/B10,"") | E10: =IF(B10>0,COUNTIFS(Syn_Lines!$C$2:$C$4838,$A10,Syn_Lines!$V$2:$V$4838,1)/B10,"") | F10: =IF(B10>0,COUNTIFS(Syn_Lines!$C$2:$C$4838,$A10,Syn_Lines!$W$2:$W$4838,1)/B10,"") | G10: =COUNTIFS(Syn_Lines!$C$2:$C$4838,$A10,Syn_Lines!$U$2:$U$4838,1,Syn_Lines!$AB$2:$AB$4838,">0") | H10: =IF(B10>0,AVERAGEIFS(Syn_Lines!$AB$2:$AB$4838,Syn_Lines!$C$2:$C$4838,$A10,Syn_Lines!$U$2:$U$4838,1),"") | I10: =COUNTIFS(Syn_Lines!$C$2:$C$4838,$A10,Syn_Lines!$Y$2:$Y$4838,1) | J10: =IF(I10>0,AVERAGEIFS(Syn_Lines!$AC$2:$AC$4838,Syn_Lines!$C$2:$C$4838,$A10,Syn_Lines!$Y$2:$Y$4838,1),"") | K10: =IF(I10>1,SQRT(MAX(0,(SUMIFS(Syn_Lines!$AD$2:$AD$4838,Syn_Lines!$C$2:$C$4838,$A10,Syn_Lines!$Y$2:$Y$4838,1)-I10*J10^2)/(I10-1))),"") | L10: =SUMIFS(Syn_Lines!$M$2:$M$4838,Syn_Lines!$C$2:$C$4838,$A10,Syn_Lines!$K$2:$K$4838,0) | M10: =SUMIFS(Syn_Lines!$O$2:$O$4838,Syn_Lines!$C$2:$C$4838,$A10,Syn_Lines!$K$2:$K$4838,0) | N10: =IF(L10>0,M10/L10,"") | O10: =SUMIFS(Syn_Lines!$S$2:$S$4838,Syn_Lines!$C$2:$C$4838,$A10,Syn_Lines!$K$2:$K$4838,0) | P10: =SUMIFS(Syn_Lines!$T$2:$T$4838,Syn_Lines!$C$2:$C$4838,$A10,Syn_Lines!$K$2:$K$4838,0) | Q10: =IF(P10>0,O10/P10-1,"") | R10: =O10/SUM($O$5:$O$18) | S10: =COUNTIFS(Syn_Lines!$C$2:$C$4838,$A10,Syn_Lines!$Z$2:$Z$4838,1) | T10: =COUNTIFS(Syn_Lines!$C$2:$C$4838,$A10,Syn_Lines!$AA$2:$AA$4838,1) | U10: =SUMIFS(Syn_Lines!$AE$2:$AE$4838,Syn_Lines!$C$2:$C$4838,$A10,Syn_Lines!$AA$2:$AA$4838,1) | V10: =COUNTIFS(Syn_Lines!$C$2:$C$4838,$A10,Syn_Lines!$U$2:$U$4838,1,Syn_Lines!$AF$2:$AF$4838,"prior_12m") | W10: =IF(V10>0,COUNTIFS(Syn_Lines!$C$2:$C$4838,$A10,Syn_Lines!$X$2:$X$4838,1,Syn_Lines!$AF$2:$AF$4838,"prior_12m")/V10,"") | X10: =COUNTIFS(Syn_Lines!$C$2:$C$4838,$A10,Syn_Lines!$U$2:$U$4838,1,Syn_Lines!$AF$2:$AF$4838,"last_12m") | Y10: =IF(X10>0,COUNTIFS(Syn_Lines!$C$2:$C$4838,$A10,Syn_Lines!$X$2:$X$4838,1,Syn_Lines!$AF$2:$AF$4838,"last_12m")/X10,"") | Z10: =IF(OR(W10="",Y10=""),"",Y10-W10) | AA10: =COUNTIFS(Syn_Lines!$C$2:$C$4838,$A10,Syn_Lines!$L$2:$L$4838,1)
A11: SUP-07 | B11: =COUNTIFS(Syn_Lines!$C$2:$C$4838,$A11,Syn_Lines!$U$2:$U$4838,1) | C11: =COUNTIFS(Syn_Lines!$C$2:$C$4838,$A11,Syn_Lines!$X$2:$X$4838,1) | D11: =IF(B11>0,C11/B11,"") | E11: =IF(B11>0,COUNTIFS(Syn_Lines!$C$2:$C$4838,$A11,Syn_Lines!$V$2:$V$4838,1)/B11,"") | F11: =IF(B11>0,COUNTIFS(Syn_Lines!$C$2:$C$4838,$A11,Syn_Lines!$W$2:$W$4838,1)/B11,"") | G11: =COUNTIFS(Syn_Lines!$C$2:$C$4838,$A11,Syn_Lines!$U$2:$U$4838,1,Syn_Lines!$AB$2:$AB$4838,">0") | H11: =IF(B11>0,AVERAGEIFS(Syn_Lines!$AB$2:$AB$4838,Syn_Lines!$C$2:$C$4838,$A11,Syn_Lines!$U$2:$U$4838,1),"") | I11: =COUNTIFS(Syn_Lines!$C$2:$C$4838,$A11,Syn_Lines!$Y$2:$Y$4838,1) | J11: =IF(I11>0,AVERAGEIFS(Syn_Lines!$AC$2:$AC$4838,Syn_Lines!$C$2:$C$4838,$A11,Syn_Lines!$Y$2:$Y$4838,1),"") | K11: =IF(I11>1,SQRT(MAX(0,(SUMIFS(Syn_Lines!$AD$2:$AD$4838,Syn_Lines!$C$2:$C$4838,$A11,Syn_Lines!$Y$2:$Y$4838,1)-I11*J11^2)/(I11-1))),"") | L11: =SUMIFS(Syn_Lines!$M$2:$M$4838,Syn_Lines!$C$2:$C$4838,$A11,Syn_Lines!$K$2:$K$4838,0) | M11: =SUMIFS(Syn_Lines!$O$2:$O$4838,Syn_Lines!$C$2:$C$4838,$A11,Syn_Lines!$K$2:$K$4838,0) | N11: =IF(L11>0,M11/L11,"") | O11: =SUMIFS(Syn_Lines!$S$2:$S$4838,Syn_Lines!$C$2:$C$4838,$A11,Syn_Lines!$K$2:$K$4838,0) | P11: =SUMIFS(Syn_Lines!$T$2:$T$4838,Syn_Lines!$C$2:$C$4838,$A11,Syn_Lines!$K$2:$K$4838,0) | Q11: =IF(P11>0,O11/P11-1,"") | R11: =O11/SUM($O$5:$O$18) | S11: =COUNTIFS(Syn_Lines!$C$2:$C$4838,$A11,Syn_Lines!$Z$2:$Z$4838,1) | T11: =COUNTIFS(Syn_Lines!$C$2:$C$4838,$A11,Syn_Lines!$AA$2:$AA$4838,1) | U11: =SUMIFS(Syn_Lines!$AE$2:$AE$4838,Syn_Lines!$C$2:$C$4838,$A11,Syn_Lines!$AA$2:$AA$4838,1) | V11: =COUNTIFS(Syn_Lines!$C$2:$C$4838,$A11,Syn_Lines!$U$2:$U$4838,1,Syn_Lines!$AF$2:$AF$4838,"prior_12m") | W11: =IF(V11>0,COUNTIFS(Syn_Lines!$C$2:$C$4838,$A11,Syn_Lines!$X$2:$X$4838,1,Syn_Lines!$AF$2:$AF$4838,"prior_12m")/V11,"") | X11: =COUNTIFS(Syn_Lines!$C$2:$C$4838,$A11,Syn_Lines!$U$2:$U$4838,1,Syn_Lines!$AF$2:$AF$4838,"last_12m") | Y11: =IF(X11>0,COUNTIFS(Syn_Lines!$C$2:$C$4838,$A11,Syn_Lines!$X$2:$X$4838,1,Syn_Lines!$AF$2:$AF$4838,"last_12m")/X11,"") | Z11: =IF(OR(W11="",Y11=""),"",Y11-W11) | AA11: =COUNTIFS(Syn_Lines!$C$2:$C$4838,$A11,Syn_Lines!$L$2:$L$4838,1)
A12: SUP-08 | B12: =COUNTIFS(Syn_Lines!$C$2:$C$4838,$A12,Syn_Lines!$U$2:$U$4838,1) | C12: =COUNTIFS(Syn_Lines!$C$2:$C$4838,$A12,Syn_Lines!$X$2:$X$4838,1) | D12: =IF(B12>0,C12/B12,"") | E12: =IF(B12>0,COUNTIFS(Syn_Lines!$C$2:$C$4838,$A12,Syn_Lines!$V$2:$V$4838,1)/B12,"") | F12: =IF(B12>0,COUNTIFS(Syn_Lines!$C$2:$C$4838,$A12,Syn_Lines!$W$2:$W$4838,1)/B12,"") | G12: =COUNTIFS(Syn_Lines!$C$2:$C$4838,$A12,Syn_Lines!$U$2:$U$4838,1,Syn_Lines!$AB$2:$AB$4838,">0") | H12: =IF(B12>0,AVERAGEIFS(Syn_Lines!$AB$2:$AB$4838,Syn_Lines!$C$2:$C$4838,$A12,Syn_Lines!$U$2:$U$4838,1),"") | I12: =COUNTIFS(Syn_Lines!$C$2:$C$4838,$A12,Syn_Lines!$Y$2:$Y$4838,1) | J12: =IF(I12>0,AVERAGEIFS(Syn_Lines!$AC$2:$AC$4838,Syn_Lines!$C$2:$C$4838,$A12,Syn_Lines!$Y$2:$Y$4838,1),"") | K12: =IF(I12>1,SQRT(MAX(0,(SUMIFS(Syn_Lines!$AD$2:$AD$4838,Syn_Lines!$C$2:$C$4838,$A12,Syn_Lines!$Y$2:$Y$4838,1)-I12*J12^2)/(I12-1))),"") | L12: =SUMIFS(Syn_Lines!$M$2:$M$4838,Syn_Lines!$C$2:$C$4838,$A12,Syn_Lines!$K$2:$K$4838,0) | M12: =SUMIFS(Syn_Lines!$O$2:$O$4838,Syn_Lines!$C$2:$C$4838,$A12,Syn_Lines!$K$2:$K$4838,0) | N12: =IF(L12>0,M12/L12,"") | O12: =SUMIFS(Syn_Lines!$S$2:$S$4838,Syn_Lines!$C$2:$C$4838,$A12,Syn_Lines!$K$2:$K$4838,0) | P12: =SUMIFS(Syn_Lines!$T$2:$T$4838,Syn_Lines!$C$2:$C$4838,$A12,Syn_Lines!$K$2:$K$4838,0) | Q12: =IF(P12>0,O12/P12-1,"") | R12: =O12/SUM($O$5:$O$18) | S12: =COUNTIFS(Syn_Lines!$C$2:$C$4838,$A12,Syn_Lines!$Z$2:$Z$4838,1) | T12: =COUNTIFS(Syn_Lines!$C$2:$C$4838,$A12,Syn_Lines!$AA$2:$AA$4838,1) | U12: =SUMIFS(Syn_Lines!$AE$2:$AE$4838,Syn_Lines!$C$2:$C$4838,$A12,Syn_Lines!$AA$2:$AA$4838,1) | V12: =COUNTIFS(Syn_Lines!$C$2:$C$4838,$A12,Syn_Lines!$U$2:$U$4838,1,Syn_Lines!$AF$2:$AF$4838,"prior_12m") | W12: =IF(V12>0,COUNTIFS(Syn_Lines!$C$2:$C$4838,$A12,Syn_Lines!$X$2:$X$4838,1,Syn_Lines!$AF$2:$AF$4838,"prior_12m")/V12,"") | X12: =COUNTIFS(Syn_Lines!$C$2:$C$4838,$A12,Syn_Lines!$U$2:$U$4838,1,Syn_Lines!$AF$2:$AF$4838,"last_12m") | Y12: =IF(X12>0,COUNTIFS(Syn_Lines!$C$2:$C$4838,$A12,Syn_Lines!$X$2:$X$4838,1,Syn_Lines!$AF$2:$AF$4838,"last_12m")/X12,"") | Z12: =IF(OR(W12="",Y12=""),"",Y12-W12) | AA12: =COUNTIFS(Syn_Lines!$C$2:$C$4838,$A12,Syn_Lines!$L$2:$L$4838,1)
A13: SUP-09 | B13: =COUNTIFS(Syn_Lines!$C$2:$C$4838,$A13,Syn_Lines!$U$2:$U$4838,1) | C13: =COUNTIFS(Syn_Lines!$C$2:$C$4838,$A13,Syn_Lines!$X$2:$X$4838,1) | D13: =IF(B13>0,C13/B13,"") | E13: =IF(B13>0,COUNTIFS(Syn_Lines!$C$2:$C$4838,$A13,Syn_Lines!$V$2:$V$4838,1)/B13,"") | F13: =IF(B13>0,COUNTIFS(Syn_Lines!$C$2:$C$4838,$A13,Syn_Lines!$W$2:$W$4838,1)/B13,"") | G13: =COUNTIFS(Syn_Lines!$C$2:$C$4838,$A13,Syn_Lines!$U$2:$U$4838,1,Syn_Lines!$AB$2:$AB$4838,">0") | H13: =IF(B13>0,AVERAGEIFS(Syn_Lines!$AB$2:$AB$4838,Syn_Lines!$C$2:$C$4838,$A13,Syn_Lines!$U$2:$U$4838,1),"") | I13: =COUNTIFS(Syn_Lines!$C$2:$C$4838,$A13,Syn_Lines!$Y$2:$Y$4838,1) | J13: =IF(I13>0,AVERAGEIFS(Syn_Lines!$AC$2:$AC$4838,Syn_Lines!$C$2:$C$4838,$A13,Syn_Lines!$Y$2:$Y$4838,1),"") | K13: =IF(I13>1,SQRT(MAX(0,(SUMIFS(Syn_Lines!$AD$2:$AD$4838,Syn_Lines!$C$2:$C$4838,$A13,Syn_Lines!$Y$2:$Y$4838,1)-I13*J13^2)/(I13-1))),"") | L13: =SUMIFS(Syn_Lines!$M$2:$M$4838,Syn_Lines!$C$2:$C$4838,$A13,Syn_Lines!$K$2:$K$4838,0) | M13: =SUMIFS(Syn_Lines!$O$2:$O$4838,Syn_Lines!$C$2:$C$4838,$A13,Syn_Lines!$K$2:$K$4838,0) | N13: =IF(L13>0,M13/L13,"") | O13: =SUMIFS(Syn_Lines!$S$2:$S$4838,Syn_Lines!$C$2:$C$4838,$A13,Syn_Lines!$K$2:$K$4838,0) | P13: =SUMIFS(Syn_Lines!$T$2:$T$4838,Syn_Lines!$C$2:$C$4838,$A13,Syn_Lines!$K$2:$K$4838,0) | Q13: =IF(P13>0,O13/P13-1,"") | R13: =O13/SUM($O$5:$O$18) | S13: =COUNTIFS(Syn_Lines!$C$2:$C$4838,$A13,Syn_Lines!$Z$2:$Z$4838,1) | T13: =COUNTIFS(Syn_Lines!$C$2:$C$4838,$A13,Syn_Lines!$AA$2:$AA$4838,1) | U13: =SUMIFS(Syn_Lines!$AE$2:$AE$4838,Syn_Lines!$C$2:$C$4838,$A13,Syn_Lines!$AA$2:$AA$4838,1) | V13: =COUNTIFS(Syn_Lines!$C$2:$C$4838,$A13,Syn_Lines!$U$2:$U$4838,1,Syn_Lines!$AF$2:$AF$4838,"prior_12m") | W13: =IF(V13>0,COUNTIFS(Syn_Lines!$C$2:$C$4838,$A13,Syn_Lines!$X$2:$X$4838,1,Syn_Lines!$AF$2:$AF$4838,"prior_12m")/V13,"") | X13: =COUNTIFS(Syn_Lines!$C$2:$C$4838,$A13,Syn_Lines!$U$2:$U$4838,1,Syn_Lines!$AF$2:$AF$4838,"last_12m") | Y13: =IF(X13>0,COUNTIFS(Syn_Lines!$C$2:$C$4838,$A13,Syn_Lines!$X$2:$X$4838,1,Syn_Lines!$AF$2:$AF$4838,"last_12m")/X13,"") | Z13: =IF(OR(W13="",Y13=""),"",Y13-W13) | AA13: =COUNTIFS(Syn_Lines!$C$2:$C$4838,$A13,Syn_Lines!$L$2:$L$4838,1)
A14: SUP-10 | B14: =COUNTIFS(Syn_Lines!$C$2:$C$4838,$A14,Syn_Lines!$U$2:$U$4838,1) | C14: =COUNTIFS(Syn_Lines!$C$2:$C$4838,$A14,Syn_Lines!$X$2:$X$4838,1) | D14: =IF(B14>0,C14/B14,"") | E14: =IF(B14>0,COUNTIFS(Syn_Lines!$C$2:$C$4838,$A14,Syn_Lines!$V$2:$V$4838,1)/B14,"") | F14: =IF(B14>0,COUNTIFS(Syn_Lines!$C$2:$C$4838,$A14,Syn_Lines!$W$2:$W$4838,1)/B14,"") | G14: =COUNTIFS(Syn_Lines!$C$2:$C$4838,$A14,Syn_Lines!$U$2:$U$4838,1,Syn_Lines!$AB$2:$AB$4838,">0") | H14: =IF(B14>0,AVERAGEIFS(Syn_Lines!$AB$2:$AB$4838,Syn_Lines!$C$2:$C$4838,$A14,Syn_Lines!$U$2:$U$4838,1),"") | I14: =COUNTIFS(Syn_Lines!$C$2:$C$4838,$A14,Syn_Lines!$Y$2:$Y$4838,1) | J14: =IF(I14>0,AVERAGEIFS(Syn_Lines!$AC$2:$AC$4838,Syn_Lines!$C$2:$C$4838,$A14,Syn_Lines!$Y$2:$Y$4838,1),"") | K14: =IF(I14>1,SQRT(MAX(0,(SUMIFS(Syn_Lines!$AD$2:$AD$4838,Syn_Lines!$C$2:$C$4838,$A14,Syn_Lines!$Y$2:$Y$4838,1)-I14*J14^2)/(I14-1))),"") | L14: =SUMIFS(Syn_Lines!$M$2:$M$4838,Syn_Lines!$C$2:$C$4838,$A14,Syn_Lines!$K$2:$K$4838,0) | M14: =SUMIFS(Syn_Lines!$O$2:$O$4838,Syn_Lines!$C$2:$C$4838,$A14,Syn_Lines!$K$2:$K$4838,0) | N14: =IF(L14>0,M14/L14,"") | O14: =SUMIFS(Syn_Lines!$S$2:$S$4838,Syn_Lines!$C$2:$C$4838,$A14,Syn_Lines!$K$2:$K$4838,0) | P14: =SUMIFS(Syn_Lines!$T$2:$T$4838,Syn_Lines!$C$2:$C$4838,$A14,Syn_Lines!$K$2:$K$4838,0) | Q14: =IF(P14>0,O14/P14-1,"") | R14: =O14/SUM($O$5:$O$18) | S14: =COUNTIFS(Syn_Lines!$C$2:$C$4838,$A14,Syn_Lines!$Z$2:$Z$4838,1) | T14: =COUNTIFS(Syn_Lines!$C$2:$C$4838,$A14,Syn_Lines!$AA$2:$AA$4838,1) | U14: =SUMIFS(Syn_Lines!$AE$2:$AE$4838,Syn_Lines!$C$2:$C$4838,$A14,Syn_Lines!$AA$2:$AA$4838,1) | V14: =COUNTIFS(Syn_Lines!$C$2:$C$4838,$A14,Syn_Lines!$U$2:$U$4838,1,Syn_Lines!$AF$2:$AF$4838,"prior_12m") | W14: =IF(V14>0,COUNTIFS(Syn_Lines!$C$2:$C$4838,$A14,Syn_Lines!$X$2:$X$4838,1,Syn_Lines!$AF$2:$AF$4838,"prior_12m")/V14,"") | X14: =COUNTIFS(Syn_Lines!$C$2:$C$4838,$A14,Syn_Lines!$U$2:$U$4838,1,Syn_Lines!$AF$2:$AF$4838,"last_12m") | Y14: =IF(X14>0,COUNTIFS(Syn_Lines!$C$2:$C$4838,$A14,Syn_Lines!$X$2:$X$4838,1,Syn_Lines!$AF$2:$AF$4838,"last_12m")/X14,"") | Z14: =IF(OR(W14="",Y14=""),"",Y14-W14) | AA14: =COUNTIFS(Syn_Lines!$C$2:$C$4838,$A14,Syn_Lines!$L$2:$L$4838,1)
A15: SUP-11 | B15: =COUNTIFS(Syn_Lines!$C$2:$C$4838,$A15,Syn_Lines!$U$2:$U$4838,1) | C15: =COUNTIFS(Syn_Lines!$C$2:$C$4838,$A15,Syn_Lines!$X$2:$X$4838,1) | D15: =IF(B15>0,C15/B15,"") | E15: =IF(B15>0,COUNTIFS(Syn_Lines!$C$2:$C$4838,$A15,Syn_Lines!$V$2:$V$4838,1)/B15,"") | F15: =IF(B15>0,COUNTIFS(Syn_Lines!$C$2:$C$4838,$A15,Syn_Lines!$W$2:$W$4838,1)/B15,"") | G15: =COUNTIFS(Syn_Lines!$C$2:$C$4838,$A15,Syn_Lines!$U$2:$U$4838,1,Syn_Lines!$AB$2:$AB$4838,">0") | H15: =IF(B15>0,AVERAGEIFS(Syn_Lines!$AB$2:$AB$4838,Syn_Lines!$C$2:$C$4838,$A15,Syn_Lines!$U$2:$U$4838,1),"") | I15: =COUNTIFS(Syn_Lines!$C$2:$C$4838,$A15,Syn_Lines!$Y$2:$Y$4838,1) | J15: =IF(I15>0,AVERAGEIFS(Syn_Lines!$AC$2:$AC$4838,Syn_Lines!$C$2:$C$4838,$A15,Syn_Lines!$Y$2:$Y$4838,1),"") | K15: =IF(I15>1,SQRT(MAX(0,(SUMIFS(Syn_Lines!$AD$2:$AD$4838,Syn_Lines!$C$2:$C$4838,$A15,Syn_Lines!$Y$2:$Y$4838,1)-I15*J15^2)/(I15-1))),"") | L15: =SUMIFS(Syn_Lines!$M$2:$M$4838,Syn_Lines!$C$2:$C$4838,$A15,Syn_Lines!$K$2:$K$4838,0) | M15: =SUMIFS(Syn_Lines!$O$2:$O$4838,Syn_Lines!$C$2:$C$4838,$A15,Syn_Lines!$K$2:$K$4838,0) | N15: =IF(L15>0,M15/L15,"") | O15: =SUMIFS(Syn_Lines!$S$2:$S$4838,Syn_Lines!$C$2:$C$4838,$A15,Syn_Lines!$K$2:$K$4838,0) | P15: =SUMIFS(Syn_Lines!$T$2:$T$4838,Syn_Lines!$C$2:$C$4838,$A15,Syn_Lines!$K$2:$K$4838,0) | Q15: =IF(P15>0,O15/P15-1,"") | R15: =O15/SUM($O$5:$O$18) | S15: =COUNTIFS(Syn_Lines!$C$2:$C$4838,$A15,Syn_Lines!$Z$2:$Z$4838,1) | T15: =COUNTIFS(Syn_Lines!$C$2:$C$4838,$A15,Syn_Lines!$AA$2:$AA$4838,1) | U15: =SUMIFS(Syn_Lines!$AE$2:$AE$4838,Syn_Lines!$C$2:$C$4838,$A15,Syn_Lines!$AA$2:$AA$4838,1) | V15: =COUNTIFS(Syn_Lines!$C$2:$C$4838,$A15,Syn_Lines!$U$2:$U$4838,1,Syn_Lines!$AF$2:$AF$4838,"prior_12m") | W15: =IF(V15>0,COUNTIFS(Syn_Lines!$C$2:$C$4838,$A15,Syn_Lines!$X$2:$X$4838,1,Syn_Lines!$AF$2:$AF$4838,"prior_12m")/V15,"") | X15: =COUNTIFS(Syn_Lines!$C$2:$C$4838,$A15,Syn_Lines!$U$2:$U$4838,1,Syn_Lines!$AF$2:$AF$4838,"last_12m") | Y15: =IF(X15>0,COUNTIFS(Syn_Lines!$C$2:$C$4838,$A15,Syn_Lines!$X$2:$X$4838,1,Syn_Lines!$AF$2:$AF$4838,"last_12m")/X15,"") | Z15: =IF(OR(W15="",Y15=""),"",Y15-W15) | AA15: =COUNTIFS(Syn_Lines!$C$2:$C$4838,$A15,Syn_Lines!$L$2:$L$4838,1)
A16: SUP-12 | B16: =COUNTIFS(Syn_Lines!$C$2:$C$4838,$A16,Syn_Lines!$U$2:$U$4838,1) | C16: =COUNTIFS(Syn_Lines!$C$2:$C$4838,$A16,Syn_Lines!$X$2:$X$4838,1) | D16: =IF(B16>0,C16/B16,"") | E16: =IF(B16>0,COUNTIFS(Syn_Lines!$C$2:$C$4838,$A16,Syn_Lines!$V$2:$V$4838,1)/B16,"") | F16: =IF(B16>0,COUNTIFS(Syn_Lines!$C$2:$C$4838,$A16,Syn_Lines!$W$2:$W$4838,1)/B16,"") | G16: =COUNTIFS(Syn_Lines!$C$2:$C$4838,$A16,Syn_Lines!$U$2:$U$4838,1,Syn_Lines!$AB$2:$AB$4838,">0") | H16: =IF(B16>0,AVERAGEIFS(Syn_Lines!$AB$2:$AB$4838,Syn_Lines!$C$2:$C$4838,$A16,Syn_Lines!$U$2:$U$4838,1),"") | I16: =COUNTIFS(Syn_Lines!$C$2:$C$4838,$A16,Syn_Lines!$Y$2:$Y$4838,1) | J16: =IF(I16>0,AVERAGEIFS(Syn_Lines!$AC$2:$AC$4838,Syn_Lines!$C$2:$C$4838,$A16,Syn_Lines!$Y$2:$Y$4838,1),"") | K16: =IF(I16>1,SQRT(MAX(0,(SUMIFS(Syn_Lines!$AD$2:$AD$4838,Syn_Lines!$C$2:$C$4838,$A16,Syn_Lines!$Y$2:$Y$4838,1)-I16*J16^2)/(I16-1))),"") | L16: =SUMIFS(Syn_Lines!$M$2:$M$4838,Syn_Lines!$C$2:$C$4838,$A16,Syn_Lines!$K$2:$K$4838,0) | M16: =SUMIFS(Syn_Lines!$O$2:$O$4838,Syn_Lines!$C$2:$C$4838,$A16,Syn_Lines!$K$2:$K$4838,0) | N16: =IF(L16>0,M16/L16,"") | O16: =SUMIFS(Syn_Lines!$S$2:$S$4838,Syn_Lines!$C$2:$C$4838,$A16,Syn_Lines!$K$2:$K$4838,0) | P16: =SUMIFS(Syn_Lines!$T$2:$T$4838,Syn_Lines!$C$2:$C$4838,$A16,Syn_Lines!$K$2:$K$4838,0) | Q16: =IF(P16>0,O16/P16-1,"") | R16: =O16/SUM($O$5:$O$18) | S16: =COUNTIFS(Syn_Lines!$C$2:$C$4838,$A16,Syn_Lines!$Z$2:$Z$4838,1) | T16: =COUNTIFS(Syn_Lines!$C$2:$C$4838,$A16,Syn_Lines!$AA$2:$AA$4838,1) | U16: =SUMIFS(Syn_Lines!$AE$2:$AE$4838,Syn_Lines!$C$2:$C$4838,$A16,Syn_Lines!$AA$2:$AA$4838,1) | V16: =COUNTIFS(Syn_Lines!$C$2:$C$4838,$A16,Syn_Lines!$U$2:$U$4838,1,Syn_Lines!$AF$2:$AF$4838,"prior_12m") | W16: =IF(V16>0,COUNTIFS(Syn_Lines!$C$2:$C$4838,$A16,Syn_Lines!$X$2:$X$4838,1,Syn_Lines!$AF$2:$AF$4838,"prior_12m")/V16,"") | X16: =COUNTIFS(Syn_Lines!$C$2:$C$4838,$A16,Syn_Lines!$U$2:$U$4838,1,Syn_Lines!$AF$2:$AF$4838,"last_12m") | Y16: =IF(X16>0,COUNTIFS(Syn_Lines!$C$2:$C$4838,$A16,Syn_Lines!$X$2:$X$4838,1,Syn_Lines!$AF$2:$AF$4838,"last_12m")/X16,"") | Z16: =IF(OR(W16="",Y16=""),"",Y16-W16) | AA16: =COUNTIFS(Syn_Lines!$C$2:$C$4838,$A16,Syn_Lines!$L$2:$L$4838,1)
... A18: SUP-14 | B18: =COUNTIFS(Syn_Lines!$C$2:$C$4838,$A18,Syn_Lines!$U$2:$U$4838,1) | C18: =COUNTIFS(Syn_Lines!$C$2:$C$4838,$A18,Syn_Lines!$X$2:$X$4838,1) | D18: =IF(B18>0,C18/B18,"") | E18: =IF(B18>0,COUNTIFS(Syn_Lines!$C$2:$C$4838,$A18,Syn_Lines!$V$2:$V$4838,1)/B18,"") | F18: =IF(B18>0,COUNTIFS(Syn_Lines!$C$2:$C$4838,$A18,Syn_Lines!$W$2:$W$4838,1)/B18,"") | G18: =COUNTIFS(Syn_Lines!$C$2:$C$4838,$A18,Syn_Lines!$U$2:$U$4838,1,Syn_Lines!$AB$2:$AB$4838,">0") | H18: =IF(B18>0,AVERAGEIFS(Syn_Lines!$AB$2:$AB$4838,Syn_Lines!$C$2:$C$4838,$A18,Syn_Lines!$U$2:$U$4838,1),"") | I18: =COUNTIFS(Syn_Lines!$C$2:$C$4838,$A18,Syn_Lines!$Y$2:$Y$4838,1) | J18: =IF(I18>0,AVERAGEIFS(Syn_Lines!$AC$2:$AC$4838,Syn_Lines!$C$2:$C$4838,$A18,Syn_Lines!$Y$2:$Y$4838,1),"") | K18: =IF(I18>1,SQRT(MAX(0,(SUMIFS(Syn_Lines!$AD$2:$AD$4838,Syn_Lines!$C$2:$C$4838,$A18,Syn_Lines!$Y$2:$Y$4838,1)-I18*J18^2)/(I18-1))),"") | L18: =SUMIFS(Syn_Lines!$M$2:$M$4838,Syn_Lines!$C$2:$C$4838,$A18,Syn_Lines!$K$2:$K$4838,0) | M18: =SUMIFS(Syn_Lines!$O$2:$O$4838,Syn_Lines!$C$2:$C$4838,$A18,Syn_Lines!$K$2:$K$4838,0) | N18: =IF(L18>0,M18/L18,"") | O18: =SUMIFS(Syn_Lines!$S$2:$S$4838,Syn_Lines!$C$2:$C$4838,$A18,Syn_Lines!$K$2:$K$4838,0) | P18: =SUMIFS(Syn_Lines!$T$2:$T$4838,Syn_Lines!$C$2:$C$4838,$A18,Syn_Lines!$K$2:$K$4838,0) | Q18: =IF(P18>0,O18/P18-1,"") | R18: =O18/SUM($O$5:$O$18) | S18: =COUNTIFS(Syn_Lines!$C$2:$C$4838,$A18,Syn_Lines!$Z$2:$Z$4838,1) | T18: =COUNTIFS(Syn_Lines!$C$2:$C$4838,$A18,Syn_Lines!$AA$2:$AA$4838,1) | U18: =SUMIFS(Syn_Lines!$AE$2:$AE$4838,Syn_Lines!$C$2:$C$4838,$A18,Syn_Lines!$AA$2:$AA$4838,1) | V18: =COUNTIFS(Syn_Lines!$C$2:$C$4838,$A18,Syn_Lines!$U$2:$U$4838,1,Syn_Lines!$AF$2:$AF$4838,"prior_12m") | W18: =IF(V18>0,COUNTIFS(Syn_Lines!$C$2:$C$4838,$A18,Syn_Lines!$X$2:$X$4838,1,Syn_Lines!$AF$2:$AF$4838,"prior_12m")/V18,"") | X18: =COUNTIFS(Syn_Lines!$C$2:$C$4838,$A18,Syn_Lines!$U$2:$U$4838,1,Syn_Lines!$AF$2:$AF$4838,"last_12m") | Y18: =IF(X18>0,COUNTIFS(Syn_Lines!$C$2:$C$4838,$A18,Syn_Lines!$X$2:$X$4838,1,Syn_Lines!$AF$2:$AF$4838,"last_12m")/X18,"") | Z18: =IF(OR(W18="",Y18=""),"",Y18-W18) | AA18: =COUNTIFS(Syn_Lines!$C$2:$C$4838,$A18,Syn_Lines!$L$2:$L$4838,1)
A19: All suppliers | B19: =SUM(B5:B18) | C19: =SUM(C5:C18) | D19: =C19/B19 | G19: =SUM(G5:G18) | I19: =SUM(I5:I18) | L19: =SUM(L5:L18) | M19: =SUM(M5:M18) | N19: =M19/L19 | O19: =SUM(O5:O18) | P19: =SUM(P5:P18) | S19: =SUM(S5:S18) | T19: =SUM(T5:T18) | U19: =SUM(U5:U18) | AA19: =SUM(AA5:AA18)

Sheet Dependency
A1: Supplier dependency by category (spend share)
A2: SYNTHETIC DEMONSTRATION DATA - not real suppliers or real performance
A4: Supplier ID | B4: Spend: ELEC | C4: Spend: FLEET | D4: Spend: MRO | E4: Spend: PPE | F4: Spend: CHEM | G4: Spend: IT | I4: Share: ELEC | J4: Share: FLEET | K4: Share: MRO | L4: Share: PPE | M4: Share: CHEM | N4: Share: IT | O4: Max category share | P4: Main category | Q4: Suppliers in main category | R4: Share of total spend | S4: Dependency risk
A5: SUP-01 | B5: =SUMIFS(Syn_Lines!$S$2:$S$4838,Syn_Lines!$C$2:$C$4838,$A5,Syn_Lines!$D$2:$D$4838,"ELEC",Syn_Lines!$K$2:$K$4838,0) | C5: =SUMIFS(Syn_Lines!$S$2:$S$4838,Syn_Lines!$C$2:$C$4838,$A5,Syn_Lines!$D$2:$D$4838,"FLEET",Syn_Lines!$K$2:$K$4838,0) | D5: =SUMIFS(Syn_Lines!$S$2:$S$4838,Syn_Lines!$C$2:$C$4838,$A5,Syn_Lines!$D$2:$D$4838,"MRO",Syn_Lines!$K$2:$K$4838,0) | E5: =SUMIFS(Syn_Lines!$S$2:$S$4838,Syn_Lines!$C$2:$C$4838,$A5,Syn_Lines!$D$2:$D$4838,"PPE",Syn_Lines!$K$2:$K$4838,0) | F5: =SUMIFS(Syn_Lines!$S$2:$S$4838,Syn_Lines!$C$2:$C$4838,$A5,Syn_Lines!$D$2:$D$4838,"CHEM",Syn_Lines!$K$2:$K$4838,0) | G5: =SUMIFS(Syn_Lines!$S$2:$S$4838,Syn_Lines!$C$2:$C$4838,$A5,Syn_Lines!$D$2:$D$4838,"IT",Syn_Lines!$K$2:$K$4838,0) | I5: =IF(B$19>0,B5/B$19,0) | J5: =IF(C$19>0,C5/C$19,0) | K5: =IF(D$19>0,D5/D$19,0) | L5: =IF(E$19>0,E5/E$19,0) | M5: =IF(F$19>0,F5/F$19,0) | N5: =IF(G$19>0,G5/G$19,0) | O5: =MAX(I5:N5) | P5: =MID(INDEX($I$4:$N$4,MATCH(O5,I5:N5,0)),8,10) | Q5: =INDEX($B$20:$G$20,MATCH(O5,I5:N5,0)) | R5: =Supplier_Summary!R5 | S5: =IF(OR(Q5=1,O5>=Assumptions!$C$38,R5>=Assumptions!$C$39),"High",IF(OR(O5>=Assumptions!$C$40,R5>=Assumptions!$C$41),"Medium","Low"))
A6: SUP-02 | B6: =SUMIFS(Syn_Lines!$S$2:$S$4838,Syn_Lines!$C$2:$C$4838,$A6,Syn_Lines!$D$2:$D$4838,"ELEC",Syn_Lines!$K$2:$K$4838,0) | C6: =SUMIFS(Syn_Lines!$S$2:$S$4838,Syn_Lines!$C$2:$C$4838,$A6,Syn_Lines!$D$2:$D$4838,"FLEET",Syn_Lines!$K$2:$K$4838,0) | D6: =SUMIFS(Syn_Lines!$S$2:$S$4838,Syn_Lines!$C$2:$C$4838,$A6,Syn_Lines!$D$2:$D$4838,"MRO",Syn_Lines!$K$2:$K$4838,0) | E6: =SUMIFS(Syn_Lines!$S$2:$S$4838,Syn_Lines!$C$2:$C$4838,$A6,Syn_Lines!$D$2:$D$4838,"PPE",Syn_Lines!$K$2:$K$4838,0) | F6: =SUMIFS(Syn_Lines!$S$2:$S$4838,Syn_Lines!$C$2:$C$4838,$A6,Syn_Lines!$D$2:$D$4838,"CHEM",Syn_Lines!$K$2:$K$4838,0) | G6: =SUMIFS(Syn_Lines!$S$2:$S$4838,Syn_Lines!$C$2:$C$4838,$A6,Syn_Lines!$D$2:$D$4838,"IT",Syn_Lines!$K$2:$K$4838,0) | I6: =IF(B$19>0,B6/B$19,0) | J6: =IF(C$19>0,C6/C$19,0) | K6: =IF(D$19>0,D6/D$19,0) | L6: =IF(E$19>0,E6/E$19,0) | M6: =IF(F$19>0,F6/F$19,0) | N6: =IF(G$19>0,G6/G$19,0) | O6: =MAX(I6:N6) | P6: =MID(INDEX($I$4:$N$4,MATCH(O6,I6:N6,0)),8,10) | Q6: =INDEX($B$20:$G$20,MATCH(O6,I6:N6,0)) | R6: =Supplier_Summary!R6 | S6: =IF(OR(Q6=1,O6>=Assumptions!$C$38,R6>=Assumptions!$C$39),"High",IF(OR(O6>=Assumptions!$C$40,R6>=Assumptions!$C$41),"Medium","Low"))
A7: SUP-03 | B7: =SUMIFS(Syn_Lines!$S$2:$S$4838,Syn_Lines!$C$2:$C$4838,$A7,Syn_Lines!$D$2:$D$4838,"ELEC",Syn_Lines!$K$2:$K$4838,0) | C7: =SUMIFS(Syn_Lines!$S$2:$S$4838,Syn_Lines!$C$2:$C$4838,$A7,Syn_Lines!$D$2:$D$4838,"FLEET",Syn_Lines!$K$2:$K$4838,0) | D7: =SUMIFS(Syn_Lines!$S$2:$S$4838,Syn_Lines!$C$2:$C$4838,$A7,Syn_Lines!$D$2:$D$4838,"MRO",Syn_Lines!$K$2:$K$4838,0) | E7: =SUMIFS(Syn_Lines!$S$2:$S$4838,Syn_Lines!$C$2:$C$4838,$A7,Syn_Lines!$D$2:$D$4838,"PPE",Syn_Lines!$K$2:$K$4838,0) | F7: =SUMIFS(Syn_Lines!$S$2:$S$4838,Syn_Lines!$C$2:$C$4838,$A7,Syn_Lines!$D$2:$D$4838,"CHEM",Syn_Lines!$K$2:$K$4838,0) | G7: =SUMIFS(Syn_Lines!$S$2:$S$4838,Syn_Lines!$C$2:$C$4838,$A7,Syn_Lines!$D$2:$D$4838,"IT",Syn_Lines!$K$2:$K$4838,0) | I7: =IF(B$19>0,B7/B$19,0) | J7: =IF(C$19>0,C7/C$19,0) | K7: =IF(D$19>0,D7/D$19,0) | L7: =IF(E$19>0,E7/E$19,0) | M7: =IF(F$19>0,F7/F$19,0) | N7: =IF(G$19>0,G7/G$19,0) | O7: =MAX(I7:N7) | P7: =MID(INDEX($I$4:$N$4,MATCH(O7,I7:N7,0)),8,10) | Q7: =INDEX($B$20:$G$20,MATCH(O7,I7:N7,0)) | R7: =Supplier_Summary!R7 | S7: =IF(OR(Q7=1,O7>=Assumptions!$C$38,R7>=Assumptions!$C$39),"High",IF(OR(O7>=Assumptions!$C$40,R7>=Assumptions!$C$41),"Medium","Low"))
A8: SUP-04 | B8: =SUMIFS(Syn_Lines!$S$2:$S$4838,Syn_Lines!$C$2:$C$4838,$A8,Syn_Lines!$D$2:$D$4838,"ELEC",Syn_Lines!$K$2:$K$4838,0) | C8: =SUMIFS(Syn_Lines!$S$2:$S$4838,Syn_Lines!$C$2:$C$4838,$A8,Syn_Lines!$D$2:$D$4838,"FLEET",Syn_Lines!$K$2:$K$4838,0) | D8: =SUMIFS(Syn_Lines!$S$2:$S$4838,Syn_Lines!$C$2:$C$4838,$A8,Syn_Lines!$D$2:$D$4838,"MRO",Syn_Lines!$K$2:$K$4838,0) | E8: =SUMIFS(Syn_Lines!$S$2:$S$4838,Syn_Lines!$C$2:$C$4838,$A8,Syn_Lines!$D$2:$D$4838,"PPE",Syn_Lines!$K$2:$K$4838,0) | F8: =SUMIFS(Syn_Lines!$S$2:$S$4838,Syn_Lines!$C$2:$C$4838,$A8,Syn_Lines!$D$2:$D$4838,"CHEM",Syn_Lines!$K$2:$K$4838,0) | G8: =SUMIFS(Syn_Lines!$S$2:$S$4838,Syn_Lines!$C$2:$C$4838,$A8,Syn_Lines!$D$2:$D$4838,"IT",Syn_Lines!$K$2:$K$4838,0) | I8: =IF(B$19>0,B8/B$19,0) | J8: =IF(C$19>0,C8/C$19,0) | K8: =IF(D$19>0,D8/D$19,0) | L8: =IF(E$19>0,E8/E$19,0) | M8: =IF(F$19>0,F8/F$19,0) | N8: =IF(G$19>0,G8/G$19,0) | O8: =MAX(I8:N8) | P8: =MID(INDEX($I$4:$N$4,MATCH(O8,I8:N8,0)),8,10) | Q8: =INDEX($B$20:$G$20,MATCH(O8,I8:N8,0)) | R8: =Supplier_Summary!R8 | S8: =IF(OR(Q8=1,O8>=Assumptions!$C$38,R8>=Assumptions!$C$39),"High",IF(OR(O8>=Assumptions!$C$40,R8>=Assumptions!$C$41),"Medium","Low"))
A9: SUP-05 | B9: =SUMIFS(Syn_Lines!$S$2:$S$4838,Syn_Lines!$C$2:$C$4838,$A9,Syn_Lines!$D$2:$D$4838,"ELEC",Syn_Lines!$K$2:$K$4838,0) | C9: =SUMIFS(Syn_Lines!$S$2:$S$4838,Syn_Lines!$C$2:$C$4838,$A9,Syn_Lines!$D$2:$D$4838,"FLEET",Syn_Lines!$K$2:$K$4838,0) | D9: =SUMIFS(Syn_Lines!$S$2:$S$4838,Syn_Lines!$C$2:$C$4838,$A9,Syn_Lines!$D$2:$D$4838,"MRO",Syn_Lines!$K$2:$K$4838,0) | E9: =SUMIFS(Syn_Lines!$S$2:$S$4838,Syn_Lines!$C$2:$C$4838,$A9,Syn_Lines!$D$2:$D$4838,"PPE",Syn_Lines!$K$2:$K$4838,0) | F9: =SUMIFS(Syn_Lines!$S$2:$S$4838,Syn_Lines!$C$2:$C$4838,$A9,Syn_Lines!$D$2:$D$4838,"CHEM",Syn_Lines!$K$2:$K$4838,0) | G9: =SUMIFS(Syn_Lines!$S$2:$S$4838,Syn_Lines!$C$2:$C$4838,$A9,Syn_Lines!$D$2:$D$4838,"IT",Syn_Lines!$K$2:$K$4838,0) | I9: =IF(B$19>0,B9/B$19,0) | J9: =IF(C$19>0,C9/C$19,0) | K9: =IF(D$19>0,D9/D$19,0) | L9: =IF(E$19>0,E9/E$19,0) | M9: =IF(F$19>0,F9/F$19,0) | N9: =IF(G$19>0,G9/G$19,0) | O9: =MAX(I9:N9) | P9: =MID(INDEX($I$4:$N$4,MATCH(O9,I9:N9,0)),8,10) | Q9: =INDEX($B$20:$G$20,MATCH(O9,I9:N9,0)) | R9: =Supplier_Summary!R9 | S9: =IF(OR(Q9=1,O9>=Assumptions!$C$38,R9>=Assumptions!$C$39),"High",IF(OR(O9>=Assumptions!$C$40,R9>=Assumptions!$C$41),"Medium","Low"))
A10: SUP-06 | B10: =SUMIFS(Syn_Lines!$S$2:$S$4838,Syn_Lines!$C$2:$C$4838,$A10,Syn_Lines!$D$2:$D$4838,"ELEC",Syn_Lines!$K$2:$K$4838,0) | C10: =SUMIFS(Syn_Lines!$S$2:$S$4838,Syn_Lines!$C$2:$C$4838,$A10,Syn_Lines!$D$2:$D$4838,"FLEET",Syn_Lines!$K$2:$K$4838,0) | D10: =SUMIFS(Syn_Lines!$S$2:$S$4838,Syn_Lines!$C$2:$C$4838,$A10,Syn_Lines!$D$2:$D$4838,"MRO",Syn_Lines!$K$2:$K$4838,0) | E10: =SUMIFS(Syn_Lines!$S$2:$S$4838,Syn_Lines!$C$2:$C$4838,$A10,Syn_Lines!$D$2:$D$4838,"PPE",Syn_Lines!$K$2:$K$4838,0) | F10: =SUMIFS(Syn_Lines!$S$2:$S$4838,Syn_Lines!$C$2:$C$4838,$A10,Syn_Lines!$D$2:$D$4838,"CHEM",Syn_Lines!$K$2:$K$4838,0) | G10: =SUMIFS(Syn_Lines!$S$2:$S$4838,Syn_Lines!$C$2:$C$4838,$A10,Syn_Lines!$D$2:$D$4838,"IT",Syn_Lines!$K$2:$K$4838,0) | I10: =IF(B$19>0,B10/B$19,0) | J10: =IF(C$19>0,C10/C$19,0) | K10: =IF(D$19>0,D10/D$19,0) | L10: =IF(E$19>0,E10/E$19,0) | M10: =IF(F$19>0,F10/F$19,0) | N10: =IF(G$19>0,G10/G$19,0) | O10: =MAX(I10:N10) | P10: =MID(INDEX($I$4:$N$4,MATCH(O10,I10:N10,0)),8,10) | Q10: =INDEX($B$20:$G$20,MATCH(O10,I10:N10,0)) | R10: =Supplier_Summary!R10 | S10: =IF(OR(Q10=1,O10>=Assumptions!$C$38,R10>=Assumptions!$C$39),"High",IF(OR(O10>=Assumptions!$C$40,R10>=Assumptions!$C$41),"Medium","Low"))
A11: SUP-07 | B11: =SUMIFS(Syn_Lines!$S$2:$S$4838,Syn_Lines!$C$2:$C$4838,$A11,Syn_Lines!$D$2:$D$4838,"ELEC",Syn_Lines!$K$2:$K$4838,0) | C11: =SUMIFS(Syn_Lines!$S$2:$S$4838,Syn_Lines!$C$2:$C$4838,$A11,Syn_Lines!$D$2:$D$4838,"FLEET",Syn_Lines!$K$2:$K$4838,0) | D11: =SUMIFS(Syn_Lines!$S$2:$S$4838,Syn_Lines!$C$2:$C$4838,$A11,Syn_Lines!$D$2:$D$4838,"MRO",Syn_Lines!$K$2:$K$4838,0) | E11: =SUMIFS(Syn_Lines!$S$2:$S$4838,Syn_Lines!$C$2:$C$4838,$A11,Syn_Lines!$D$2:$D$4838,"PPE",Syn_Lines!$K$2:$K$4838,0) | F11: =SUMIFS(Syn_Lines!$S$2:$S$4838,Syn_Lines!$C$2:$C$4838,$A11,Syn_Lines!$D$2:$D$4838,"CHEM",Syn_Lines!$K$2:$K$4838,0) | G11: =SUMIFS(Syn_Lines!$S$2:$S$4838,Syn_Lines!$C$2:$C$4838,$A11,Syn_Lines!$D$2:$D$4838,"IT",Syn_Lines!$K$2:$K$4838,0) | I11: =IF(B$19>0,B11/B$19,0) | J11: =IF(C$19>0,C11/C$19,0) | K11: =IF(D$19>0,D11/D$19,0) | L11: =IF(E$19>0,E11/E$19,0) | M11: =IF(F$19>0,F11/F$19,0) | N11: =IF(G$19>0,G11/G$19,0) | O11: =MAX(I11:N11) | P11: =MID(INDEX($I$4:$N$4,MATCH(O11,I11:N11,0)),8,10) | Q11: =INDEX($B$20:$G$20,MATCH(O11,I11:N11,0)) | R11: =Supplier_Summary!R11 | S11: =IF(OR(Q11=1,O11>=Assumptions!$C$38,R11>=Assumptions!$C$39),"High",IF(OR(O11>=Assumptions!$C$40,R11>=Assumptions!$C$41),"Medium","Low"))
A12: SUP-08 | B12: =SUMIFS(Syn_Lines!$S$2:$S$4838,Syn_Lines!$C$2:$C$4838,$A12,Syn_Lines!$D$2:$D$4838,"ELEC",Syn_Lines!$K$2:$K$4838,0) | C12: =SUMIFS(Syn_Lines!$S$2:$S$4838,Syn_Lines!$C$2:$C$4838,$A12,Syn_Lines!$D$2:$D$4838,"FLEET",Syn_Lines!$K$2:$K$4838,0) | D12: =SUMIFS(Syn_Lines!$S$2:$S$4838,Syn_Lines!$C$2:$C$4838,$A12,Syn_Lines!$D$2:$D$4838,"MRO",Syn_Lines!$K$2:$K$4838,0) | E12: =SUMIFS(Syn_Lines!$S$2:$S$4838,Syn_Lines!$C$2:$C$4838,$A12,Syn_Lines!$D$2:$D$4838,"PPE",Syn_Lines!$K$2:$K$4838,0) | F12: =SUMIFS(Syn_Lines!$S$2:$S$4838,Syn_Lines!$C$2:$C$4838,$A12,Syn_Lines!$D$2:$D$4838,"CHEM",Syn_Lines!$K$2:$K$4838,0) | G12: =SUMIFS(Syn_Lines!$S$2:$S$4838,Syn_Lines!$C$2:$C$4838,$A12,Syn_Lines!$D$2:$D$4838,"IT",Syn_Lines!$K$2:$K$4838,0) | I12: =IF(B$19>0,B12/B$19,0) | J12: =IF(C$19>0,C12/C$19,0) | K12: =IF(D$19>0,D12/D$19,0) | L12: =IF(E$19>0,E12/E$19,0) | M12: =IF(F$19>0,F12/F$19,0) | N12: =IF(G$19>0,G12/G$19,0) | O12: =MAX(I12:N12) | P12: =MID(INDEX($I$4:$N$4,MATCH(O12,I12:N12,0)),8,10) | Q12: =INDEX($B$20:$G$20,MATCH(O12,I12:N12,0)) | R12: =Supplier_Summary!R12 | S12: =IF(OR(Q12=1,O12>=Assumptions!$C$38,R12>=Assumptions!$C$39),"High",IF(OR(O12>=Assumptions!$C$40,R12>=Assumptions!$C$41),"Medium","Low"))
A13: SUP-09 | B13: =SUMIFS(Syn_Lines!$S$2:$S$4838,Syn_Lines!$C$2:$C$4838,$A13,Syn_Lines!$D$2:$D$4838,"ELEC",Syn_Lines!$K$2:$K$4838,0) | C13: =SUMIFS(Syn_Lines!$S$2:$S$4838,Syn_Lines!$C$2:$C$4838,$A13,Syn_Lines!$D$2:$D$4838,"FLEET",Syn_Lines!$K$2:$K$4838,0) | D13: =SUMIFS(Syn_Lines!$S$2:$S$4838,Syn_Lines!$C$2:$C$4838,$A13,Syn_Lines!$D$2:$D$4838,"MRO",Syn_Lines!$K$2:$K$4838,0) | E13: =SUMIFS(Syn_Lines!$S$2:$S$4838,Syn_Lines!$C$2:$C$4838,$A13,Syn_Lines!$D$2:$D$4838,"PPE",Syn_Lines!$K$2:$K$4838,0) | F13: =SUMIFS(Syn_Lines!$S$2:$S$4838,Syn_Lines!$C$2:$C$4838,$A13,Syn_Lines!$D$2:$D$4838,"CHEM",Syn_Lines!$K$2:$K$4838,0) | G13: =SUMIFS(Syn_Lines!$S$2:$S$4838,Syn_Lines!$C$2:$C$4838,$A13,Syn_Lines!$D$2:$D$4838,"IT",Syn_Lines!$K$2:$K$4838,0) | I13: =IF(B$19>0,B13/B$19,0) | J13: =IF(C$19>0,C13/C$19,0) | K13: =IF(D$19>0,D13/D$19,0) | L13: =IF(E$19>0,E13/E$19,0) | M13: =IF(F$19>0,F13/F$19,0) | N13: =IF(G$19>0,G13/G$19,0) | O13: =MAX(I13:N13) | P13: =MID(INDEX($I$4:$N$4,MATCH(O13,I13:N13,0)),8,10) | Q13: =INDEX($B$20:$G$20,MATCH(O13,I13:N13,0)) | R13: =Supplier_Summary!R13 | S13: =IF(OR(Q13=1,O13>=Assumptions!$C$38,R13>=Assumptions!$C$39),"High",IF(OR(O13>=Assumptions!$C$40,R13>=Assumptions!$C$41),"Medium","Low"))
A14: SUP-10 | B14: =SUMIFS(Syn_Lines!$S$2:$S$4838,Syn_Lines!$C$2:$C$4838,$A14,Syn_Lines!$D$2:$D$4838,"ELEC",Syn_Lines!$K$2:$K$4838,0) | C14: =SUMIFS(Syn_Lines!$S$2:$S$4838,Syn_Lines!$C$2:$C$4838,$A14,Syn_Lines!$D$2:$D$4838,"FLEET",Syn_Lines!$K$2:$K$4838,0) | D14: =SUMIFS(Syn_Lines!$S$2:$S$4838,Syn_Lines!$C$2:$C$4838,$A14,Syn_Lines!$D$2:$D$4838,"MRO",Syn_Lines!$K$2:$K$4838,0) | E14: =SUMIFS(Syn_Lines!$S$2:$S$4838,Syn_Lines!$C$2:$C$4838,$A14,Syn_Lines!$D$2:$D$4838,"PPE",Syn_Lines!$K$2:$K$4838,0) | F14: =SUMIFS(Syn_Lines!$S$2:$S$4838,Syn_Lines!$C$2:$C$4838,$A14,Syn_Lines!$D$2:$D$4838,"CHEM",Syn_Lines!$K$2:$K$4838,0) | G14: =SUMIFS(Syn_Lines!$S$2:$S$4838,Syn_Lines!$C$2:$C$4838,$A14,Syn_Lines!$D$2:$D$4838,"IT",Syn_Lines!$K$2:$K$4838,0) | I14: =IF(B$19>0,B14/B$19,0) | J14: =IF(C$19>0,C14/C$19,0) | K14: =IF(D$19>0,D14/D$19,0) | L14: =IF(E$19>0,E14/E$19,0) | M14: =IF(F$19>0,F14/F$19,0) | N14: =IF(G$19>0,G14/G$19,0) | O14: =MAX(I14:N14) | P14: =MID(INDEX($I$4:$N$4,MATCH(O14,I14:N14,0)),8,10) | Q14: =INDEX($B$20:$G$20,MATCH(O14,I14:N14,0)) | R14: =Supplier_Summary!R14 | S14: =IF(OR(Q14=1,O14>=Assumptions!$C$38,R14>=Assumptions!$C$39),"High",IF(OR(O14>=Assumptions!$C$40,R14>=Assumptions!$C$41),"Medium","Low"))
A15: SUP-11 | B15: =SUMIFS(Syn_Lines!$S$2:$S$4838,Syn_Lines!$C$2:$C$4838,$A15,Syn_Lines!$D$2:$D$4838,"ELEC",Syn_Lines!$K$2:$K$4838,0) | C15: =SUMIFS(Syn_Lines!$S$2:$S$4838,Syn_Lines!$C$2:$C$4838,$A15,Syn_Lines!$D$2:$D$4838,"FLEET",Syn_Lines!$K$2:$K$4838,0) | D15: =SUMIFS(Syn_Lines!$S$2:$S$4838,Syn_Lines!$C$2:$C$4838,$A15,Syn_Lines!$D$2:$D$4838,"MRO",Syn_Lines!$K$2:$K$4838,0) | E15: =SUMIFS(Syn_Lines!$S$2:$S$4838,Syn_Lines!$C$2:$C$4838,$A15,Syn_Lines!$D$2:$D$4838,"PPE",Syn_Lines!$K$2:$K$4838,0) | F15: =SUMIFS(Syn_Lines!$S$2:$S$4838,Syn_Lines!$C$2:$C$4838,$A15,Syn_Lines!$D$2:$D$4838,"CHEM",Syn_Lines!$K$2:$K$4838,0) | G15: =SUMIFS(Syn_Lines!$S$2:$S$4838,Syn_Lines!$C$2:$C$4838,$A15,Syn_Lines!$D$2:$D$4838,"IT",Syn_Lines!$K$2:$K$4838,0) | I15: =IF(B$19>0,B15/B$19,0) | J15: =IF(C$19>0,C15/C$19,0) | K15: =IF(D$19>0,D15/D$19,0) | L15: =IF(E$19>0,E15/E$19,0) | M15: =IF(F$19>0,F15/F$19,0) | N15: =IF(G$19>0,G15/G$19,0) | O15: =MAX(I15:N15) | P15: =MID(INDEX($I$4:$N$4,MATCH(O15,I15:N15,0)),8,10) | Q15: =INDEX($B$20:$G$20,MATCH(O15,I15:N15,0)) | R15: =Supplier_Summary!R15 | S15: =IF(OR(Q15=1,O15>=Assumptions!$C$38,R15>=Assumptions!$C$39),"High",IF(OR(O15>=Assumptions!$C$40,R15>=Assumptions!$C$41),"Medium","Low"))
A16: SUP-12 | B16: =SUMIFS(Syn_Lines!$S$2:$S$4838,Syn_Lines!$C$2:$C$4838,$A16,Syn_Lines!$D$2:$D$4838,"ELEC",Syn_Lines!$K$2:$K$4838,0) | C16: =SUMIFS(Syn_Lines!$S$2:$S$4838,Syn_Lines!$C$2:$C$4838,$A16,Syn_Lines!$D$2:$D$4838,"FLEET",Syn_Lines!$K$2:$K$4838,0) | D16: =SUMIFS(Syn_Lines!$S$2:$S$4838,Syn_Lines!$C$2:$C$4838,$A16,Syn_Lines!$D$2:$D$4838,"MRO",Syn_Lines!$K$2:$K$4838,0) | E16: =SUMIFS(Syn_Lines!$S$2:$S$4838,Syn_Lines!$C$2:$C$4838,$A16,Syn_Lines!$D$2:$D$4838,"PPE",Syn_Lines!$K$2:$K$4838,0) | F16: =SUMIFS(Syn_Lines!$S$2:$S$4838,Syn_Lines!$C$2:$C$4838,$A16,Syn_Lines!$D$2:$D$4838,"CHEM",Syn_Lines!$K$2:$K$4838,0) | G16: =SUMIFS(Syn_Lines!$S$2:$S$4838,Syn_Lines!$C$2:$C$4838,$A16,Syn_Lines!$D$2:$D$4838,"IT",Syn_Lines!$K$2:$K$4838,0) | I16: =IF(B$19>0,B16/B$19,0) | J16: =IF(C$19>0,C16/C$19,0) | K16: =IF(D$19>0,D16/D$19,0) | L16: =IF(E$19>0,E16/E$19,0) | M16: =IF(F$19>0,F16/F$19,0) | N16: =IF(G$19>0,G16/G$19,0) | O16: =MAX(I16:N16) | P16: =MID(INDEX($I$4:$N$4,MATCH(O16,I16:N16,0)),8,10) | Q16: =INDEX($B$20:$G$20,MATCH(O16,I16:N16,0)) | R16: =Supplier_Summary!R16 | S16: =IF(OR(Q16=1,O16>=Assumptions!$C$38,R16>=Assumptions!$C$39),"High",IF(OR(O16>=Assumptions!$C$40,R16>=Assumptions!$C$41),"Medium","Low"))
... A18: SUP-14 | B18: =SUMIFS(Syn_Lines!$S$2:$S$4838,Syn_Lines!$C$2:$C$4838,$A18,Syn_Lines!$D$2:$D$4838,"ELEC",Syn_Lines!$K$2:$K$4838,0) | C18: =SUMIFS(Syn_Lines!$S$2:$S$4838,Syn_Lines!$C$2:$C$4838,$A18,Syn_Lines!$D$2:$D$4838,"FLEET",Syn_Lines!$K$2:$K$4838,0) | D18: =SUMIFS(Syn_Lines!$S$2:$S$4838,Syn_Lines!$C$2:$C$4838,$A18,Syn_Lines!$D$2:$D$4838,"MRO",Syn_Lines!$K$2:$K$4838,0) | E18: =SUMIFS(Syn_Lines!$S$2:$S$4838,Syn_Lines!$C$2:$C$4838,$A18,Syn_Lines!$D$2:$D$4838,"PPE",Syn_Lines!$K$2:$K$4838,0) | F18: =SUMIFS(Syn_Lines!$S$2:$S$4838,Syn_Lines!$C$2:$C$4838,$A18,Syn_Lines!$D$2:$D$4838,"CHEM",Syn_Lines!$K$2:$K$4838,0) | G18: =SUMIFS(Syn_Lines!$S$2:$S$4838,Syn_Lines!$C$2:$C$4838,$A18,Syn_Lines!$D$2:$D$4838,"IT",Syn_Lines!$K$2:$K$4838,0) | I18: =IF(B$19>0,B18/B$19,0) | J18: =IF(C$19>0,C18/C$19,0) | K18: =IF(D$19>0,D18/D$19,0) | L18: =IF(E$19>0,E18/E$19,0) | M18: =IF(F$19>0,F18/F$19,0) | N18: =IF(G$19>0,G18/G$19,0) | O18: =MAX(I18:N18) | P18: =MID(INDEX($I$4:$N$4,MATCH(O18,I18:N18,0)),8,10) | Q18: =INDEX($B$20:$G$20,MATCH(O18,I18:N18,0)) | R18: =Supplier_Summary!R18 | S18: =IF(OR(Q18=1,O18>=Assumptions!$C$38,R18>=Assumptions!$C$39),"High",IF(OR(O18>=Assumptions!$C$40,R18>=Assumptions!$C$41),"Medium","Low"))
A19: Category total | B19: =SUM(B5:B18) | C19: =SUM(C5:C18) | D19: =SUM(D5:D18) | E19: =SUM(E5:E18) | F19: =SUM(F5:F18) | G19: =SUM(G5:G18)
A20: Suppliers with spend | B20: =COUNTIF(B5:B18,">0") | C20: =COUNTIF(C5:C18,">0") | D20: =COUNTIF(D5:D18,">0") | E20: =COUNTIF(E5:E18,">0") | F20: =COUNTIF(F5:F18,">0") | G20: =COUNTIF(G5:G18,">0")

Sheet Scorecard
A1: Supplier performance scorecard
A2: SYNTHETIC DEMONSTRATION DATA - not real suppliers or real performance. Score = weighted 0-100 components; see Assumptions.
A4: Supplier ID | B4: Supplier name (XLOOKUP) | C4: Due lines | D4: Evidence status | E4: OTIF rate | F4: Reject rate | G4: Lead-time SD used | H4: Avg days late | I4: Score: OTIF | J4: Score: quality | K4: Score: lead-time consistency | L4: Score: lateness | M4: Weight used | N4: Performance score | O4: Rank (ranked only) | P4: Performance tier | Q4: Dependency risk | R4: Action quadrant
A5: SUP-01 | B5: =XLOOKUP(A5,Syn_Suppliers!$A$5:$A$18,Syn_Suppliers!$B$5:$B$18,"not found") | C5: =Supplier_Summary!B5 | D5: =IF(C5>=Assumptions!$C$24,"Ranked",IF(C5>=Assumptions!$C$25,"Provisional","Insufficient evidence")) | E5: =Supplier_Summary!D5 | F5: =Supplier_Summary!N5 | G5: =IF(Supplier_Summary!I5>=Assumptions!$C$26,Supplier_Summary!K5,"") | H5: =Supplier_Summary!H5 | I5: =IF(E5="","",MIN(1,MAX(0,(E5-Assumptions!$C$16)/(Assumptions!$C$15-Assumptions!$C$16)))*100) | J5: =IF(F5="","",MIN(1,MAX(0,(Assumptions!$C$18-F5)/(Assumptions!$C$18-Assumptions!$C$17)))*100) | K5: =IF(G5="","",MIN(1,MAX(0,(Assumptions!$C$20-G5)/(Assumptions!$C$20-Assumptions!$C$19)))*100) | L5: =IF(H5="","",MIN(1,MAX(0,(Assumptions!$C$22-H5)/(Assumptions!$C$22-Assumptions!$C$21)))*100) | M5: =IF(I5="",0,Assumptions!$C$10)+IF(J5="",0,Assumptions!$C$11)+IF(K5="",0,Assumptions!$C$12)+IF(L5="",0,Assumptions!$C$13) | N5: =IF(OR(D5="Insufficient evidence",M5=0),"",ROUND((IF(I5="",0,I5*Assumptions!$C$10)+IF(J5="",0,J5*Assumptions!$C$11)+IF(K5="",0,K5*Assumptions!$C$12)+IF(L5="",0,L5*Assumptions!$C$13))/M5,1)) | O5: =IF(D5="Ranked",1+COUNTIFS($D$5:$D$18,"Ranked",$N$5:$N$18,">"&N5),"") | P5: =IF(N5="","Not scored",IF(N5>=Assumptions!$C$27,"Preferred",IF(N5>=Assumptions!$C$28,"Acceptable",IF(N5>=Assumptions!$C$29,"Improvement needed","At risk")))) | Q5: =Dependency!S5 | R5: =IF(D5="Insufficient evidence","Insufficient evidence",IF(Q5="High",IF(N5>=Assumptions!$C$28,"Strategic - protect and monitor","Critical - act now"),IF(N5>=Assumptions!$C$28,"Maintain","Develop or replace")))
A6: SUP-02 | B6: =XLOOKUP(A6,Syn_Suppliers!$A$5:$A$18,Syn_Suppliers!$B$5:$B$18,"not found") | C6: =Supplier_Summary!B6 | D6: =IF(C6>=Assumptions!$C$24,"Ranked",IF(C6>=Assumptions!$C$25,"Provisional","Insufficient evidence")) | E6: =Supplier_Summary!D6 | F6: =Supplier_Summary!N6 | G6: =IF(Supplier_Summary!I6>=Assumptions!$C$26,Supplier_Summary!K6,"") | H6: =Supplier_Summary!H6 | I6: =IF(E6="","",MIN(1,MAX(0,(E6-Assumptions!$C$16)/(Assumptions!$C$15-Assumptions!$C$16)))*100) | J6: =IF(F6="","",MIN(1,MAX(0,(Assumptions!$C$18-F6)/(Assumptions!$C$18-Assumptions!$C$17)))*100) | K6: =IF(G6="","",MIN(1,MAX(0,(Assumptions!$C$20-G6)/(Assumptions!$C$20-Assumptions!$C$19)))*100) | L6: =IF(H6="","",MIN(1,MAX(0,(Assumptions!$C$22-H6)/(Assumptions!$C$22-Assumptions!$C$21)))*100) | M6: =IF(I6="",0,Assumptions!$C$10)+IF(J6="",0,Assumptions!$C$11)+IF(K6="",0,Assumptions!$C$12)+IF(L6="",0,Assumptions!$C$13) | N6: =IF(OR(D6="Insufficient evidence",M6=0),"",ROUND((IF(I6="",0,I6*Assumptions!$C$10)+IF(J6="",0,J6*Assumptions!$C$11)+IF(K6="",0,K6*Assumptions!$C$12)+IF(L6="",0,L6*Assumptions!$C$13))/M6,1)) | O6: =IF(D6="Ranked",1+COUNTIFS($D$5:$D$18,"Ranked",$N$5:$N$18,">"&N6),"") | P6: =IF(N6="","Not scored",IF(N6>=Assumptions!$C$27,"Preferred",IF(N6>=Assumptions!$C$28,"Acceptable",IF(N6>=Assumptions!$C$29,"Improvement needed","At risk")))) | Q6: =Dependency!S6 | R6: =IF(D6="Insufficient evidence","Insufficient evidence",IF(Q6="High",IF(N6>=Assumptions!$C$28,"Strategic - protect and monitor","Critical - act now"),IF(N6>=Assumptions!$C$28,"Maintain","Develop or replace")))
A7: SUP-03 | B7: =XLOOKUP(A7,Syn_Suppliers!$A$5:$A$18,Syn_Suppliers!$B$5:$B$18,"not found") | C7: =Supplier_Summary!B7 | D7: =IF(C7>=Assumptions!$C$24,"Ranked",IF(C7>=Assumptions!$C$25,"Provisional","Insufficient evidence")) | E7: =Supplier_Summary!D7 | F7: =Supplier_Summary!N7 | G7: =IF(Supplier_Summary!I7>=Assumptions!$C$26,Supplier_Summary!K7,"") | H7: =Supplier_Summary!H7 | I7: =IF(E7="","",MIN(1,MAX(0,(E7-Assumptions!$C$16)/(Assumptions!$C$15-Assumptions!$C$16)))*100) | J7: =IF(F7="","",MIN(1,MAX(0,(Assumptions!$C$18-F7)/(Assumptions!$C$18-Assumptions!$C$17)))*100) | K7: =IF(G7="","",MIN(1,MAX(0,(Assumptions!$C$20-G7)/(Assumptions!$C$20-Assumptions!$C$19)))*100) | L7: =IF(H7="","",MIN(1,MAX(0,(Assumptions!$C$22-H7)/(Assumptions!$C$22-Assumptions!$C$21)))*100) | M7: =IF(I7="",0,Assumptions!$C$10)+IF(J7="",0,Assumptions!$C$11)+IF(K7="",0,Assumptions!$C$12)+IF(L7="",0,Assumptions!$C$13) | N7: =IF(OR(D7="Insufficient evidence",M7=0),"",ROUND((IF(I7="",0,I7*Assumptions!$C$10)+IF(J7="",0,J7*Assumptions!$C$11)+IF(K7="",0,K7*Assumptions!$C$12)+IF(L7="",0,L7*Assumptions!$C$13))/M7,1)) | O7: =IF(D7="Ranked",1+COUNTIFS($D$5:$D$18,"Ranked",$N$5:$N$18,">"&N7),"") | P7: =IF(N7="","Not scored",IF(N7>=Assumptions!$C$27,"Preferred",IF(N7>=Assumptions!$C$28,"Acceptable",IF(N7>=Assumptions!$C$29,"Improvement needed","At risk")))) | Q7: =Dependency!S7 | R7: =IF(D7="Insufficient evidence","Insufficient evidence",IF(Q7="High",IF(N7>=Assumptions!$C$28,"Strategic - protect and monitor","Critical - act now"),IF(N7>=Assumptions!$C$28,"Maintain","Develop or replace")))
A8: SUP-04 | B8: =XLOOKUP(A8,Syn_Suppliers!$A$5:$A$18,Syn_Suppliers!$B$5:$B$18,"not found") | C8: =Supplier_Summary!B8 | D8: =IF(C8>=Assumptions!$C$24,"Ranked",IF(C8>=Assumptions!$C$25,"Provisional","Insufficient evidence")) | E8: =Supplier_Summary!D8 | F8: =Supplier_Summary!N8 | G8: =IF(Supplier_Summary!I8>=Assumptions!$C$26,Supplier_Summary!K8,"") | H8: =Supplier_Summary!H8 | I8: =IF(E8="","",MIN(1,MAX(0,(E8-Assumptions!$C$16)/(Assumptions!$C$15-Assumptions!$C$16)))*100) | J8: =IF(F8="","",MIN(1,MAX(0,(Assumptions!$C$18-F8)/(Assumptions!$C$18-Assumptions!$C$17)))*100) | K8: =IF(G8="","",MIN(1,MAX(0,(Assumptions!$C$20-G8)/(Assumptions!$C$20-Assumptions!$C$19)))*100) | L8: =IF(H8="","",MIN(1,MAX(0,(Assumptions!$C$22-H8)/(Assumptions!$C$22-Assumptions!$C$21)))*100) | M8: =IF(I8="",0,Assumptions!$C$10)+IF(J8="",0,Assumptions!$C$11)+IF(K8="",0,Assumptions!$C$12)+IF(L8="",0,Assumptions!$C$13) | N8: =IF(OR(D8="Insufficient evidence",M8=0),"",ROUND((IF(I8="",0,I8*Assumptions!$C$10)+IF(J8="",0,J8*Assumptions!$C$11)+IF(K8="",0,K8*Assumptions!$C$12)+IF(L8="",0,L8*Assumptions!$C$13))/M8,1)) | O8: =IF(D8="Ranked",1+COUNTIFS($D$5:$D$18,"Ranked",$N$5:$N$18,">"&N8),"") | P8: =IF(N8="","Not scored",IF(N8>=Assumptions!$C$27,"Preferred",IF(N8>=Assumptions!$C$28,"Acceptable",IF(N8>=Assumptions!$C$29,"Improvement needed","At risk")))) | Q8: =Dependency!S8 | R8: =IF(D8="Insufficient evidence","Insufficient evidence",IF(Q8="High",IF(N8>=Assumptions!$C$28,"Strategic - protect and monitor","Critical - act now"),IF(N8>=Assumptions!$C$28,"Maintain","Develop or replace")))
A9: SUP-05 | B9: =XLOOKUP(A9,Syn_Suppliers!$A$5:$A$18,Syn_Suppliers!$B$5:$B$18,"not found") | C9: =Supplier_Summary!B9 | D9: =IF(C9>=Assumptions!$C$24,"Ranked",IF(C9>=Assumptions!$C$25,"Provisional","Insufficient evidence")) | E9: =Supplier_Summary!D9 | F9: =Supplier_Summary!N9 | G9: =IF(Supplier_Summary!I9>=Assumptions!$C$26,Supplier_Summary!K9,"") | H9: =Supplier_Summary!H9 | I9: =IF(E9="","",MIN(1,MAX(0,(E9-Assumptions!$C$16)/(Assumptions!$C$15-Assumptions!$C$16)))*100) | J9: =IF(F9="","",MIN(1,MAX(0,(Assumptions!$C$18-F9)/(Assumptions!$C$18-Assumptions!$C$17)))*100) | K9: =IF(G9="","",MIN(1,MAX(0,(Assumptions!$C$20-G9)/(Assumptions!$C$20-Assumptions!$C$19)))*100) | L9: =IF(H9="","",MIN(1,MAX(0,(Assumptions!$C$22-H9)/(Assumptions!$C$22-Assumptions!$C$21)))*100) | M9: =IF(I9="",0,Assumptions!$C$10)+IF(J9="",0,Assumptions!$C$11)+IF(K9="",0,Assumptions!$C$12)+IF(L9="",0,Assumptions!$C$13) | N9: =IF(OR(D9="Insufficient evidence",M9=0),"",ROUND((IF(I9="",0,I9*Assumptions!$C$10)+IF(J9="",0,J9*Assumptions!$C$11)+IF(K9="",0,K9*Assumptions!$C$12)+IF(L9="",0,L9*Assumptions!$C$13))/M9,1)) | O9: =IF(D9="Ranked",1+COUNTIFS($D$5:$D$18,"Ranked",$N$5:$N$18,">"&N9),"") | P9: =IF(N9="","Not scored",IF(N9>=Assumptions!$C$27,"Preferred",IF(N9>=Assumptions!$C$28,"Acceptable",IF(N9>=Assumptions!$C$29,"Improvement needed","At risk")))) | Q9: =Dependency!S9 | R9: =IF(D9="Insufficient evidence","Insufficient evidence",IF(Q9="High",IF(N9>=Assumptions!$C$28,"Strategic - protect and monitor","Critical - act now"),IF(N9>=Assumptions!$C$28,"Maintain","Develop or replace")))
A10: SUP-06 | B10: =XLOOKUP(A10,Syn_Suppliers!$A$5:$A$18,Syn_Suppliers!$B$5:$B$18,"not found") | C10: =Supplier_Summary!B10 | D10: =IF(C10>=Assumptions!$C$24,"Ranked",IF(C10>=Assumptions!$C$25,"Provisional","Insufficient evidence")) | E10: =Supplier_Summary!D10 | F10: =Supplier_Summary!N10 | G10: =IF(Supplier_Summary!I10>=Assumptions!$C$26,Supplier_Summary!K10,"") | H10: =Supplier_Summary!H10 | I10: =IF(E10="","",MIN(1,MAX(0,(E10-Assumptions!$C$16)/(Assumptions!$C$15-Assumptions!$C$16)))*100) | J10: =IF(F10="","",MIN(1,MAX(0,(Assumptions!$C$18-F10)/(Assumptions!$C$18-Assumptions!$C$17)))*100) | K10: =IF(G10="","",MIN(1,MAX(0,(Assumptions!$C$20-G10)/(Assumptions!$C$20-Assumptions!$C$19)))*100) | L10: =IF(H10="","",MIN(1,MAX(0,(Assumptions!$C$22-H10)/(Assumptions!$C$22-Assumptions!$C$21)))*100) | M10: =IF(I10="",0,Assumptions!$C$10)+IF(J10="",0,Assumptions!$C$11)+IF(K10="",0,Assumptions!$C$12)+IF(L10="",0,Assumptions!$C$13) | N10: =IF(OR(D10="Insufficient evidence",M10=0),"",ROUND((IF(I10="",0,I10*Assumptions!$C$10)+IF(J10="",0,J10*Assumptions!$C$11)+IF(K10="",0,K10*Assumptions!$C$12)+IF(L10="",0,L10*Assumptions!$C$13))/M10,1)) | O10: =IF(D10="Ranked",1+COUNTIFS($D$5:$D$18,"Ranked",$N$5:$N$18,">"&N10),"") | P10: =IF(N10="","Not scored",IF(N10>=Assumptions!$C$27,"Preferred",IF(N10>=Assumptions!$C$28,"Acceptable",IF(N10>=Assumptions!$C$29,"Improvement needed","At risk")))) | Q10: =Dependency!S10 | R10: =IF(D10="Insufficient evidence","Insufficient evidence",IF(Q10="High",IF(N10>=Assumptions!$C$28,"Strategic - protect and monitor","Critical - act now"),IF(N10>=Assumptions!$C$28,"Maintain","Develop or replace")))
A11: SUP-07 | B11: =XLOOKUP(A11,Syn_Suppliers!$A$5:$A$18,Syn_Suppliers!$B$5:$B$18,"not found") | C11: =Supplier_Summary!B11 | D11: =IF(C11>=Assumptions!$C$24,"Ranked",IF(C11>=Assumptions!$C$25,"Provisional","Insufficient evidence")) | E11: =Supplier_Summary!D11 | F11: =Supplier_Summary!N11 | G11: =IF(Supplier_Summary!I11>=Assumptions!$C$26,Supplier_Summary!K11,"") | H11: =Supplier_Summary!H11 | I11: =IF(E11="","",MIN(1,MAX(0,(E11-Assumptions!$C$16)/(Assumptions!$C$15-Assumptions!$C$16)))*100) | J11: =IF(F11="","",MIN(1,MAX(0,(Assumptions!$C$18-F11)/(Assumptions!$C$18-Assumptions!$C$17)))*100) | K11: =IF(G11="","",MIN(1,MAX(0,(Assumptions!$C$20-G11)/(Assumptions!$C$20-Assumptions!$C$19)))*100) | L11: =IF(H11="","",MIN(1,MAX(0,(Assumptions!$C$22-H11)/(Assumptions!$C$22-Assumptions!$C$21)))*100) | M11: =IF(I11="",0,Assumptions!$C$10)+IF(J11="",0,Assumptions!$C$11)+IF(K11="",0,Assumptions!$C$12)+IF(L11="",0,Assumptions!$C$13) | N11: =IF(OR(D11="Insufficient evidence",M11=0),"",ROUND((IF(I11="",0,I11*Assumptions!$C$10)+IF(J11="",0,J11*Assumptions!$C$11)+IF(K11="",0,K11*Assumptions!$C$12)+IF(L11="",0,L11*Assumptions!$C$13))/M11,1)) | O11: =IF(D11="Ranked",1+COUNTIFS($D$5:$D$18,"Ranked",$N$5:$N$18,">"&N11),"") | P11: =IF(N11="","Not scored",IF(N11>=Assumptions!$C$27,"Preferred",IF(N11>=Assumptions!$C$28,"Acceptable",IF(N11>=Assumptions!$C$29,"Improvement needed","At risk")))) | Q11: =Dependency!S11 | R11: =IF(D11="Insufficient evidence","Insufficient evidence",IF(Q11="High",IF(N11>=Assumptions!$C$28,"Strategic - protect and monitor","Critical - act now"),IF(N11>=Assumptions!$C$28,"Maintain","Develop or replace")))
A12: SUP-08 | B12: =XLOOKUP(A12,Syn_Suppliers!$A$5:$A$18,Syn_Suppliers!$B$5:$B$18,"not found") | C12: =Supplier_Summary!B12 | D12: =IF(C12>=Assumptions!$C$24,"Ranked",IF(C12>=Assumptions!$C$25,"Provisional","Insufficient evidence")) | E12: =Supplier_Summary!D12 | F12: =Supplier_Summary!N12 | G12: =IF(Supplier_Summary!I12>=Assumptions!$C$26,Supplier_Summary!K12,"") | H12: =Supplier_Summary!H12 | I12: =IF(E12="","",MIN(1,MAX(0,(E12-Assumptions!$C$16)/(Assumptions!$C$15-Assumptions!$C$16)))*100) | J12: =IF(F12="","",MIN(1,MAX(0,(Assumptions!$C$18-F12)/(Assumptions!$C$18-Assumptions!$C$17)))*100) | K12: =IF(G12="","",MIN(1,MAX(0,(Assumptions!$C$20-G12)/(Assumptions!$C$20-Assumptions!$C$19)))*100) | L12: =IF(H12="","",MIN(1,MAX(0,(Assumptions!$C$22-H12)/(Assumptions!$C$22-Assumptions!$C$21)))*100) | M12: =IF(I12="",0,Assumptions!$C$10)+IF(J12="",0,Assumptions!$C$11)+IF(K12="",0,Assumptions!$C$12)+IF(L12="",0,Assumptions!$C$13) | N12: =IF(OR(D12="Insufficient evidence",M12=0),"",ROUND((IF(I12="",0,I12*Assumptions!$C$10)+IF(J12="",0,J12*Assumptions!$C$11)+IF(K12="",0,K12*Assumptions!$C$12)+IF(L12="",0,L12*Assumptions!$C$13))/M12,1)) | O12: =IF(D12="Ranked",1+COUNTIFS($D$5:$D$18,"Ranked",$N$5:$N$18,">"&N12),"") | P12: =IF(N12="","Not scored",IF(N12>=Assumptions!$C$27,"Preferred",IF(N12>=Assumptions!$C$28,"Acceptable",IF(N12>=Assumptions!$C$29,"Improvement needed","At risk")))) | Q12: =Dependency!S12 | R12: =IF(D12="Insufficient evidence","Insufficient evidence",IF(Q12="High",IF(N12>=Assumptions!$C$28,"Strategic - protect and monitor","Critical - act now"),IF(N12>=Assumptions!$C$28,"Maintain","Develop or replace")))
A13: SUP-09 | B13: =XLOOKUP(A13,Syn_Suppliers!$A$5:$A$18,Syn_Suppliers!$B$5:$B$18,"not found") | C13: =Supplier_Summary!B13 | D13: =IF(C13>=Assumptions!$C$24,"Ranked",IF(C13>=Assumptions!$C$25,"Provisional","Insufficient evidence")) | E13: =Supplier_Summary!D13 | F13: =Supplier_Summary!N13 | G13: =IF(Supplier_Summary!I13>=Assumptions!$C$26,Supplier_Summary!K13,"") | H13: =Supplier_Summary!H13 | I13: =IF(E13="","",MIN(1,MAX(0,(E13-Assumptions!$C$16)/(Assumptions!$C$15-Assumptions!$C$16)))*100) | J13: =IF(F13="","",MIN(1,MAX(0,(Assumptions!$C$18-F13)/(Assumptions!$C$18-Assumptions!$C$17)))*100) | K13: =IF(G13="","",MIN(1,MAX(0,(Assumptions!$C$20-G13)/(Assumptions!$C$20-Assumptions!$C$19)))*100) | L13: =IF(H13="","",MIN(1,MAX(0,(Assumptions!$C$22-H13)/(Assumptions!$C$22-Assumptions!$C$21)))*100) | M13: =IF(I13="",0,Assumptions!$C$10)+IF(J13="",0,Assumptions!$C$11)+IF(K13="",0,Assumptions!$C$12)+IF(L13="",0,Assumptions!$C$13) | N13: =IF(OR(D13="Insufficient evidence",M13=0),"",ROUND((IF(I13="",0,I13*Assumptions!$C$10)+IF(J13="",0,J13*Assumptions!$C$11)+IF(K13="",0,K13*Assumptions!$C$12)+IF(L13="",0,L13*Assumptions!$C$13))/M13,1)) | O13: =IF(D13="Ranked",1+COUNTIFS($D$5:$D$18,"Ranked",$N$5:$N$18,">"&N13),"") | P13: =IF(N13="","Not scored",IF(N13>=Assumptions!$C$27,"Preferred",IF(N13>=Assumptions!$C$28,"Acceptable",IF(N13>=Assumptions!$C$29,"Improvement needed","At risk")))) | Q13: =Dependency!S13 | R13: =IF(D13="Insufficient evidence","Insufficient evidence",IF(Q13="High",IF(N13>=Assumptions!$C$28,"Strategic - protect and monitor","Critical - act now"),IF(N13>=Assumptions!$C$28,"Maintain","Develop or replace")))
A14: SUP-10 | B14: =XLOOKUP(A14,Syn_Suppliers!$A$5:$A$18,Syn_Suppliers!$B$5:$B$18,"not found") | C14: =Supplier_Summary!B14 | D14: =IF(C14>=Assumptions!$C$24,"Ranked",IF(C14>=Assumptions!$C$25,"Provisional","Insufficient evidence")) | E14: =Supplier_Summary!D14 | F14: =Supplier_Summary!N14 | G14: =IF(Supplier_Summary!I14>=Assumptions!$C$26,Supplier_Summary!K14,"") | H14: =Supplier_Summary!H14 | I14: =IF(E14="","",MIN(1,MAX(0,(E14-Assumptions!$C$16)/(Assumptions!$C$15-Assumptions!$C$16)))*100) | J14: =IF(F14="","",MIN(1,MAX(0,(Assumptions!$C$18-F14)/(Assumptions!$C$18-Assumptions!$C$17)))*100) | K14: =IF(G14="","",MIN(1,MAX(0,(Assumptions!$C$20-G14)/(Assumptions!$C$20-Assumptions!$C$19)))*100) | L14: =IF(H14="","",MIN(1,MAX(0,(Assumptions!$C$22-H14)/(Assumptions!$C$22-Assumptions!$C$21)))*100) | M14: =IF(I14="",0,Assumptions!$C$10)+IF(J14="",0,Assumptions!$C$11)+IF(K14="",0,Assumptions!$C$12)+IF(L14="",0,Assumptions!$C$13) | N14: =IF(OR(D14="Insufficient evidence",M14=0),"",ROUND((IF(I14="",0,I14*Assumptions!$C$10)+IF(J14="",0,J14*Assumptions!$C$11)+IF(K14="",0,K14*Assumptions!$C$12)+IF(L14="",0,L14*Assumptions!$C$13))/M14,1)) | O14: =IF(D14="Ranked",1+COUNTIFS($D$5:$D$18,"Ranked",$N$5:$N$18,">"&N14),"") | P14: =IF(N14="","Not scored",IF(N14>=Assumptions!$C$27,"Preferred",IF(N14>=Assumptions!$C$28,"Acceptable",IF(N14>=Assumptions!$C$29,"Improvement needed","At risk")))) | Q14: =Dependency!S14 | R14: =IF(D14="Insufficient evidence","Insufficient evidence",IF(Q14="High",IF(N14>=Assumptions!$C$28,"Strategic - protect and monitor","Critical - act now"),IF(N14>=Assumptions!$C$28,"Maintain","Develop or replace")))
A15: SUP-11 | B15: =XLOOKUP(A15,Syn_Suppliers!$A$5:$A$18,Syn_Suppliers!$B$5:$B$18,"not found") | C15: =Supplier_Summary!B15 | D15: =IF(C15>=Assumptions!$C$24,"Ranked",IF(C15>=Assumptions!$C$25,"Provisional","Insufficient evidence")) | E15: =Supplier_Summary!D15 | F15: =Supplier_Summary!N15 | G15: =IF(Supplier_Summary!I15>=Assumptions!$C$26,Supplier_Summary!K15,"") | H15: =Supplier_Summary!H15 | I15: =IF(E15="","",MIN(1,MAX(0,(E15-Assumptions!$C$16)/(Assumptions!$C$15-Assumptions!$C$16)))*100) | J15: =IF(F15="","",MIN(1,MAX(0,(Assumptions!$C$18-F15)/(Assumptions!$C$18-Assumptions!$C$17)))*100) | K15: =IF(G15="","",MIN(1,MAX(0,(Assumptions!$C$20-G15)/(Assumptions!$C$20-Assumptions!$C$19)))*100) | L15: =IF(H15="","",MIN(1,MAX(0,(Assumptions!$C$22-H15)/(Assumptions!$C$22-Assumptions!$C$21)))*100) | M15: =IF(I15="",0,Assumptions!$C$10)+IF(J15="",0,Assumptions!$C$11)+IF(K15="",0,Assumptions!$C$12)+IF(L15="",0,Assumptions!$C$13) | N15: =IF(OR(D15="Insufficient evidence",M15=0),"",ROUND((IF(I15="",0,I15*Assumptions!$C$10)+IF(J15="",0,J15*Assumptions!$C$11)+IF(K15="",0,K15*Assumptions!$C$12)+IF(L15="",0,L15*Assumptions!$C$13))/M15,1)) | O15: =IF(D15="Ranked",1+COUNTIFS($D$5:$D$18,"Ranked",$N$5:$N$18,">"&N15),"") | P15: =IF(N15="","Not scored",IF(N15>=Assumptions!$C$27,"Preferred",IF(N15>=Assumptions!$C$28,"Acceptable",IF(N15>=Assumptions!$C$29,"Improvement needed","At risk")))) | Q15: =Dependency!S15 | R15: =IF(D15="Insufficient evidence","Insufficient evidence",IF(Q15="High",IF(N15>=Assumptions!$C$28,"Strategic - protect and monitor","Critical - act now"),IF(N15>=Assumptions!$C$28,"Maintain","Develop or replace")))
A16: SUP-12 | B16: =XLOOKUP(A16,Syn_Suppliers!$A$5:$A$18,Syn_Suppliers!$B$5:$B$18,"not found") | C16: =Supplier_Summary!B16 | D16: =IF(C16>=Assumptions!$C$24,"Ranked",IF(C16>=Assumptions!$C$25,"Provisional","Insufficient evidence")) | E16: =Supplier_Summary!D16 | F16: =Supplier_Summary!N16 | G16: =IF(Supplier_Summary!I16>=Assumptions!$C$26,Supplier_Summary!K16,"") | H16: =Supplier_Summary!H16 | I16: =IF(E16="","",MIN(1,MAX(0,(E16-Assumptions!$C$16)/(Assumptions!$C$15-Assumptions!$C$16)))*100) | J16: =IF(F16="","",MIN(1,MAX(0,(Assumptions!$C$18-F16)/(Assumptions!$C$18-Assumptions!$C$17)))*100) | K16: =IF(G16="","",MIN(1,MAX(0,(Assumptions!$C$20-G16)/(Assumptions!$C$20-Assumptions!$C$19)))*100) | L16: =IF(H16="","",MIN(1,MAX(0,(Assumptions!$C$22-H16)/(Assumptions!$C$22-Assumptions!$C$21)))*100) | M16: =IF(I16="",0,Assumptions!$C$10)+IF(J16="",0,Assumptions!$C$11)+IF(K16="",0,Assumptions!$C$12)+IF(L16="",0,Assumptions!$C$13) | N16: =IF(OR(D16="Insufficient evidence",M16=0),"",ROUND((IF(I16="",0,I16*Assumptions!$C$10)+IF(J16="",0,J16*Assumptions!$C$11)+IF(K16="",0,K16*Assumptions!$C$12)+IF(L16="",0,L16*Assumptions!$C$13))/M16,1)) | O16: =IF(D16="Ranked",1+COUNTIFS($D$5:$D$18,"Ranked",$N$5:$N$18,">"&N16),"") | P16: =IF(N16="","Not scored",IF(N16>=Assumptions!$C$27,"Preferred",IF(N16>=Assumptions!$C$28,"Acceptable",IF(N16>=Assumptions!$C$29,"Improvement needed","At risk")))) | Q16: =Dependency!S16 | R16: =IF(D16="Insufficient evidence","Insufficient evidence",IF(Q16="High",IF(N16>=Assumptions!$C$28,"Strategic - protect and monitor","Critical - act now"),IF(N16>=Assumptions!$C$28,"Maintain","Develop or replace")))
... A18: SUP-14 | B18: =XLOOKUP(A18,Syn_Suppliers!$A$5:$A$18,Syn_Suppliers!$B$5:$B$18,"not found") | C18: =Supplier_Summary!B18 | D18: =IF(C18>=Assumptions!$C$24,"Ranked",IF(C18>=Assumptions!$C$25,"Provisional","Insufficient evidence")) | E18: =Supplier_Summary!D18 | F18: =Supplier_Summary!N18 | G18: =IF(Supplier_Summary!I18>=Assumptions!$C$26,Supplier_Summary!K18,"") | H18: =Supplier_Summary!H18 | I18: =IF(E18="","",MIN(1,MAX(0,(E18-Assumptions!$C$16)/(Assumptions!$C$15-Assumptions!$C$16)))*100) | J18: =IF(F18="","",MIN(1,MAX(0,(Assumptions!$C$18-F18)/(Assumptions!$C$18-Assumptions!$C$17)))*100) | K18: =IF(G18="","",MIN(1,MAX(0,(Assumptions!$C$20-G18)/(Assumptions!$C$20-Assumptions!$C$19)))*100) | L18: =IF(H18="","",MIN(1,MAX(0,(Assumptions!$C$22-H18)/(Assumptions!$C$22-Assumptions!$C$21)))*100) | M18: =IF(I18="",0,Assumptions!$C$10)+IF(J18="",0,Assumptions!$C$11)+IF(K18="",0,Assumptions!$C$12)+IF(L18="",0,Assumptions!$C$13) | N18: =IF(OR(D18="Insufficient evidence",M18=0),"",ROUND((IF(I18="",0,I18*Assumptions!$C$10)+IF(J18="",0,J18*Assumptions!$C$11)+IF(K18="",0,K18*Assumptions!$C$12)+IF(L18="",0,L18*Assumptions!$C$13))/M18,1)) | O18: =IF(D18="Ranked",1+COUNTIFS($D$5:$D$18,"Ranked",$N$5:$N$18,">"&N18),"") | P18: =IF(N18="","Not scored",IF(N18>=Assumptions!$C$27,"Preferred",IF(N18>=Assumptions!$C$28,"Acceptable",IF(N18>=Assumptions!$C$29,"Improvement needed","At risk")))) | Q18: =Dependency!S18 | R18: =IF(D18="Insufficient evidence","Insufficient evidence",IF(Q18="High",IF(N18>=Assumptions!$C$28,"Strategic - protect and monitor","Critical - act now"),IF(N18>=Assumptions!$C$28,"Maintain","Develop or replace")))
A20: How to read
A21: 1. Each component is scaled linearly from 0 points (poor value) to 100 points (target value) and clipped; thresholds are on Assumptions.
A22: 2. Missing components (e.g. fewer completed lines than needed for lead-time variability) are dropped and the remaining weights re-normalised - never scored as poor.
A23: 3. Suppliers below the ranking threshold are shown as Provisional; below the provisional threshold they are not scored. Equal scores share a rank.
A24: 4. Dependency risk is assessed separately from performance and combined only in the action quadrant.

Sheet Delivery_Trend
A1: Monthly OTIF (all synthetic suppliers)
A2: SYNTHETIC DEMONSTRATION DATA - not real suppliers or real performance. Lines grouped by promised month.
A4: Promised month | B4: Due lines | C4: OTIF lines | D4: OTIF rate | E4: On-time lines | F4: On-time rate
A5: 45566 | B5: =COUNTIFS(Syn_Lines!$AG$2:$AG$4838,A5,Syn_Lines!$U$2:$U$4838,1) | C5: =COUNTIFS(Syn_Lines!$AG$2:$AG$4838,A5,Syn_Lines!$X$2:$X$4838,1) | D5: =IF(B5>0,C5/B5,"") | E5: =COUNTIFS(Syn_Lines!$AG$2:$AG$4838,A5,Syn_Lines!$V$2:$V$4838,1) | F5: =IF(B5>0,E5/B5,"")
A6: 45597 | B6: =COUNTIFS(Syn_Lines!$AG$2:$AG$4838,A6,Syn_Lines!$U$2:$U$4838,1) | C6: =COUNTIFS(Syn_Lines!$AG$2:$AG$4838,A6,Syn_Lines!$X$2:$X$4838,1) | D6: =IF(B6>0,C6/B6,"") | E6: =COUNTIFS(Syn_Lines!$AG$2:$AG$4838,A6,Syn_Lines!$V$2:$V$4838,1) | F6: =IF(B6>0,E6/B6,"")
A7: 45627 | B7: =COUNTIFS(Syn_Lines!$AG$2:$AG$4838,A7,Syn_Lines!$U$2:$U$4838,1) | C7: =COUNTIFS(Syn_Lines!$AG$2:$AG$4838,A7,Syn_Lines!$X$2:$X$4838,1) | D7: =IF(B7>0,C7/B7,"") | E7: =COUNTIFS(Syn_Lines!$AG$2:$AG$4838,A7,Syn_Lines!$V$2:$V$4838,1) | F7: =IF(B7>0,E7/B7,"")
A8: 45658 | B8: =COUNTIFS(Syn_Lines!$AG$2:$AG$4838,A8,Syn_Lines!$U$2:$U$4838,1) | C8: =COUNTIFS(Syn_Lines!$AG$2:$AG$4838,A8,Syn_Lines!$X$2:$X$4838,1) | D8: =IF(B8>0,C8/B8,"") | E8: =COUNTIFS(Syn_Lines!$AG$2:$AG$4838,A8,Syn_Lines!$V$2:$V$4838,1) | F8: =IF(B8>0,E8/B8,"")
A9: 45689 | B9: =COUNTIFS(Syn_Lines!$AG$2:$AG$4838,A9,Syn_Lines!$U$2:$U$4838,1) | C9: =COUNTIFS(Syn_Lines!$AG$2:$AG$4838,A9,Syn_Lines!$X$2:$X$4838,1) | D9: =IF(B9>0,C9/B9,"") | E9: =COUNTIFS(Syn_Lines!$AG$2:$AG$4838,A9,Syn_Lines!$V$2:$V$4838,1) | F9: =IF(B9>0,E9/B9,"")
A10: 45717 | B10: =COUNTIFS(Syn_Lines!$AG$2:$AG$4838,A10,Syn_Lines!$U$2:$U$4838,1) | C10: =COUNTIFS(Syn_Lines!$AG$2:$AG$4838,A10,Syn_Lines!$X$2:$X$4838,1) | D10: =IF(B10>0,C10/B10,"") | E10: =COUNTIFS(Syn_Lines!$AG$2:$AG$4838,A10,Syn_Lines!$V$2:$V$4838,1) | F10: =IF(B10>0,E10/B10,"")
A11: 45748 | B11: =COUNTIFS(Syn_Lines!$AG$2:$AG$4838,A11,Syn_Lines!$U$2:$U$4838,1) | C11: =COUNTIFS(Syn_Lines!$AG$2:$AG$4838,A11,Syn_Lines!$X$2:$X$4838,1) | D11: =IF(B11>0,C11/B11,"") | E11: =COUNTIFS(Syn_Lines!$AG$2:$AG$4838,A11,Syn_Lines!$V$2:$V$4838,1) | F11: =IF(B11>0,E11/B11,"")
A12: 45778 | B12: =COUNTIFS(Syn_Lines!$AG$2:$AG$4838,A12,Syn_Lines!$U$2:$U$4838,1) | C12: =COUNTIFS(Syn_Lines!$AG$2:$AG$4838,A12,Syn_Lines!$X$2:$X$4838,1) | D12: =IF(B12>0,C12/B12,"") | E12: =COUNTIFS(Syn_Lines!$AG$2:$AG$4838,A12,Syn_Lines!$V$2:$V$4838,1) | F12: =IF(B12>0,E12/B12,"")
A13: 45809 | B13: =COUNTIFS(Syn_Lines!$AG$2:$AG$4838,A13,Syn_Lines!$U$2:$U$4838,1) | C13: =COUNTIFS(Syn_Lines!$AG$2:$AG$4838,A13,Syn_Lines!$X$2:$X$4838,1) | D13: =IF(B13>0,C13/B13,"") | E13: =COUNTIFS(Syn_Lines!$AG$2:$AG$4838,A13,Syn_Lines!$V$2:$V$4838,1) | F13: =IF(B13>0,E13/B13,"")
A14: 45839 | B14: =COUNTIFS(Syn_Lines!$AG$2:$AG$4838,A14,Syn_Lines!$U$2:$U$4838,1) | C14: =COUNTIFS(Syn_Lines!$AG$2:$AG$4838,A14,Syn_Lines!$X$2:$X$4838,1) | D14: =IF(B14>0,C14/B14,"") | E14: =COUNTIFS(Syn_Lines!$AG$2:$AG$4838,A14,Syn_Lines!$V$2:$V$4838,1) | F14: =IF(B14>0,E14/B14,"")
A15: 45870 | B15: =COUNTIFS(Syn_Lines!$AG$2:$AG$4838,A15,Syn_Lines!$U$2:$U$4838,1) | C15: =COUNTIFS(Syn_Lines!$AG$2:$AG$4838,A15,Syn_Lines!$X$2:$X$4838,1) | D15: =IF(B15>0,C15/B15,"") | E15: =COUNTIFS(Syn_Lines!$AG$2:$AG$4838,A15,Syn_Lines!$V$2:$V$4838,1) | F15: =IF(B15>0,E15/B15,"")
A16: 45901 | B16: =COUNTIFS(Syn_Lines!$AG$2:$AG$4838,A16,Syn_Lines!$U$2:$U$4838,1) | C16: =COUNTIFS(Syn_Lines!$AG$2:$AG$4838,A16,Syn_Lines!$X$2:$X$4838,1) | D16: =IF(B16>0,C16/B16,"") | E16: =COUNTIFS(Syn_Lines!$AG$2:$AG$4838,A16,Syn_Lines!$V$2:$V$4838,1) | F16: =IF(B16>0,E16/B16,"")
... A28: 46266 | B28: =COUNTIFS(Syn_Lines!$AG$2:$AG$4838,A28,Syn_Lines!$U$2:$U$4838,1) | C28: =COUNTIFS(Syn_Lines!$AG$2:$AG$4838,A28,Syn_Lines!$X$2:$X$4838,1) | D28: =IF(B28>0,C28/B28,"") | E28: =COUNTIFS(Syn_Lines!$AG$2:$AG$4838,A28,Syn_Lines!$V$2:$V$4838,1) | F28: =IF(B28>0,E28/B28,"")

Sheet Exceptions
A1: Supplier exception flags (live) and overdue lines
A2: SYNTHETIC DEMONSTRATION DATA - not real suppliers or real performance. Flags recalculate from Supplier_Summary and Assumptions.
A4: Supplier ID | B4: S1 Chronic late | C4: S2 Deteriorating | D4: S3 Unstable lead time | E4: S4 Incomplete deliveries | F4: S5 Quality | G4: S6 PPV above contract | H4: S8 High dependency | I4: Flags raised
A5: SUP-01 | B5: =IF(AND(Supplier_Summary!B5>=Assumptions!$C$32,Supplier_Summary!D5<Assumptions!$C$31),"FLAG","") | C5: =IF(AND(Supplier_Summary!V5>=Assumptions!$C$32,Supplier_Summary!X5>=Assumptions!$C$32),IF(Supplier_Summary!Z5<=-Assumptions!$C$36,"FLAG",""),"") | D5: =IF(AND(Supplier_Summary!I5>=Assumptions!$C$26,Supplier_Summary!K5>=Assumptions!$C$33),"FLAG","") | E5: =IF(AND(Supplier_Summary!B5>=Assumptions!$C$32,Supplier_Summary!F5<Assumptions!$C$34),"FLAG","") | F5: =IF(AND(Supplier_Summary!B5>=Assumptions!$C$32,Supplier_Summary!N5>=Assumptions!$C$35),"FLAG","") | G5: =IF(Supplier_Summary!Q5>=Assumptions!$C$37,"FLAG","") | H5: =IF(Scorecard!Q5="High","FLAG","") | I5: =COUNTIF(B5:H5,"FLAG")
A6: SUP-02 | B6: =IF(AND(Supplier_Summary!B6>=Assumptions!$C$32,Supplier_Summary!D6<Assumptions!$C$31),"FLAG","") | C6: =IF(AND(Supplier_Summary!V6>=Assumptions!$C$32,Supplier_Summary!X6>=Assumptions!$C$32),IF(Supplier_Summary!Z6<=-Assumptions!$C$36,"FLAG",""),"") | D6: =IF(AND(Supplier_Summary!I6>=Assumptions!$C$26,Supplier_Summary!K6>=Assumptions!$C$33),"FLAG","") | E6: =IF(AND(Supplier_Summary!B6>=Assumptions!$C$32,Supplier_Summary!F6<Assumptions!$C$34),"FLAG","") | F6: =IF(AND(Supplier_Summary!B6>=Assumptions!$C$32,Supplier_Summary!N6>=Assumptions!$C$35),"FLAG","") | G6: =IF(Supplier_Summary!Q6>=Assumptions!$C$37,"FLAG","") | H6: =IF(Scorecard!Q6="High","FLAG","") | I6: =COUNTIF(B6:H6,"FLAG")
A7: SUP-03 | B7: =IF(AND(Supplier_Summary!B7>=Assumptions!$C$32,Supplier_Summary!D7<Assumptions!$C$31),"FLAG","") | C7: =IF(AND(Supplier_Summary!V7>=Assumptions!$C$32,Supplier_Summary!X7>=Assumptions!$C$32),IF(Supplier_Summary!Z7<=-Assumptions!$C$36,"FLAG",""),"") | D7: =IF(AND(Supplier_Summary!I7>=Assumptions!$C$26,Supplier_Summary!K7>=Assumptions!$C$33),"FLAG","") | E7: =IF(AND(Supplier_Summary!B7>=Assumptions!$C$32,Supplier_Summary!F7<Assumptions!$C$34),"FLAG","") | F7: =IF(AND(Supplier_Summary!B7>=Assumptions!$C$32,Supplier_Summary!N7>=Assumptions!$C$35),"FLAG","") | G7: =IF(Supplier_Summary!Q7>=Assumptions!$C$37,"FLAG","") | H7: =IF(Scorecard!Q7="High","FLAG","") | I7: =COUNTIF(B7:H7,"FLAG")
A8: SUP-04 | B8: =IF(AND(Supplier_Summary!B8>=Assumptions!$C$32,Supplier_Summary!D8<Assumptions!$C$31),"FLAG","") | C8: =IF(AND(Supplier_Summary!V8>=Assumptions!$C$32,Supplier_Summary!X8>=Assumptions!$C$32),IF(Supplier_Summary!Z8<=-Assumptions!$C$36,"FLAG",""),"") | D8: =IF(AND(Supplier_Summary!I8>=Assumptions!$C$26,Supplier_Summary!K8>=Assumptions!$C$33),"FLAG","") | E8: =IF(AND(Supplier_Summary!B8>=Assumptions!$C$32,Supplier_Summary!F8<Assumptions!$C$34),"FLAG","") | F8: =IF(AND(Supplier_Summary!B8>=Assumptions!$C$32,Supplier_Summary!N8>=Assumptions!$C$35),"FLAG","") | G8: =IF(Supplier_Summary!Q8>=Assumptions!$C$37,"FLAG","") | H8: =IF(Scorecard!Q8="High","FLAG","") | I8: =COUNTIF(B8:H8,"FLAG")
A9: SUP-05 | B9: =IF(AND(Supplier_Summary!B9>=Assumptions!$C$32,Supplier_Summary!D9<Assumptions!$C$31),"FLAG","") | C9: =IF(AND(Supplier_Summary!V9>=Assumptions!$C$32,Supplier_Summary!X9>=Assumptions!$C$32),IF(Supplier_Summary!Z9<=-Assumptions!$C$36,"FLAG",""),"") | D9: =IF(AND(Supplier_Summary!I9>=Assumptions!$C$26,Supplier_Summary!K9>=Assumptions!$C$33),"FLAG","") | E9: =IF(AND(Supplier_Summary!B9>=Assumptions!$C$32,Supplier_Summary!F9<Assumptions!$C$34),"FLAG","") | F9: =IF(AND(Supplier_Summary!B9>=Assumptions!$C$32,Supplier_Summary!N9>=Assumptions!$C$35),"FLAG","") | G9: =IF(Supplier_Summary!Q9>=Assumptions!$C$37,"FLAG","") | H9: =IF(Scorecard!Q9="High","FLAG","") | I9: =COUNTIF(B9:H9,"FLAG")
A10: SUP-06 | B10: =IF(AND(Supplier_Summary!B10>=Assumptions!$C$32,Supplier_Summary!D10<Assumptions!$C$31),"FLAG","") | C10: =IF(AND(Supplier_Summary!V10>=Assumptions!$C$32,Supplier_Summary!X10>=Assumptions!$C$32),IF(Supplier_Summary!Z10<=-Assumptions!$C$36,"FLAG",""),"") | D10: =IF(AND(Supplier_Summary!I10>=Assumptions!$C$26,Supplier_Summary!K10>=Assumptions!$C$33),"FLAG","") | E10: =IF(AND(Supplier_Summary!B10>=Assumptions!$C$32,Supplier_Summary!F10<Assumptions!$C$34),"FLAG","") | F10: =IF(AND(Supplier_Summary!B10>=Assumptions!$C$32,Supplier_Summary!N10>=Assumptions!$C$35),"FLAG","") | G10: =IF(Supplier_Summary!Q10>=Assumptions!$C$37,"FLAG","") | H10: =IF(Scorecard!Q10="High","FLAG","") | I10: =COUNTIF(B10:H10,"FLAG")
A11: SUP-07 | B11: =IF(AND(Supplier_Summary!B11>=Assumptions!$C$32,Supplier_Summary!D11<Assumptions!$C$31),"FLAG","") | C11: =IF(AND(Supplier_Summary!V11>=Assumptions!$C$32,Supplier_Summary!X11>=Assumptions!$C$32),IF(Supplier_Summary!Z11<=-Assumptions!$C$36,"FLAG",""),"") | D11: =IF(AND(Supplier_Summary!I11>=Assumptions!$C$26,Supplier_Summary!K11>=Assumptions!$C$33),"FLAG","") | E11: =IF(AND(Supplier_Summary!B11>=Assumptions!$C$32,Supplier_Summary!F11<Assumptions!$C$34),"FLAG","") | F11: =IF(AND(Supplier_Summary!B11>=Assumptions!$C$32,Supplier_Summary!N11>=Assumptions!$C$35),"FLAG","") | G11: =IF(Supplier_Summary!Q11>=Assumptions!$C$37,"FLAG","") | H11: =IF(Scorecard!Q11="High","FLAG","") | I11: =COUNTIF(B11:H11,"FLAG")
A12: SUP-08 | B12: =IF(AND(Supplier_Summary!B12>=Assumptions!$C$32,Supplier_Summary!D12<Assumptions!$C$31),"FLAG","") | C12: =IF(AND(Supplier_Summary!V12>=Assumptions!$C$32,Supplier_Summary!X12>=Assumptions!$C$32),IF(Supplier_Summary!Z12<=-Assumptions!$C$36,"FLAG",""),"") | D12: =IF(AND(Supplier_Summary!I12>=Assumptions!$C$26,Supplier_Summary!K12>=Assumptions!$C$33),"FLAG","") | E12: =IF(AND(Supplier_Summary!B12>=Assumptions!$C$32,Supplier_Summary!F12<Assumptions!$C$34),"FLAG","") | F12: =IF(AND(Supplier_Summary!B12>=Assumptions!$C$32,Supplier_Summary!N12>=Assumptions!$C$35),"FLAG","") | G12: =IF(Supplier_Summary!Q12>=Assumptions!$C$37,"FLAG","") | H12: =IF(Scorecard!Q12="High","FLAG","") | I12: =COUNTIF(B12:H12,"FLAG")
A13: SUP-09 | B13: =IF(AND(Supplier_Summary!B13>=Assumptions!$C$32,Supplier_Summary!D13<Assumptions!$C$31),"FLAG","") | C13: =IF(AND(Supplier_Summary!V13>=Assumptions!$C$32,Supplier_Summary!X13>=Assumptions!$C$32),IF(Supplier_Summary!Z13<=-Assumptions!$C$36,"FLAG",""),"") | D13: =IF(AND(Supplier_Summary!I13>=Assumptions!$C$26,Supplier_Summary!K13>=Assumptions!$C$33),"FLAG","") | E13: =IF(AND(Supplier_Summary!B13>=Assumptions!$C$32,Supplier_Summary!F13<Assumptions!$C$34),"FLAG","") | F13: =IF(AND(Supplier_Summary!B13>=Assumptions!$C$32,Supplier_Summary!N13>=Assumptions!$C$35),"FLAG","") | G13: =IF(Supplier_Summary!Q13>=Assumptions!$C$37,"FLAG","") | H13: =IF(Scorecard!Q13="High","FLAG","") | I13: =COUNTIF(B13:H13,"FLAG")
A14: SUP-10 | B14: =IF(AND(Supplier_Summary!B14>=Assumptions!$C$32,Supplier_Summary!D14<Assumptions!$C$31),"FLAG","") | C14: =IF(AND(Supplier_Summary!V14>=Assumptions!$C$32,Supplier_Summary!X14>=Assumptions!$C$32),IF(Supplier_Summary!Z14<=-Assumptions!$C$36,"FLAG",""),"") | D14: =IF(AND(Supplier_Summary!I14>=Assumptions!$C$26,Supplier_Summary!K14>=Assumptions!$C$33),"FLAG","") | E14: =IF(AND(Supplier_Summary!B14>=Assumptions!$C$32,Supplier_Summary!F14<Assumptions!$C$34),"FLAG","") | F14: =IF(AND(Supplier_Summary!B14>=Assumptions!$C$32,Supplier_Summary!N14>=Assumptions!$C$35),"FLAG","") | G14: =IF(Supplier_Summary!Q14>=Assumptions!$C$37,"FLAG","") | H14: =IF(Scorecard!Q14="High","FLAG","") | I14: =COUNTIF(B14:H14,"FLAG")
A15: SUP-11 | B15: =IF(AND(Supplier_Summary!B15>=Assumptions!$C$32,Supplier_Summary!D15<Assumptions!$C$31),"FLAG","") | C15: =IF(AND(Supplier_Summary!V15>=Assumptions!$C$32,Supplier_Summary!X15>=Assumptions!$C$32),IF(Supplier_Summary!Z15<=-Assumptions!$C$36,"FLAG",""),"") | D15: =IF(AND(Supplier_Summary!I15>=Assumptions!$C$26,Supplier_Summary!K15>=Assumptions!$C$33),"FLAG","") | E15: =IF(AND(Supplier_Summary!B15>=Assumptions!$C$32,Supplier_Summary!F15<Assumptions!$C$34),"FLAG","") | F15: =IF(AND(Supplier_Summary!B15>=Assumptions!$C$32,Supplier_Summary!N15>=Assumptions!$C$35),"FLAG","") | G15: =IF(Supplier_Summary!Q15>=Assumptions!$C$37,"FLAG","") | H15: =IF(Scorecard!Q15="High","FLAG","") | I15: =COUNTIF(B15:H15,"FLAG")
A16: SUP-12 | B16: =IF(AND(Supplier_Summary!B16>=Assumptions!$C$32,Supplier_Summary!D16<Assumptions!$C$31),"FLAG","") | C16: =IF(AND(Supplier_Summary!V16>=Assumptions!$C$32,Supplier_Summary!X16>=Assumptions!$C$32),IF(Supplier_Summary!Z16<=-Assumptions!$C$36,"FLAG",""),"") | D16: =IF(AND(Supplier_Summary!I16>=Assumptions!$C$26,Supplier_Summary!K16>=Assumptions!$C$33),"FLAG","") | E16: =IF(AND(Supplier_Summary!B16>=Assumptions!$C$32,Supplier_Summary!F16<Assumptions!$C$34),"FLAG","") | F16: =IF(AND(Supplier_Summary!B16>=Assumptions!$C$32,Supplier_Summary!N16>=Assumptions!$C$35),"FLAG","") | G16: =IF(Supplier_Summary!Q16>=Assumptions!$C$37,"FLAG","") | H16: =IF(Scorecard!Q16="High","FLAG","") | I16: =COUNTIF(B16:H16,"FLAG")
... A18: SUP-14 | B18: =IF(AND(Supplier_Summary!B18>=Assumptions!$C$32,Supplier_Summary!D18<Assumptions!$C$31),"FLAG","") | C18: =IF(AND(Supplier_Summary!V18>=Assumptions!$C$32,Supplier_Summary!X18>=Assumptions!$C$32),IF(Supplier_Summary!Z18<=-Assumptions!$C$36,"FLAG",""),"") | D18: =IF(AND(Supplier_Summary!I18>=Assumptions!$C$26,Supplier_Summary!K18>=Assumptions!$C$33),"FLAG","") | E18: =IF(AND(Supplier_Summary!B18>=Assumptions!$C$32,Supplier_Summary!F18<Assumptions!$C$34),"FLAG","") | F18: =IF(AND(Supplier_Summary!B18>=Assumptions!$C$32,Supplier_Summary!N18>=Assumptions!$C$35),"FLAG","") | G18: =IF(Supplier_Summary!Q18>=Assumptions!$C$37,"FLAG","") | H18: =IF(Scorecard!Q18="High","FLAG","") | I18: =COUNTIF(B18:H18,"FLAG")
A21: S7 Overdue open PO lines (list exported by the pipeline; count check is live)
A22: Live count of overdue lines: | C22: =SUM(Syn_Lines!$AA$2:$AA$4838) | D22: 8 | E22: =IF(C22=D22,"List complete","Re-run pipeline")
A24: PO line | B24: Supplier | C24: Item | D24: Promised | E24: Ordered | F24: Received | G24: Open value | H24: Days past promise
A25: SPO-02109-1 | B25: SUP-01 | C25: ELEC-04 | D25: 46173 | E25: 26 | F25: 0 | G25: 1999.14 | H25: 122
A26: SPO-02231-1 | B26: SUP-04 | C26: FLEET-05 | D26: 46202 | E26: 13 | F26: 0 | G26: 2129.27 | H26: 93
A27: SPO-02355-1 | B27: SUP-01 | C27: ELEC-03 | D27: 46244 | E27: 29 | F27: 0 | G27: 2746.01 | H27: 51
A28: SPO-02388-1 | B28: SUP-01 | C28: ELEC-08 | D28: 46253 | E28: 38 | F28: 0 | G28: 671.84 | H28: 42
A29: SPO-02451-1 | B29: SUP-01 | C29: ELEC-08 | D29: 46272 | E29: 162 | F29: 0 | G29: 2825.28 | H29: 23
A30: SPO-02474-1 | B30: SUP-01 | C30: ELEC-06 | D30: 46276 | E30: 7 | F30: 0 | G30: 1012.83 | H30: 19
A31: SPO-02496-1 | B31: SUP-01 | C31: ELEC-04 | D31: 46281 | E31: 17 | F31: 0 | G31: 1250.18 | H31: 14
A32: SPO-02524-1 | B32: SUP-14 | C32: FLEET-03 | D32: 46289 | E32: 66 | F32: 45 | G32: 434.49 | H32: 6

Sheet Scenario
A1: What-if scenarios (modelled, not realised savings)
A2: SYNTHETIC DEMONSTRATION DATA - not real suppliers or real performance for A and B; C uses observed City of Austin prices.
A4: A. Reallocate volume between suppliers (last 12 months of due lines)
A5: Category | B5: ELEC
A6: Move volume from supplier | B6: SUP-01
A7: Move volume to supplier | B7: SUP-02
A8: Share of volume moved | B8: 0.3
A9: Cost per late line (Assumptions) | B9: =Assumptions!$C$43
A11: Last 12 months | B11: From supplier | C11: To supplier
A12: Due lines | B12: =COUNTIFS(Syn_Lines!$C$2:$C$4838,$B$6,Syn_Lines!$D$2:$D$4838,$B$5,Syn_Lines!$AF$2:$AF$4838,"last_12m",Syn_Lines!$U$2:$U$4838,1) | C12: =COUNTIFS(Syn_Lines!$C$2:$C$4838,$B$7,Syn_Lines!$D$2:$D$4838,$B$5,Syn_Lines!$AF$2:$AF$4838,"last_12m",Syn_Lines!$U$2:$U$4838,1)
A13: OTIF lines | B13: =COUNTIFS(Syn_Lines!$C$2:$C$4838,$B$6,Syn_Lines!$D$2:$D$4838,$B$5,Syn_Lines!$AF$2:$AF$4838,"last_12m",Syn_Lines!$U$2:$U$4838,1,Syn_Lines!$X$2:$X$4838,1) | C13: =COUNTIFS(Syn_Lines!$C$2:$C$4838,$B$7,Syn_Lines!$D$2:$D$4838,$B$5,Syn_Lines!$AF$2:$AF$4838,"last_12m",Syn_Lines!$U$2:$U$4838,1,Syn_Lines!$X$2:$X$4838,1)
A14: Spend | B14: =SUMIFS(Syn_Lines!$S$2:$S$4838,Syn_Lines!$C$2:$C$4838,$B$6,Syn_Lines!$D$2:$D$4838,$B$5,Syn_Lines!$AF$2:$AF$4838,"last_12m",Syn_Lines!$K$2:$K$4838,0) | C14: =SUMIFS(Syn_Lines!$S$2:$S$4838,Syn_Lines!$C$2:$C$4838,$B$7,Syn_Lines!$D$2:$D$4838,$B$5,Syn_Lines!$AF$2:$AF$4838,"last_12m",Syn_Lines!$K$2:$K$4838,0)
A15: Value at contract price | B15: =SUMIFS(Syn_Lines!$T$2:$T$4838,Syn_Lines!$C$2:$C$4838,$B$6,Syn_Lines!$D$2:$D$4838,$B$5,Syn_Lines!$AF$2:$AF$4838,"last_12m",Syn_Lines!$K$2:$K$4838,0) | C15: =SUMIFS(Syn_Lines!$T$2:$T$4838,Syn_Lines!$C$2:$C$4838,$B$7,Syn_Lines!$D$2:$D$4838,$B$5,Syn_Lines!$AF$2:$AF$4838,"last_12m",Syn_Lines!$K$2:$K$4838,0)
A16: OTIF rate | B16: =IF(B12>0,B13/B12,"") | C16: =IF(C12>0,C13/C12,"")
A17: PPV vs contract | B17: =IF(B15>0,B14/B15-1,"") | C17: =IF(C15>0,C14/C15-1,"")
A19: Result at the chosen share | B19: Value
A20: Lines moved per year | B20: =B8*B12
A21: Spend moved per year | B21: =B8*B14
A22: Late lines per year - before | B22: =B12*(1-B16)+C12*(1-C16)
A23: Late lines per year - after | B23: =(1-B8)*B12*(1-B16)+(C12+B8*B12)*(1-C16)
A24: Late lines avoided per year | B24: =B22-B23
A25: Modelled late-handling cost avoided | B25: =B24*B9
A26: Modelled price impact (+ costs more) | B26: =B21*((1+C17)/(1+B17)-1)
A27: Net modelled benefit per year | B27: =B25-B26
A28: Assumes the receiving supplier keeps its current OTIF and pricing at higher volume; confirm capacity and contract terms first.
A30: Sensitivity: share moved | B30: Late lines avoided | C30: Cost avoided | D30: Price impact | E30: Net benefit
A31: 0 | B31: =A31*B12*(C16-B16) | C31: =B31*$B$9 | D31: =A31*$B$14*((1+$C$17)/(1+$B$17)-1) | E31: =C31-D31
A32: 0.1 | B32: =A32*B12*(C16-B16) | C32: =B32*$B$9 | D32: =A32*$B$14*((1+$C$17)/(1+$B$17)-1) | E32: =C32-D32
A33: 0.2 | B33: =A33*B12*(C16-B16) | C33: =B33*$B$9 | D33: =A33*$B$14*((1+$C$17)/(1+$B$17)-1) | E33: =C33-D33
A34: 0.3 | B34: =A34*B12*(C16-B16) | C34: =B34*$B$9 | D34: =A34*$B$14*((1+$C$17)/(1+$B$17)-1) | E34: =C34-D34
A35: 0.4 | B35: =A35*B12*(C16-B16) | C35: =B35*$B$9 | D35: =A35*$B$14*((1+$C$17)/(1+$B$17)-1) | E35: =C35-D35
A36: 0.5 | B36: =A36*B12*(C16-B16) | C36: =B36*$B$9 | D36: =A36*$B$14*((1+$C$17)/(1+$B$17)-1) | E36: =C36-D36
A39: B. Late lines avoided if each ranked supplier reached the OTIF target
A40: Supplier | B40: Due lines last 12m | C40: OTIF last 12m | D40: Late lines now | E40: Late lines at target | F40: Late lines avoided | G40: Cost avoided
A41: SUP-01 | B41: =Supplier_Summary!X5 | C41: =IF(Supplier_Summary!Y5="",Supplier_Summary!D5,Supplier_Summary!Y5) | D41: =B41*(1-C41) | E41: =B41*(1-MAX(C41,Assumptions!$C$15)) | F41: =D41-E41 | G41: =F41*Assumptions!$C$43
A42: SUP-04 | B42: =Supplier_Summary!X8 | C42: =IF(Supplier_Summary!Y8="",Supplier_Summary!D8,Supplier_Summary!Y8) | D42: =B42*(1-C42) | E42: =B42*(1-MAX(C42,Assumptions!$C$15)) | F42: =D42-E42 | G42: =F42*Assumptions!$C$43
A43: SUP-07 | B43: =Supplier_Summary!X11 | C43: =IF(Supplier_Summary!Y11="",Supplier_Summary!D11,Supplier_Summary!Y11) | D43: =B43*(1-C43) | E43: =B43*(1-MAX(C43,Assumptions!$C$15)) | F43: =D43-E43 | G43: =F43*Assumptions!$C$43
A44: SUP-12 | B44: =Supplier_Summary!X16 | C44: =IF(Supplier_Summary!Y16="",Supplier_Summary!D16,Supplier_Summary!Y16) | D44: =B44*(1-C44) | E44: =B44*(1-MAX(C44,Assumptions!$C$15)) | F44: =D44-E44 | G44: =F44*Assumptions!$C$43
A45: SUP-10 | B45: =Supplier_Summary!X14 | C45: =IF(Supplier_Summary!Y14="",Supplier_Summary!D14,Supplier_Summary!Y14) | D45: =B45*(1-C45) | E45: =B45*(1-MAX(C45,Assumptions!$C$15)) | F45: =D45-E45 | G45: =F45*Assumptions!$C$43
A46: SUP-08 | B46: =Supplier_Summary!X12 | C46: =IF(Supplier_Summary!Y12="",Supplier_Summary!D12,Supplier_Summary!Y12) | D46: =B46*(1-C46) | E46: =B46*(1-MAX(C46,Assumptions!$C$15)) | F46: =D46-E46 | G46: =F46*Assumptions!$C$43
A47: SUP-14 | B47: =Supplier_Summary!X18 | C47: =IF(Supplier_Summary!Y18="",Supplier_Summary!D18,Supplier_Summary!Y18) | D47: =B47*(1-C47) | E47: =B47*(1-MAX(C47,Assumptions!$C$15)) | F47: =D47-E47 | G47: =F47*Assumptions!$C$43
A48: SUP-05 | B48: =Supplier_Summary!X9 | C48: =IF(Supplier_Summary!Y9="",Supplier_Summary!D9,Supplier_Summary!Y9) | D48: =B48*(1-C48) | E48: =B48*(1-MAX(C48,Assumptions!$C$15)) | F48: =D48-E48 | G48: =F48*Assumptions!$C$43
A49: SUP-02 | B49: =Supplier_Summary!X6 | C49: =IF(Supplier_Summary!Y6="",Supplier_Summary!D6,Supplier_Summary!Y6) | D49: =B49*(1-C49) | E49: =B49*(1-MAX(C49,Assumptions!$C$15)) | F49: =D49-E49 | G49: =F49*Assumptions!$C$43
A50: SUP-11 | B50: =Supplier_Summary!X15 | C50: =IF(Supplier_Summary!Y15="",Supplier_Summary!D15,Supplier_Summary!Y15) | D50: =B50*(1-C50) | E50: =B50*(1-MAX(C50,Assumptions!$C$15)) | F50: =D50-E50 | G50: =F50*Assumptions!$C$43
A51: SUP-06 | B51: =Supplier_Summary!X10 | C51: =IF(Supplier_Summary!Y10="",Supplier_Summary!D10,Supplier_Summary!Y10) | D51: =B51*(1-C51) | E51: =B51*(1-MAX(C51,Assumptions!$C$15)) | F51: =D51-E51 | G51: =F51*Assumptions!$C$43
A52: SUP-09 | B52: =Supplier_Summary!X13 | C52: =IF(Supplier_Summary!Y13="",Supplier_Summary!D13,Supplier_Summary!Y13) | D52: =B52*(1-C52) | E52: =B52*(1-MAX(C52,Assumptions!$C$15)) | F52: =D52-E52 | G52: =F52*Assumptions!$C$43
A54: C. Price harmonisation on like-for-like items (OBSERVED City of Austin prices)
A55: Excess paid above item-year median on flagged lines, FY2022-FY2026 total (pipeline value) | B55: 4764677.9
A57: Capture rate (input) | B57: Modelled opportunity
A58: 0.25 | B58: =A58*$B$55
A59: 0.5 | B59: =A59*$B$55
A60: 1 | B60: =A60*$B$55
A62: Not a savings forecast: price differences may reflect urgency, order size, delivery terms or market timing.

Sheet Austin_Vendors
A1: Vendor spend and concentration
A2: OBSERVED DATA - City of Austin purchase orders (data.austintexas.gov), FY2022-FY2026. Top 150 vendors; the rest aggregated.
A4: Vendor code | B4: Vendor name | C4: Spend (USD) | D4: POs | E4: NIGP classes | F4: Spend on master agreements | G4: Share of total | H4: Cumulative share | I4: Rank | J4: Pareto class | K4: Avg PO value | L4: Agreement share
A5: V8846A96E19 | B5: SILSBEE FORD INC | C5: 85078026 | D5: 211 | E5: 4 | F5: 85036166 | G5: =C5/SUM($C$5:$C$155) | H5: =SUM($C$5:C5)/SUM($C$5:$C$155) | I5: =RANK.EQ(C5,$C$5:$C$154,0) | J5: =IF(H5-G5<0.8,"A",IF(H5-G5<0.95,"B","C")) | K5: =C5/D5 | L5: =IF(C5>0,F5/C5,"")
A6: VA93920ED48 | B6: Pinnacle Petroleum Incorporated | C6: 79789998 | D6: 261 | E6: 1 | F6: 79789998 | G6: =C6/SUM($C$5:$C$155) | H6: =SUM($C$5:C6)/SUM($C$5:$C$155) | I6: =RANK.EQ(C6,$C$5:$C$154,0) | J6: =IF(H6-G6<0.8,"A",IF(H6-G6<0.95,"B","C")) | K6: =C6/D6 | L6: =IF(C6>0,F6/C6,"")
A7: V7347CB5E42 | B7: TECHLINE INC | C7: 59916949 | D7: 619 | E7: 8 | F7: 59550317 | G7: =C7/SUM($C$5:$C$155) | H7: =SUM($C$5:C7)/SUM($C$5:$C$155) | I7: =RANK.EQ(C7,$C$5:$C$154,0) | J7: =IF(H7-G7<0.8,"A",IF(H7-G7<0.95,"B","C")) | K7: =C7/D7 | L7: =IF(C7>0,F7/C7,"")
A8: V598FFF5984 | B8: KBS ELECTRICAL DISTRIBUTORS INC | C8: 53095164 | D8: 377 | E8: 7 | F8: 52470578 | G8: =C8/SUM($C$5:$C$155) | H8: =SUM($C$5:C8)/SUM($C$5:$C$155) | I8: =RANK.EQ(C8,$C$5:$C$154,0) | J8: =IF(H8-G8<0.8,"A",IF(H8-G8<0.95,"B","C")) | K8: =C8/D8 | L8: =IF(C8>0,F8/C8,"")
A9: V5E4248F5E1 | B9: TEXAS ELECTRIC COOPERATIVES | C9: 52670578 | D9: 160 | E9: 1 | F9: 52661578 | G9: =C9/SUM($C$5:$C$155) | H9: =SUM($C$5:C9)/SUM($C$5:$C$155) | I9: =RANK.EQ(C9,$C$5:$C$154,0) | J9: =IF(H9-G9<0.8,"A",IF(H9-G9<0.95,"B","C")) | K9: =C9/D9 | L9: =IF(C9>0,F9/C9,"")
A10: VA263EE8FC7 | B10: MOTOROLA SOLUTIONS INC | C10: 43655133 | D10: 310 | E10: 1 | F10: 43655133 | G10: =C10/SUM($C$5:$C$155) | H10: =SUM($C$5:C10)/SUM($C$5:$C$155) | I10: =RANK.EQ(C10,$C$5:$C$154,0) | J10: =IF(H10-G10<0.8,"A",IF(H10-G10<0.95,"B","C")) | K10: =C10/D10 | L10: =IF(C10>0,F10/C10,"")
A11: V5AD2837BCD | B11: W W GRAINGER INC | C11: 40845493 | D11: 729 | E11: 10 | F11: 40816945 | G11: =C11/SUM($C$5:$C$155) | H11: =SUM($C$5:C11)/SUM($C$5:$C$155) | I11: =RANK.EQ(C11,$C$5:$C$154,0) | J11: =IF(H11-G11<0.8,"A",IF(H11-G11<0.95,"B","C")) | K11: =C11/D11 | L11: =IF(C11>0,F11/C11,"")
A12: V0093315844 | B12: METRO FIRE APPARATUS SPECIALISTS INC | C12: 40244644 | D12: 201 | E12: 8 | F12: 40182819 | G12: =C12/SUM($C$5:$C$155) | H12: =SUM($C$5:C12)/SUM($C$5:$C$155) | I12: =RANK.EQ(C12,$C$5:$C$154,0) | J12: =IF(H12-G12<0.8,"A",IF(H12-G12<0.95,"B","C")) | K12: =C12/D12 | L12: =IF(C12>0,F12/C12,"")
A13: VE85F0A772F | B13: Siddons-Martin Emergency Group, LLC | C13: 35566136 | D13: 32 | E13: 7 | F13: 35526211 | G13: =C13/SUM($C$5:$C$155) | H13: =SUM($C$5:C13)/SUM($C$5:$C$155) | I13: =RANK.EQ(C13,$C$5:$C$154,0) | J13: =IF(H13-G13<0.8,"A",IF(H13-G13<0.95,"B","C")) | K13: =C13/D13 | L13: =IF(C13>0,F13/C13,"")
A14: V0F0A0DF53E | B14: Asphalt Inc LLC | C14: 33407882 | D14: 249 | E14: 1 | F14: 33407882 | G14: =C14/SUM($C$5:$C$155) | H14: =SUM($C$5:C14)/SUM($C$5:$C$155) | I14: =RANK.EQ(C14,$C$5:$C$154,0) | J14: =IF(H14-G14<0.8,"A",IF(H14-G14<0.95,"B","C")) | K14: =C14/D14 | L14: =IF(C14>0,F14/C14,"")
A15: V55771B0254 | B15: DELL MARKETING LP | C15: 29360844 | D15: 1594 | E15: 10 | F15: 29327373 | G15: =C15/SUM($C$5:$C$155) | H15: =SUM($C$5:C15)/SUM($C$5:$C$155) | I15: =RANK.EQ(C15,$C$5:$C$154,0) | J15: =IF(H15-G15<0.8,"A",IF(H15-G15<0.95,"B","C")) | K15: =C15/D15 | L15: =IF(C15>0,F15/C15,"")
A16: V7C6965C402 | B16: Axon Enterprise, Inc. | C16: 28934528 | D16: 29 | E16: 3 | F16: 28902778 | G16: =C16/SUM($C$5:$C$155) | H16: =SUM($C$5:C16)/SUM($C$5:$C$155) | I16: =RANK.EQ(C16,$C$5:$C$154,0) | J16: =IF(H16-G16<0.8,"A",IF(H16-G16<0.95,"B","C")) | K16: =C16/D16 | L16: =IF(C16>0,F16/C16,"")
... A154: VB3F8E10AC5 | B154: ATLANTIC DIVING SUPPLY INC | C154: 1727613.1 | D154: 40 | E154: 3 | F154: 1618499.1 | G154: =C154/SUM($C$5:$C$155) | H154: =SUM($C$5:C154)/SUM($C$5:$C$155) | I154: =RANK.EQ(C154,$C$5:$C$154,0) | J154: =IF(H154-G154<0.8,"A",IF(H154-G154<0.95,"B","C")) | K154: =C154/D154 | L154: =IF(C154>0,F154/C154,"")
A155: ALL_OTHER | B155: All other vendors (1,785) | C155: 2.6360858e+08 | D155: 16999 | F155: 2.1646334e+08 | G155: =C155/SUM($C$5:$C$155) | K155: =C155/D155 | L155: =IF(C155>0,F155/C155,"")
B156: Total | C156: =SUM(C5:C155) | D156: =SUM(D5:D155) | F156: =SUM(F5:F155) | L156: =F156/C156
B158: Top-10 vendor share (formula) | C158: =SUMIFS(G5:G154,I5:I154,"<=10")
B159: Vendors to reach 80% of spend (formula) | C159: =COUNTIFS(J5:J154,"A")
B160: Vendor HHI, all 1,900+ vendors (pipeline value) | C160: 150.5

Sheet Austin_Categories
A1: Category spend and supplier dependency
A2: OBSERVED DATA - City of Austin purchase orders (data.austintexas.gov), FY2022-FY2026. NIGP classes with spend >= $1,000,000.
A3: Thresholds (inputs): | C3: Single-vendor share | D3: 0.9 | E3: HHI highly concentrated | F3: 2500
A5: NIGP class | B5: Class label | C5: Spend family | D5: Spend (USD) | E5: Vendors | F5: Top vendor | G5: Top vendor share | H5: Top vendor orders | I5: HHI | J5: Standalone spend (no master agreement) | K5: Share of total | L5: Spend rank | M5: Dependency flag | N5: Agreement coverage
A6: 070 | B6: 070 Automotive Vehicles and Transport Equip (including Trailers) | C6: Fleet vehicles, parts & tires | D6: 2.8750038e+08 | E6: 47 | F6: SILSBEE FORD INC | G6: 0.29587665 | H6: 208 | I6: 1420.9 | J6: 605058.93 | K6: =D6/Austin_Vendors!$C$156 | L6: =RANK.EQ(D6,$D$6:$D$84,0) | M6: =IF(G6>=$D$3,"R1 single-vendor",IF(I6>=$F$3,"R2 highly concentrated","")) | N6: =1-J6/D6
A7: 285 | B7: 285 Electrical Equipment and Supplies (except Cable and Wire) | C7: Electrical & utility equipment | D7: 2.6024914e+08 | E7: 118 | F7: TEXAS ELECTRIC COOPERATIVES | G7: 0.20238521 | H7: 160 | I7: 1344 | J7: 2227108 | K7: =D7/Austin_Vendors!$C$156 | L7: =RANK.EQ(D7,$D$6:$D$84,0) | M7: =IF(G7>=$D$3,"R1 single-vendor",IF(I7>=$F$3,"R2 highly concentrated","")) | N7: =1-J7/D7
A8: 405 | B8: 405 Fuel, Oil, Grease and Lubricants | C8: Fuel & lubricants | D8: 86487319 | E8: 14 | F8: Pinnacle Petroleum Incorporated | G8: 0.92256297 | H8: 261 | I8: 8525 | J8: 42269.41 | K8: =D8/Austin_Vendors!$C$156 | L8: =RANK.EQ(D8,$D$6:$D$84,0) | M8: =IF(G8>=$D$3,"R1 single-vendor",IF(I8>=$F$3,"R2 highly concentrated","")) | N8: =1-J8/D8
A9: 885 | B9: 885 Ferric Sulfate (feso4) | C9: Water & wastewater treatment | D9: 66313010 | E9: 35 | F9: LHOIST NORTH AMERICA OF TEXAS, LLC | G9: 0.29700272 | H9: 60 | I9: 1391.1 | J9: 4296035.9 | K9: =D9/Austin_Vendors!$C$156 | L9: =RANK.EQ(D9,$D$6:$D$84,0) | M9: =IF(G9>=$D$3,"R1 single-vendor",IF(I9>=$F$3,"R2 highly concentrated","")) | N9: =1-J9/D9
A10: 725 | B10: 725 Radio Communication, Telephone, and Telecommunicat | C10: Radio, telecom & video | D10: 62672625 | E10: 65 | F10: MOTOROLA SOLUTIONS INC | G10: 0.69655824 | H10: 310 | I10: 5223.9 | J10: 597977.62 | K10: =D10/Austin_Vendors!$C$156 | L10: =RANK.EQ(D10,$D$6:$D$84,0) | M10: =IF(G10>=$D$3,"R1 single-vendor",IF(I10>=$F$3,"R2 highly concentrated","")) | N10: =1-J10/D10
A11: 204 | B11: 204 Computer Hardware and Peripherals for Microcompute | C11: IT hardware & software | D11: 59785094 | E11: 82 | F11: DELL MARKETING LP | G11: 0.28887038 | H11: 870 | I11: 1873.8 | J11: 2164563.2 | K11: =D11/Austin_Vendors!$C$156 | L11: =RANK.EQ(D11,$D$6:$D$84,0) | M11: =IF(G11>=$D$3,"R1 single-vendor",IF(I11>=$F$3,"R2 highly concentrated","")) | N11: =1-J11/D11
A12: 208 | B12: 208 Computer Software for Microcomputers (preprogrammed) | C12: IT hardware & software | D12: 55796623 | E12: 151 | F12: OverDrive, Inc. | G12: 0.13002431 | H12: 9 | I12: 564.4 | J12: 1273951.7 | K12: =D12/Austin_Vendors!$C$156 | L12: =RANK.EQ(D12,$D$6:$D$84,0) | M12: =IF(G12>=$D$3,"R1 single-vendor",IF(I12>=$F$3,"R2 highly concentrated","")) | N12: =1-J12/D12
A13: 890 | B13: 890 Water Supply, Groundwater, Sewage Treatment, Related Equip | C13: Water & wastewater treatment | D13: 52811646 | E13: 93 | F13: Ferguson US Holdings, Inc | G13: 0.23277594 | H13: 160 | I13: 1138.7 | J13: 6634408.4 | K13: =D13/Austin_Vendors!$C$156 | L13: =RANK.EQ(D13,$D$6:$D$84,0) | M13: =IF(G13>=$D$3,"R1 single-vendor",IF(I13>=$F$3,"R2 highly concentrated","")) | N13: =1-J13/D13
A14: 545 | B14: 545 Impact Tools, Air Powered (not Road Building) | C14: Heavy equipment & tools | D14: 51790624 | E14: 32 | F14: W W GRAINGER INC | G14: 0.62806084 | H14: 686 | I14: 4440.8 | J14: 3737679.2 | K14: =D14/Austin_Vendors!$C$156 | L14: =RANK.EQ(D14,$D$6:$D$84,0) | M14: =IF(G14>=$D$3,"R1 single-vendor",IF(I14>=$F$3,"R2 highly concentrated","")) | N14: =1-J14/D14
A15: 206 | B15: 206 Computer Hardware / Peripherals for Mini/mainframe Computers | C15: IT hardware & software | D15: 42185564 | E15: 46 | F15: CONTROL PANELS USA INC | G15: 0.2371316 | H15: 45 | I15: 1470.5 | J15: 7217391.9 | K15: =D15/Austin_Vendors!$C$156 | L15: =RANK.EQ(D15,$D$6:$D$84,0) | M15: =IF(G15>=$D$3,"R1 single-vendor",IF(I15>=$F$3,"R2 highly concentrated","")) | N15: =1-J15/D15
A16: 655 | B16: 655 Photo Equip - Film and Supplies | C16: Radio, telecom & video | D16: 41904762 | E16: 20 | F16: Axon Enterprise, Inc. | G16: 0.56881597 | H16: 19 | I16: 3527 | J16: 181641.46 | K16: =D16/Austin_Vendors!$C$156 | L16: =RANK.EQ(D16,$D$6:$D$84,0) | M16: =IF(G16>=$D$3,"R1 single-vendor",IF(I16>=$F$3,"R2 highly concentrated","")) | N16: =1-J16/D16
A17: 745 | B17: 745 Asphaltic Concrete, Hot Mix, in Accordance with It | C17: Road & construction materials | D17: 41641930 | E17: 7 | F17: Asphalt Inc LLC | G17: 0.80226544 | H17: 249 | I17: 6820.2 | J17: 48296.5 | K17: =D17/Austin_Vendors!$C$156 | L17: =RANK.EQ(D17,$D$6:$D$84,0) | M17: =IF(G17>=$D$3,"R1 single-vendor",IF(I17>=$F$3,"R2 highly concentrated","")) | N17: =1-J17/D17
... A84: 625 | B84: 625 Optical Equipment, Accessories, and Supplies | C84: Other goods | D84: 1016913 | E84: 9 | F84: Echo Healthcare, Inc. | G84: 0.78008643 | H84: 1 | I84: 6223.8 | J84: 1016913 | K84: =D84/Austin_Vendors!$C$156 | L84: =RANK.EQ(D84,$D$6:$D$84,0) | M84: =IF(G84>=$D$3,"R1 single-vendor",IF(I84>=$F$3,"R2 highly concentrated","")) | N84: =1-J84/D84
B86: Summary (formulas)
B87: Categories screened | D87: =COUNTA(A6:A84)
B88: R1 single-vendor categories | D88: =COUNTIF(M6:M84,"R1*")
B89: R2 highly concentrated categories | D89: =COUNTIF(M6:M84,"R2*")
B90: Spend in R1 categories | D90: =SUMIFS(D6:D84,M6:M84,"R1*")
B91: Largest category share held by one vendor | D91: =MAXIFS(G6:G84,D6:D84,">="&10000000)

Sheet Austin_Families
A1: Spend by family and fiscal year
A2: OBSERVED DATA - City of Austin purchase orders (data.austintexas.gov), FY2022-FY2026. Families are an analyst grouping of NIGP classes.
A4: Spend family | B4: FY2022 | C4: FY2023 | D4: FY2024 | E4: FY2025 | F4: FY2026 | G4: Total | H4: Share | I4: Change FY2022-FY2026
A5: Fleet vehicles, parts & tires | B5: 60021614 | C5: 64150870 | D5: 79814944 | E5: 66571900 | F5: 68028588 | G5: =SUM(B5:F5) | H5: =G5/SUM($G$5:$G$18) | I5: =IF(B5>0,F5/B5-1,"")
A6: Electrical & utility equipment | B6: 42258824 | C6: 72122995 | D6: 43468580 | E6: 49610568 | F6: 65038341 | G6: =SUM(B6:F6) | H6: =G6/SUM($G$5:$G$18) | I6: =IF(B6>0,F6/B6-1,"")
